Workbook

Sheet Detailed Budget
B2: 165 RANDOLPH STREET
B3: DETAILED DEVELOPMENT BUDGET — V2, DILIGENCE REVIEWED
B4: Brooklyn NY 11237 · Developer: owner’s team · Co-pro: Live Nation / Insomniac · Landlord: Eric Cohen · CONSTRUCTION CAPEX ONLY · CONFIDENTIAL
B6: Building SF | E6: 74100 | G6: THE basis. Mezzanine adds capacity inside this envelope, not area. Alleys carry no cost.
B7: Theatre seat rate ($/seat) | E7: 25 | G7: TOGGLE: 25 = MT sourcing, 125 = as filed in the dev budget. Drives the removable seating line in division 600.
B8: Mezzanine SF | E8: 14000 | G8: Inside the 74,100. Derived from the Wake test-fit occupancy loads.
B9: Perimeter LF | E9: 1089 | G9: Approximated as square. Replace with the survey.
B10: New wall band SF | E10: 32670 | G10: 1,089 LF perimeter x 30 ft lift.
B11: Capacity | E11: 7440 | G11: Wake PD04 Rev 4.4.
B12: General conditions basis | E12: 1 | G12: TOGGLE: 1 = the 11% percentage. 0 = Thomas’s own 013000 + 015800 line items ($1,696,000) instead. NEVER BOTH — they are the same site cost.
B13: Kitchen scope (0 / 1 / 2) | E13: 1 | G13: TOGGLE for division 800. 0 = concessions only, no kitchen. 1 = warming / finishing kitchen. 2 = full production kitchen with a grease hood. Each level includes the one below it.
B15: Item | C15: Qty | D15: Unit | E15: Rate | F15: Amount | G15: Rate source / basis
B16: 000 SITE & ENABLING
B17: Sidewalk shed / bridge
B18: Sidewalk shed, erect & dismantle | C18: 1089 | D18: LF | E18: 210 | F18: =C18*E18 | G18: NYC shed ~$180-240/LF erected
B19: Shed rental, 24 months | C19: 26136 | D19: LF-mo | E19: 22 | F19: =C19*E19 | G19: SCHEDULE-DRIVEN. Rented monthly — every month of programme costs $23,958. Reduced from 30 to 24 months; confirm against the real construction schedule
B20: DOT permit & renewals | C20: 1 | D20: LS | E20: 45000 | F20: =C20*E20 | G20: Sidewalk shed permit, renewed periodically
B21: Lighting & signage on shed | C21: 1089 | D21: LF | E21: 18 | F21: =C21*E21 | G21: Required by DOT
B22: Netting & debris containment | C22: 32670 | D22: SF | E22: 1.1 | F22: =C22*E22 | G22: Facade protection during the lift
B23: Sidewalk shed / bridge — subtotal | F23: =SUM(F18:F22)
B24: Interior protection & containment
B25: Slab protection, hardboard & poly | C25: 74100 | D25: SF | E25: 1.35 | F25: =C25*E25 | G25: Protecting the existing slab
B26: Dust partitions & negative air | C26: 1 | D26: LS | E26: 65000 | F26: =C26*E26 | G26: Containment during demo and abatement
B27: Protection of retained equipment | C27: 1 | D27: LS | E27: 22000 | F27: =C27*E27
B28: Interior protection & containment — subtotal | F28: =SUM(F25:F27)
B29: Temporary weather protection
B30: Temporary roof membrane at open areas | C30: 18525 | D30: SF | E30: 8.5 | F30: =C30*E30 | G30: Only ~25% of roof open at any stage on a lift
B31: Perimeter tarping at the lift band | C31: 32670 | D31: SF | E31: 3.2 | F31: =C31*E31
B32: Temporary heat & dehumidification | C32: 1 | D32: LS | E32: 85000 | F32: =C32*E32 | G32: Winter work
B33: Temporary weather protection — subtotal | F33: =SUM(F30:F32)
B34: Asbestos / hazmat abatement
B35: ACP-5 / ACP-7 filing & asbestos investigator | C35: 1 | D35: LS | E35: 45000 | F35: =C35*E35 | G35: NYC required on a 1948 building
B36: Roofing felt & mastic abatement | C36: 74100 | D36: SF | E36: 7.5 | F36: =C36*E36 | G36: SURVEY-DEPENDENT. PRESUMED ACM on a 1948 precast roof — nobody has sampled it. If the roof is clean this line goes to near zero. Get the ACP-5 survey done early; it is worth $555,750
B37: Pipe & boiler insulation abatement | C37: 1 | D37: LS | E37: 120000 | F37: =C37*E37 | G37: Dev budget notes a 5,250 MBH boiler and steam piping
B38: Lead paint abatement at steel | C38: 1 | D38: LS | E38: 95000 | F38: =C38*E38
B39: Air monitoring & clearance | C39: 1 | D39: LS | E39: 55000 | F39: =C39*E39
B40: Hazmat disposal & manifesting | C40: 1 | D40: LS | E40: 130000 | F40: =C40*E40
B41: Asbestos / hazmat abatement — subtotal | F41: =SUM(F35:F40)
B42: Demolition — interior
B43: Demo masonry walls at new entry/lobby | C43: 2500 | D43: SF | E43: 12 | F43: =C43*E43 | G43: Dev budget 024100-1 rate & qty
B44: Demo 8in CMU wall, 20ft tall | C44: 1975 | D44: SF | E44: 14 | F44: =C44*E44 | G44: Dev budget qty, unpriced
B45: Demo existing roll-up doors | C45: 8 | D45: EA | E45: 1850 | F45: =C45*E45 | G45: Dev budget qty
B46: Demo existing exterior doors | C46: 7 | D46: EA | E46: 650 | F46: =C46*E46 | G46: Dev budget qty
B47: Demo windows 1ft x 10ft | C47: 34 | D47: EA | E47: 12 | F47: =C47*E47 | G47: Dev budget 024100 rate & qty
B48: Demo ceiling-mount steam heaters & piping | C48: 28 | D48: EA | E48: 1400 | F48: =C48*E48 | G48: Dev budget qty
B49: Demo 5,250 MBH boiler & piping (15x6x7, 13,000 lb) | C49: 2 | D49: EA | E49: 28000 | F49: =C49*E49 | G49: Dev budget qty. Rigging-out is the cost
B50: Demo (5) steel columns | C50: 5 | D50: EA | E50: 9500 | F50: =C50*E50 | G50: Dev budget qty
B51: Caesarstone plant equipment removal & slurry pit remediation | C51: 1 | D51: LS | E51: 185000 | F51: =C51*E51 | G51: Countertop manufacturing leaves silica and resin residue
B52: Misc build-out demo, piping, CMU, partitions | C52: 25935 | D52: SF | E52: 2 | F52: =C52*E52 | G52: Dev budget 024100-2 rate
B53: Floor trenching for MEP | C53: 1 | D53: LS | E53: 50000 | F53: =C53*E53 | G53: Dev budget 024100-5
B54: Debris removal & dumpsters | C54: 1 | D54: LS | E54: 95000 | F54: =C54*E54
B55: Demolition — interior — subtotal | F55: =SUM(F43:F54)
B56: Sitework
B57: New sidewalks around building | C57: 1 | D57: LS | E57: 40000 | F57: =C57*E57 | G57: Dev budget 320000-1
B58: Curb cuts & DOT restoration | C58: 1 | D58: LS | E58: 35000 | F58: =C58*E58
B59: Site drainage tie-ins | C59: 1 | D59: LS | E59: 15000 | F59: =C59*E59
B60: Sitework — subtotal | F60: =SUM(F57:F59)
B61: 000 — DIVISION TOTAL | F61: =F23+F28+F33+F41+F55+F60
B63: 100 ROOF LIFT — mandatory, this is the moat
B64: Roof lift contract — YOUR QUOTE
B65: Separation of roof from perimeter walls | C65: 1089 | D65: LF | E65: 0 | F65: =C65*E65 | G65: IN the quote
B66: Hydraulic jacking: towers, sequencing, survey control | C66: 1 | D66: LS | E66: 0 | F66: =C66*E66 | G66: IN the quote
B67: Column extensions spliced to existing columns | C67: 1 | D67: LS | E67: 0 | F67: =C67*E67 | G67: IN the quote
B68: Permanent lateral bracing | C68: 1 | D68: LS | E68: 0 | F68: =C68*E68 | G68: IN the quote
B69: External metal siding enclosure at new band | C69: 32670 | D69: SF | E69: 0 | F69: =C69*E69 | G69: IN the quote
B70: Structural drawings & GC coordination | C70: 1 | D70: LS | E70: 0 | F70: =C70*E70 | G70: IN the quote
B71: ROOF LIFT CONTRACT — lump | C71: 1 | D71: LS | E71: 3500000 | F71: =C71*E71 | G71: YOUR QUOTE (Eric), midpoint of $3-4M. Sub-lines above show what it buys
B72: Roof lift contract — YOUR QUOTE — subtotal | F72: =SUM(F65:F71)
B73: Foundations for the new load path — ASK if in quote
B74: New column footings | C74: 40 | D74: EA | E74: 7500 | F74: =C74*E74 | G74: Dev budget 033000-3, QTY 0
B75: Excavation at new columns | C75: 74100 | D75: SF | E75: 6.5 | F75: =C75*E75 | G75: Dev budget 033000-1, QTY 0
B76: Underpinning at existing footings | C76: 24 | D76: EA | E76: 9500 | F76: =C76*E76 | G76: Existing footings take added load from the taller columns
B77: Rebar & dowelling into existing slab | C77: 1 | D77: LS | E77: 78000 | F77: =C77*E77
B78: Foundations for the new load path — ASK if in quote — subtotal | F78: =SUM(F74:F77)
B79: Roof-to-wall closure — ASK if in quote
B80: Closure flashing at new roof/wall joint | C80: 1089 | D80: LF | E80: 145 | F80: =C80*E80 | G80: The new joint the lift creates
B81: Air & vapour barrier continuity | C81: 1089 | D81: LF | E81: 42 | F81: =C81*E81
B82: Sealants & terminations | C82: 1 | D82: LS | E82: 38000 | F82: =C82*E82
B83: Roof-to-wall closure — ASK if in quote — subtotal | F83: =SUM(F80:F82)
B84: Envelope completion at the new band
B85: Insulation to energy code | C85: 32670 | D85: SF | E85: 8 | F85: =C85*E85 | G85: NYC energy code at the new wall area
B86: Girts & secondary framing behind siding | C86: 32670 | D86: SF | E86: 4.5 | F86: =C86*E86 | G86: If not in the lifter's siding scope — ASK
B87: Interior liner panel / furring | C87: 32670 | D87: SF | E87: 6 | F87: =C87*E87
B88: Envelope completion at the new band — subtotal | F88: =SUM(F85:F87)
B89: Roof reinstatement
B90: Roof repair & flashing where disturbed | C90: 74100 | D90: SF | E90: 6 | F90: =C90*E90 | G90: NOT a re-roof — the membrane rises with the roof
B91: New roof drains & leaders at raised level | C91: 18 | D91: EA | E91: 8500 | F91: =C91*E91 | G91: Dev budget 220000-16 rate
B92: Roof dunnage for HVAC equipment | C92: 8 | D92: LOC | E92: 20000 | F92: =C92*E92 | G92: Dev budget 055100-8 rate, QTY 0
B93: Roof penetrations framing for exhaust | C93: 1 | D93: LS | E93: 25000 | F93: =C93*E93 | G93: Dev budget 055100-9, QTY 0
B94: Roof reinstatement — subtotal | F94: =SUM(F90:F93)
B95: Fireproofing on new steel
B96: Spray-applied fireproofing, new columns & bracing | C96: 1 | D96: LS | E96: 180000 | F96: =C96*E96 | G96: NYC-required in assembly occupancy. New steel only
B97: Fireproofing on new steel — subtotal | F97: =SUM(F96:F96)
B98: MEP disconnect & reinstatement
B99: Disconnect electrical, mechanical, sprinkler at roof line | C99: 1 | D99: LS | E99: 200000 | F99: =C99*E99 | G99: EXCLUDED by the lifter
B100: Reconnect & extend electrical risers to new height | C100: 1 | D100: LS | E100: 165000 | F100: =C100*E100 | G100: EXCLUDED by the lifter
B101: Extend sprinkler mains & drops to new height | C101: 1 | D101: LS | E101: 125000 | F101: =C101*E101
B102: Extend mechanical ductwork & piping | C102: 1 | D102: LS | E102: 60000 | F102: =C102*E102
B103: MEP disconnect & reinstatement — subtotal | F103: =SUM(F99:F102)
B104: Fire separation
...

Sheet Diligence Review
B2: DILIGENCE REVIEW
B3: The 165 Randolph diligence folder, 26 files, uploaded 10 September 2026 — read against this budget.
B5: THE HEADLINE. Two files in the folder are readable cost documents, and they are the best third-party evidence in the whole exercise: Schimenti Construction’s conceptual budgets for 555 Johnson Avenue, addressed to Eric Cohen at EBC Capital. Our own landlord, the next block over, open-shop labour, priced by a real NYC general contractor. That gives us actual percentages to hold our estimator against instead of my benchmarks. It moved general conditions from 11% to 8.5%. Everything else in the folder is a scanned drawing, a CAD plot or a custom-font PDF with no recoverable text — the inventory at the bottom says which is which, and which unread files are worth someone opening by hand.
B7: FINDINGS
B8: Finding | C8: What the diligence says | D8: What we carried | E8: So what | F8: Action
B9: GENERAL CONDITIONS IS THE ONE HARD NUMBER WE NOW HAVE | C9: Schimenti priced general conditions at $2,198,000 on a $28,165,000 construction subtotal = 7.80% on the full 555 Johnson scheme, and $989,100 on $11,110,174 = 8.90% on the partial-reuse option. Both open shop, both for Eric Cohen, both in this submarket. | D9: 11.0%, which was my own benchmark rather than a quote. | E9: Two real data points from our own landlord's general contractor average 8.35%. My 11% was too high. Changed to 8.5%. | F9: APPLIED — rate moved from 11% to 8.5%. Worth $954,153 at the current trade cost. Push the estimator to justify anything above 8.5% with a staffing chart and a duration, not a percentage.
B10: OVERHEAD, PROFIT & INSURANCE IS ABOUT RIGHT — DO NOT CUT IT | C10: Schimenti's insurance/fees/bonds line is 7.11% (full) and 8.98% (partial reuse). CRITICALLY, both lines say 'Construction Contingency — Excluded' and 'Builder's Risk Insurance — Excluded'. | D10: 9.0%, described as including insurance. | E10: Comparing like with like, 9% including builder's risk against ~8% excluding it is consistent. This rate is NOT the soft one. The soft one was general conditions. | F10: NO CHANGE. Stop arguing about this line and spend the leverage on general conditions and the roof.
B11: CONTINGENCY BELONGS TO YOU, NOT THE CONTRACTOR — CONFIRMED | C11: Schimenti explicitly EXCLUDES construction contingency from both budgets. | D11: One $5,000,000 owner-held contingency below the line. | E11: A real NYC GC pricing for your own landlord excluded contractor contingency entirely. The restructure you asked for matches how this market actually quotes. | F11: NO CHANGE — this validates the structure. If our estimator insists on a 10% contractor contingency he holds and keeps, ask him why Schimenti didn't.
B12: THE 135,953 SF ERROR HAS A TRACEABLE ORIGIN | C12: 555 Johnson is ~135,000 SF: $28,165,000 divided by $208.63/SF = 134,993 SF. | D12: Thomas's Master Development Budget header states SF: 135,953. The building is 74,100 SF. | E12: The wrong area almost certainly came across from the 555 Johnson job. It is not a typo, it is a template carried over from a different building on the next block. | F12: ASK. This makes the correction much easier to land: you are not telling him he cannot count, you are showing him which file it came from. Every SF-driven line in his schedule needs re-running at 74,100.
B13: OPEN SHOP IS THE NORM ON ERIC'S PROJECTS | C13: Schimenti qualification 1.1: 'Labor Type — Open Shop'. Work hours 7am-3:30pm, single shift. A NYC licensed superintendent is required. | D13: The Rooflifters 2022 rate card, whose union status we flagged as unknown. | E13: Open shop is what got priced across the street. It supports non-union pricing as the base case and it means the Rooflifters card is probably the right basis, not a low one. | F13: ASK Rooflifters to confirm open shop, and hold the estimator to a single-shift 7am-3:30pm assumption unless he is pricing overtime for a reason he can name.
B14: THE CONSTRUCTION WINDOW COMP IS 60 WEEKS, NOT 24 MONTHS | C14: Schimenti: '70 week active project schedule and 60 weeks of construction.' Their timeline runs design kick-off Feb 2019 to TCO Feb 2021, with foundation 2 months, core and shell 6-8 months, interior fit 4 months. | D14: 24 months of sidewalk shed rental at $23,958/month. | E14: 60 weeks is 13.8 months of construction. Our roof lift genuinely extends the programme beyond their case, so I have NOT cut the duration — but 24 months now needs defending against a real comp rather than being assumed. | F14: VERIFY with the estimator. Every month you take out of the programme is $23,958 of shed alone, before general conditions. An 18-month shed saves $143,748.
B15: MEP IS 3.4x THE COMP AND THAT IS THE SECOND-BIGGEST QUESTION AFTER THE ROOF | C15: 555 Johnson mechanical + electrical = $31.54 + $24.15 = $55.69/SF. Elevators $3.16/SF. | D15: Our division 500 excluding conveying is $191.58/SF. Conveying at $4.05/SF is a near-perfect match to their $3.16. | E15: The elevator match tells us the comparison is meaningful. A 7,440-occupant assembly venue legitimately carries far more MEP than production studios — ventilation alone for 7,440 people is 110,000-150,000 CFM, and body heat is over 300 tons before a single fixture. But 3.4x is a big number to accept on trust, and it is the same doubt as the HVAC basis question. | F15: ASK. This is now the strongest reason to get a written answer on whether HVAC was priced on a load calculation or a rate per square foot.
B16: RENOVATION AND FIT-OUT OF AN EXISTING BUILDING NEARBY RAN $120-135/SF | C16: Schimenti's partial-reuse option prices Lots 25 & 37 renovation and fit-out at $2,760,000 over 23,000 SF = $120/SF, and Lot 42 at $4,050,000 over 30,000 SF = $135/SF. | D16: Not directly comparable — those are light industrial and office fit-outs, not an 8,000-cap venue. | E16: Useful as a floor, not a target. It tells you what ordinary warehouse conversion costs on this block, so any line in our budget that is just ordinary construction should sit near that band. | F16: Use it to sanity-check the non-venue-specific parts: BOH, offices, circulation, restroom blocks.
B17: GEOTECHNICAL WORK BEFORE FOUNDATION PRICING — THEIR FIRST RECOMMENDATION | C17: Schimenti's recommended next steps lead with: 'Conduct a GeoTechnical Survey of Existing Soil Conditions, Probes and Test Pits. Better information on the existing conditions will allow a targeted foundation and sub grade approach.' Their timeline puts test pits and additional borings before CDs are issued for foundations. | D17: $150,000 for 13 borings 50 ft deep, plus $85,000 existing-conditions survey and scan. | E17: We carry borings but not test pits and probes as a separate item, and their sequencing point is the real one: the survey comes BEFORE foundation pricing, not alongside it. | F17: SEQUENCE IT FIRST. This is also the strongest single argument for holding the $5,000,000 contingency: their own GC says foundation cost is unknowable until this is done.
B18: ADD ALTERNATE PRICING EXISTS FOR ADDING A FLOOR — RELEVANT TO THE BALCONY QUESTION | C18: Schimenti priced 'Add 1 Floor to Lot 25 & 37' at $9,450,000, noted as reinforce plus core and shell. | D18: Thomas carries steel framing at an upper balcony at QTY 0 — a third level that is not in our model at all. | E18: Adding a floor to an existing building is a nine-figure-per-acre proposition, not a line item. It is a reminder that the upper balcony is a scope decision with real money behind it, not a detail. | F18: DECIDE. If the test fit keeps a balcony above the mezzanine, it needs pricing as a structural addition — new steel, new egress, new sprinkler, new seating.
B19: ACOUSTIC WALLS APPEAR AS THEIR OWN DIVISION IN THE PRODUCTION STUDIO BUDGET | C19: The Production Studios budget carries 'Acoustic Walls' as a top-level trade line alongside Concrete, Masonry and Metals. | D19: Acoustic treatment is grouped under division 400 as a licence-to-operate item. | E19: Confirms that acoustic scope is treated as a major trade on this kind of building rather than a finish, which is how we treat it. | F19: NO CHANGE — but the Acoustical Data.pdf in this folder is a scanned document nobody has read. It may contain the actual STC targets, which would let us price the treatment instead of allowing for it.
B22: THE COMP — SCHIMENTI CONSTRUCTION, 555 JOHNSON AVENUE, FOR ERIC COHEN / EBC CAPITAL
B23: Full scheme 8 Jan 2019 over ~135,000 SF, and the partial site re-use option 11 Jan 2019. Note that 555 Johnson is ~135,000 SF — which is almost certainly where the 135,953 SF in Thomas’s header came from.
B24: Division | C24: Full scheme | D24: $/SF | E24: Partial re-use | F24: $/SF
B25: 2-000 Existing conditions | C25: 3128000 | D25: 23.17 | E25: 1525000 | F25: 25
B26: 3-000 Concrete / precast | C26: 6973000 | D26: 51.65 | E26: 2078519 | F26: 34.07
B27: 4-000 Masonry | C27: 3996000 | D27: 29.6 | E27: 765000 | F27: 12.54
B28: 5-000 Steel | C28: 2105000 | D28: 15.59 | E28: 1905000 | F28: 31.23
B29: 6-000 Wood & plastics | C29: 168000 | D29: 1.24 | E29: 77156 | F29: 1.26
B30: 7-000 Thermal, moisture & fireproofing | C30: 3062000 | D30: 22.68 | E30: 1860000 | F30: 30.49
B31: 8-000 Doors & windows | C31: 460000 | D31: 3.41 | E31: 36000 | F31: 0.59
B32: 9-000 Finishes | C32: 303000 | D32: 2.24 | E32: 108500 | F32: 1.78
B33: 10-000 Specialties | C33: 25000 | D33: 0.19 | E33: 25000 | F33: 0.41
B34: 14-000 Elevators & lifts | C34: 427000 | D34: 3.16 | E34: 0 | F34: 0
B35: 15-000 Mechanical (FP + plumbing + HVAC) | C35: 4258000 | D35: 31.54 | E35: 1200000 | F35: 19.67
B36: 16-000 Electrical (service, power, alarm) | C36: 3260000 | D36: 24.15 | E36: 1530000 | F36: 25.08
... B42: GRAND TOTAL | C42: 40979000 | D42: 303.55 | E42: 24055464 | F42: 178.19
B44: General conditions as % of construction subtotal | C44: 7.80% | E44: 8.90%
B45: Insurance, fees & bonds as % of construction subtotal | C45: 7.11% | E45: 8.98%
B46: Construction contingency | C46: EXCLUDED | E46: EXCLUDED
B47: Builder’s risk insurance | C47: EXCLUDED | E47: EXCLUDED
B48: Labour basis | C48: Open shop, 7am-3:30pm single shift | E48: Open shop
B49: Construction duration | C49: 60 weeks of construction, 70-week active programme | E49: same
B52: WORTH SOMEONE OPENING BY HAND — SCANNED, NO TEXT CAME OUT
B53: 537 Johnson Av_Assessment of Work (09.14.16).pdf | C53: A structural assessment of an existing building on the same block. This is the closest thing to a roof-lift precedent in the folder and it is scanned, so no text came out. Reading it could confirm or kill the whole lift approach.
B54: 50 Kip and 65 Kip Pile Cap Adequacy Check (03.22.17).pdf | C54: Foundation capacity calculations. These bear on two live numbers: the roof-lift load path ($1.33M of swing on whether footings are inside the Rooflifters quote) and the rigging-grid footings we priced at $8,500 each.
B55: 537 Johnson Av_Draft Recommended Means & Methods (03.22.17).pdf | C55: How the structural work was sequenced. Relevant to whether the grid can be erected through the open roof.
B56: Acoustical Data.pdf | C56: Would let us price acoustic treatment to a target instead of carrying an allowance.
B57: 180730- Production Studio CM Services.pdf | C57: Almost certainly the CM fee structure. Would settle the general-conditions and fee argument outright rather than by comparison.
B58: 198 Randolph Street_Alt.2 and the two .dwg files | C58: 198 Randolph is the smaller sibling building. The DWGs need CAD software this container does not have.
B61: FULL FILE INVENTORY
B62: File | C62: Status | D62: What it is
B63: 555 Johnson Ave_Conceptual Summary_190108.pdf | C63: READ | D63: Schimenti Construction to Eric Cohen, EBC Capital, 8 Jan 2019. Full conceptual budget by CSI division with $/SF, project timeline, and qualifications. THE most useful document in the folder.
B64: 555 Johnson Avenu_Conceptual Analysis_R1 Partial Reuse.pdf | C64: READ | D64: Schimenti, 11 Jan 2019. The PARTIAL SITE RE-USE option — keep existing buildings rather than demolish. The direct analogue to what we are doing at 165 Randolph.
B65: 555 Johnson Ave_Conceptual Summary_190108(1).pdf | C65: DUPLICATE | D65: Byte-identical to the file above.
B66: 555 Johnson Avenu_Conceptual Analysis_R1 Partial Reuse(1).pdf | C66: DUPLICATE | D66: Byte-identical to the partial-reuse file above.
B67: 180730- Production Studios Budget .pdf | C67: PARTIAL | D67: A three-column budget (three scheme sizes) with CSI row labels. The row labels decode — General Requirements, Sitework, Concrete, Masonry, Metals, Carpentry, Thermal & Moisture Protection, Doors & Windows, Finishes, ACOUSTIC WALLS, Equipment, Furnishings, HVAC, Plumbing, Sprinkler, Electrical — but the amounts use a custom font encoding that does not decode reliably. DO NOT quote figures from this file until someone opens it and reads them out.
B68: 180730- Production Studio CM Services.pdf | C68: NO TEXT | D68: Custom font encoding, no recoverable text. Likely the CM fee structure — worth reading manually, it would settle the general-conditions and fee argument outright.
B69: 537 Johnson Av_Assessment of Work (09.14.16).pdf | C69: NO TEXT | D69: Scanned. THE ROOF-LIFT PRECEDENT — a structural assessment of an existing building on the same block. Highest-value unread document.
B70: 537 Johnson Av_Draft Recommended Means & Methods (03.22.17).pdf | C70: NO TEXT | D70: Scanned. Means and methods for the structural work. Directly relevant to how the lift gets sequenced.
B71: 537 Johnson Av_Proposed Structural Plans (03.22.17).pdf | C71: NO TEXT | D71: Vector CAD plot.
B72: 537 Johnson Av_Proposed Conditions+Take off (05.12.17).pdf | C72: NO TEXT | D72: Vector CAD plot. A TAKE-OFF — quantities we could compare against.
B73: 537-561 Johnson Av_Progress Structural Plans (01.19.17).pdf | C73: NO TEXT | D73: Vector CAD plot.
... B85: 20170523 Covered.jpg / 20170523 Roof Soccer Night.jpg | C85: IMAGE | D85: Photographs of a covered roof and a rooftop pitch at night.

Sheet Markups Explained
B2: THE MARKUPS, EXPLAINED
B3: What each one is, who gets it, whether it is necessary, and what is actually negotiable.
B5: RESTRUCTURED. Trade cost now stands alone at $37.5M and everything else sits BELOW THE LINE as a separate cost. The three markup rates are each applied to trade cost only — they no longer compound on each other. Contractor contingency and owner contingency have been replaced by ONE $5.0M contingency, so no contingency is charged twice. A dollar of trade scope removed now saves $1.30.
B7: Line | C7: Carried | D7: Target | E7: What it is / who gets it / is it necessary | F7: What is actually negotiable
B8: Escalation | C8: 10% | D8: 6-8% | E8: WHAT IT IS: A reserve for the fact that steel, copper, switchgear and labour cost more on the day you BUY them than on the day the estimator PRICED them. It is not work. It is a bet on how much prices move between the estimate and buyout. WHO GETS IT: Nobody. You hold it. Whatever prices do not move, you keep. NECESSARY? PARTLY. It only has to cover the gap between today's estimate and the day each package is bought out. 10% implies a long gap. If you buy out the long-lead packages early it collapses. | F8: Buy out steel, switchgear, elevators and HVAC plant EARLY and lock the price. Every package you fix removes its share of this line. 6% is achievable on an early buyout.
B9: General conditions | C9: 11% | D9: 8-9% | E9: WHAT IT IS: The cost of RUNNING THE SITE, as opposed to building anything. Site superintendent, project engineer, the trailer, temporary power and water, hoisting, dumpsters, daily clean-up, scaffolding, temporary toilets, security, small tools, safety. Real people and real equipment that show up every day and put no material into the building. WHO GETS IT: The general contractor — but it is reimbursement of actual cost, not profit. On an open-book contract you can see the staffing chart behind it. NECESSARY? YES. This is cost, not margin. Somebody has to run the site. Refusing to pay it does not make it go away; it just moves into the trade prices where you cannot see it. | F9: It is DURATION-DRIVEN, not scope-driven. It is a monthly burn dressed up as a percentage. Cut three months off the programme and you cut three months of general conditions. Ask for it as a MONTHLY RATE plus a duration, not a percentage — then the number has to defend itself.
B10: Overhead, profit & insurance | C10: 9% | D10: 6-7% | E10: WHAT IT IS: Three different things bundled into one rate. OVERHEAD is the GC's head office — their estimators, accountants, rent, the people who never come to your site. PROFIT is their margin. INSURANCE is the builder's risk policy, general liability, and in New York the big one, Labor Law 240 'scaffold law' coverage, which is genuinely expensive here and is a real cost, not padding. WHO GETS IT: The general contractor. Profit is theirs to keep; insurance is a real premium they pay out; overhead funds the office. NECESSARY? YES, all three. A GC with no margin is a GC who makes it back on change orders, which is worse for you. The question is not whether, it is how much and in what form. | F10: Split it apart and price each piece. Ask for insurance as an ACTUAL PREMIUM (it is a quotable number from their broker), and overhead+profit as a FIXED FEE IN DOLLARS rather than a percentage. A fixed fee means that when scope grows, their fee does not automatically grow with it — which removes their incentive to let it grow.
B11: Contingency | C11: $5,000,000 | D11: hold it | E11: WHAT IT IS: One pot of money for what nobody can foresee yet: what is actually inside the walls and above the ceiling, what the DOB asks for on review, what the asbestos survey finds, what Con Ed says about the vault. It is NOT for scope you decide to add later — that is a budget increase, not a contingency draw. WHO GETS IT: YOU — the development entity, your team. Not Live Nation (co-pro partner, not developer) and not Eric (landlord). Unspent contingency stays yours. NECESSARY? ABSOLUTELY. This is the one line that is not optional. At $5,000,000 against $48.8M of construction cost you are carrying about 10%, which is thin for a design-stage number on a 1920s warehouse with no asbestos survey, no Con Ed feasibility letter and no structural analysis of whether the roof can be lifted at all. | F11: The RULE is negotiable, not the amount. Write down what a draw requires, who approves it, and what happens to what is left. Then draw it down deliberately as each unknown closes: the ACP-5 comes back, the Con Ed letter arrives, Rooflifters finishes Stage 3. Each one that closes clean releases money back to you.
B13: HOW IT STACKS NOW
B14: TRADE COST — the work itself | D14: ='Detailed Budget'!F473 | E14: divisions 000-500 plus 800
B15: + Escalation, 10% of trade | D15: ='Detailed Budget'!F478 | E15: on trade cost only
B16: + General conditions, 8.5% of trade | D16: ='Detailed Budget'!F479 | E16: CUT from 11% on the 555 Johnson evidence
B17: + Overhead, profit & insurance, 9% of trade | D17: ='Detailed Budget'!F480 | E17: on trade cost only
B18: CONSTRUCTION COST — the work plus its markups | D18: ='Detailed Budget'!F483 | E18: what it costs to build
B19: + Contingency | D19: ='Detailed Budget'!F485 | E19: ONE pot. Was two, stacked. Now a flat dollar figure you set
B20: + FF&E | D20: ='Detailed Budget'!F387 | E20: sound, lights, video, bars, seating, furniture
B21: + Soft costs | D21: ='Detailed Budget'!F437 | E21: design, permits, legal, project management
B22: TOTAL DEVELOPMENT COST | D22: ='Detailed Budget'!F491
B25: TWO THINGS TO UNDERSTAND BEFORE YOU CUT ANY OF THESE
B26: • | C26: CONTINGENCY IS THE ONE NOT TO CUT — and it matters MORE here than on a normal job. Eric owns the building; you are building it out and renting it. If you run out of money mid-construction you cannot pause, cannot walk away, and cannot refinance against the asset, because the improvement is already sunk into someone else's building. Every change order lands on you. $5,000,000 is about 10% of construction cost — thin for a design-stage number on a 1920s warehouse with no asbestos survey, no Con Ed feasibility letter and no structural analysis of whether the roof can be lifted at all. Do not draw it down for scope you choose to add; that is a budget increase, not a contingency draw.
B27: • | C27: THE ROOF LIFT IS THE MOST EXPENSIVE THING IN THE PROJECT. Division 100 is $7,146,288 before markups — 19% of trade cost, and roughly $9.3M of the final number once the markups are applied. $3.5M of that is your quoted lift contract; $3.6M is scope the lifter explicitly excludes. It is also mandatory, so the only two questions are whether it is a LIFT or a REPLACEMENT (a $4.9M difference) and how much of the surrounding scope is already inside the quote ($1.33M of swing). Both are answered by the same phone call.

Sheet Cut Analysis
B2: WHERE WE CAN CUT
B3: Sorted by how much it costs you to take the saving. Free money first.
B5: Read the TYPE column before the number. A FIX costs nothing. A VERIFY may vanish entirely once somebody checks. A SCOPE cut means the building is less than it was. Two rows are flagged SLA or CODE — those need a professional to sign off before they are banked.
B7: FIX — errors and overpricing. Nothing is lost.
B8: Div | C8: Item | D8: Carried | E8: Cut to | F8: Saving | G8: Gate | H8: Why, and what it costs you
B9: 500 | C9: Toilet accessories, 30 sets @ $7,500 | D9: 225000 | E9: 75000 | F9: =D9-E9 | G9: OK | H9: $7,500 per set is the dev budget's own rate but it reads as a per-RESTROOM allowance, not per fixture group. 189 fixtures across ~10 restroom groups is 10 sets, not 30. Recount off the drawings.
B10: 500 | C10: Combine existing services | D10: 200000 | E10: 0 | F10: =D10-E10 | G10: OK | H10: Only needed if you are retaining and merging the old service. With a new 5,000A service from a new vault this line is redundant. Confirm with the electrical engineer.
B11: 600 | C11: Freight & installation | D11: 375000 | E11: 250000 | F11: =D11-E11 | G11: OK | H11: Carried from FT/dev budget at $375k against a bar package now less than half the size. Scale it with the equipment.
C12: FIX subtotal | F12: =SUM(F9:F11)
B14: VERIFY — may vanish entirely once someone checks. Cheapest money on the sheet.
B15: Div | C15: Item | D15: Carried | E15: Cut to | F15: Saving | G15: Gate | H15: Why, and what it costs you
B16: 500 | C16: Generator for fire pump backup | D16: 185000 | E16: 0 | F16: =D16-E16 | G16: CODE | H16: Required only where the water supply cannot support the fire pump on utility power alone. A dedicated generator may not be needed. Ask the fire protection engineer.
B17: 000 | C17: Roofing felt & mastic abatement | D17: 555750 | E17: 0 | F17: =D17-E17 | G17: OK | H17: PRESUMED asbestos on a 1948 precast roof. Nobody has sampled it. An ACP-5 survey costs a few thousand and could delete this entire line. HIGHEST VALUE PER DOLLAR SPENT ON THIS SHEET.
B18: 100 | C18: Fire separation between zones | D18: 200000 | E18: 0 | F18: =D18-E18 | G18: CODE | H18: The lifter's own exclusion says 'if required'. A single-volume assembly space may need none. Architect to confirm.
B19: 500 | C19: HVAC — repriced on load rather than area | D19: 5205550 | E19: 4100000 | F19: =D19-E19 | G19: CODE | H19: The contractor priced $40/SF over 120,000 SF against a 74,100 SF building. Tonnage (400-500) looks right for 7,440 occupants but the COST basis does not. A real load calculation could take $1M+ out. Ask the mechanical engineer whether this was priced on load or on area.
B20: 500 | C20: Con Ed vault, conduit & feeders | D20: 850000 | E20: 850000 | F20: =D20-E20 | G20: OK | H20: My estimate with no utility quote behind it. Could go either way by several hundred thousand. Get the Con Ed feasibility letter early — it also drives the schedule.
B21: 300 | C21: Mezzanine steel at 20 lb/SF | D21: 840000 | E21: 700000 | F21: =D21-E21 | G21: CODE | H21: 20 lb/SF assumes 100 psf assembly loading throughout. If part of the mezzanine is seated rather than dense standing, the design load drops and so does the tonnage. Structural engineer to confirm.
B22: 200 | C22: Cross-span girders — bay spacing | D22: 325500 | E22: 232500 | F22: =D22-E22 | G22: ASK | H22: 7 girders at 25ft on centre. At 35ft on centre you need 5, not 7, and save $93,000. Ask the production designer whether the house plot actually needs a pick point every 25ft, or whether 35ft plus bridles covers every plot you will really hang.
B23: 200 | C23: Rigging grid vs. roof capacity | D23: 1363450 | E23: 1363450 | F23: =D23-E23 | G23: ASK | H23: DO NOT CUT THIS TO SAVE MONEY — check it against the ROOF instead. The grid is what lets the new roof stay at 15 lb/SF. If the estimator has ALSO priced a roof rated to carry rigging, you are paying twice. Confirm the roof steel is designed to carry itself and nothing else.
C24: VERIFY subtotal | F24: =SUM(F16:F23)
B26: ASK ROOFLIFTERS — may already sit inside the $3-4M quote.
B27: Div | C27: Item | D27: Carried | E27: Cut to | F27: Saving | G27: Gate | H27: Why, and what it costs you
B28: 100 | C28: Foundations for the new load path | D28: 1087650 | E28: 0 | F28: =D28-E28 | G28: ASK | H28: Ask Rooflifters whether footings and underpinning are inside the $3-4M quote. If yes, the whole group comes out.
B29: 100 | C29: Roof-to-wall closure | D29: 241643 | E29: 0 | F29: =D29-E29 | G29: ASK | H29: Ask whether the new roof/wall joint is theirs. Their scope includes 'external metal siding to enclose the building' which may already cover it.
C30: ASK ROOFLIFTERS subtotal | F30: =SUM(F28:F29)
B32: DEFER — pay later, little or no penalty.
B33: Div | C33: Item | D33: Carried | E33: Cut to | F33: Saving | G33: Gate | H33: Why, and what it costs you
B34: 600 | C34: Rent-to-buy the house PA | D34: 2200000 | E34: 0 | F34: =D34-E34 | G34: OK | H34: Defers the largest single FF&E line. NOT a saving — total cost is higher over the life of the kit. Use it for day-one cash only.
B35: 400 | C35: Entry mats & stair treads | D35: 32500 | E35: 0 | F35: =D35-E35 | G35: OK | H35: Fit-out item, no penalty for landing later.
B36: 600 | C36: Merchandise cases | D36: 26000 | E36: 0 | F36: =D36-E36 | G36: OK | H36: Furniture. Buy when the merch programme is set.
B37: 600 | C37: Office furniture | D37: 65000 | E37: 0 | F37: =D37-E37 | G37: OK | H37: Buy at fit-out, not at buyout.
B38: 500 | C38: House / architectural lighting BOH | D38: 185000 | E38: 120000 | F38: =D38-E38 | G38: OK | H38: Circulation and BOH lighting to a working standard now; decorative later.
B39: 200 | C39: Chain hoists at grid pick points | D39: 91200 | E39: 45600 | F39: =D39-E39 | G39: OK | H39: 32 motors is a full house complement. Buy 16 now, hang the rest of the points with dead-hangs, and add motors as programming demands. The STEEL is what you cannot add later; the motors you can.
C40: DEFER subtotal | F40: =SUM(F34:F39)
B42: SCOPE — real cuts. You lose something.
B43: Div | C43: Item | D43: Carried | E43: Cut to | F43: Saving | G43: Gate | H43: Why, and what it costs you
B44: 400 | C44: Decorative feature above each back bar | D44: 60000 | E44: 0 | F44: =D44-E44 | G44: OK | H44: Six decorative features at $10,000. Pure aesthetic in a room whose aesthetic is exposed structure.
B45: 400 | C45: CMU elevator tower at stage | D45: 104195 | E45: 0 | F45: =D45-E45 | G45: OK | H45: Second elevator tower. With one ADA car and a small BOH lift you do not need two masonry towers.
B46: 400 | C46: Acoustic panels — reduce coverage | D46: 1120000 | E46: 720000 | F46: =D46-E46 | G46: SLA | H46: 28,000 SF of wall panel at $40. Targeted treatment on first-reflection and rear surfaces rather than blanket coverage gets most of the acoustic benefit. RISK: this is the licence-to-operate item. Do not cut without the acoustician signing off, and do not cut the isolation or flanking control.
B47: 400 | C47: Polished concrete to sealed concrete | D47: 416000 | E47: 208000 | F47: =D47-E47 | G47: OK | H47: 52,000 SF at $8 polished vs $4 sealed. Sealed is the Infinity aesthetic anyway and it is what most of the room will be under foot traffic.
B48: 400 | C48: Interior sound/fire rated walls | D48: 360000 | E48: 270000 | F48: =D48-E48 | G48: CODE | H48: 18,000 SF at $20 is my estimate of stair and shaft enclosure. Recount off the drawings — the rated area is fixed by code but my quantity is a guess.
B49: 600 | C49: Mezzanine box chairs | D49: 197100 | E49: 120000 | F49: =D49-E49 | G49: SLA | H49: 657 chairs at $300. Fewer boxes with rail standing behind. Coordinate with the seat count counsel confirms for the classification.
B50: 600 | C50: Exterior building signage | D50: 150000 | E50: 90000 | F50: =D50-E50 | G50: OK | H50: Identification and wayfinding, not a facade programme.
B51: 600 | C51: FF&E installation labour | D51: 600000 | E51: 420000 | F51: =D51-E51 | G51: OK | H51: Dev budget's own $600k against an FF&E package now 16% smaller. Scale it.
B52: 200 | C52: VIP platforms, FOH & decking | D52: 278488 | E52: 200000 | F52: =D52-E52 | G52: OK | H52: FT actuals for an open-air stage with a larger VIP programme. Scale to the mezzanine-based VIP here.
B53: 700 | C53: Project management | D53: 1100000 | E53: 500000 | F53: =D53-E53 | G53: OK | H53: ALREADY APPLIED at your instruction. Now carried at $500,000 — 1.1% of trade cost — for OUR OWN development team: Thomas as project manager plus consultants. Live Nation is the co-pro / programming partner, not the developer. This is BELOW the 2-4% norm, so it is a number to defend, not one with more room in it. It funds roughly one full-time PM for the duration plus a limited consultant bench.
B54: 200 | C54: Access catwalk on the header lines | D54: 64750 | E54: 0 | F54: =D54-E54 | G54: OK | H54: The one soft item in the grid. Focus the rig from a genie lift between load-ins instead of walking a catwalk. Costs you crew hours on changeover, saves $64,750.
C55: SCOPE subtotal | F55: =SUM(F44:F54)
B57: SCHEDULE — programme is the cost driver, not the rate.
B58: Div | C58: Item | D58: Carried | E58: Cut to | F58: Saving | G58: Gate | H58: Why, and what it costs you
B59: 000 | C59: Sidewalk shed rental | D59: 575000 | E59: 431000 | F59: =D59-E59 | G59: OK | H59: 24 months at $23,958/month. Every month of programme costs you $23,958. An 18-month shed duration saves $143,748. Sequence the lift early and strike the shed before fit-out.
B60: 000 | C60: Temporary heat & dehumidification | D60: 85000 | E60: 45000 | F60: =D60-E60 | G60: OK | H60: Winter exposure. Sequencing the envelope closure before winter roughly halves it.
C61: SCHEDULE subtotal | F61: =SUM(F59:F60)
C63: TOTAL IDENTIFIED | F63: =F12+F24+F30+F40+F55+F61
C64: Budget as it stands | F64: ='Detailed Budget'!F491
C65: Budget with every cut taken | F65: ='Detailed Budget'!F491-F63 | H65: Not realistic to take all of them — the SCOPE and SLA rows have real consequences. Treat FIX + VERIFY + ASK as the honest target.
B67: DO THESE FOUR THINGS FIRST
B68: • | C68: Commission the ACP-5 asbestos survey. A few thousand dollars could delete $555,750 of presumed roof abatement. Best return on this sheet by an order of magnitude.
B69: • | C69: Get the four Rooflifters answers in writing: are footings in, is the roof-to-wall closure in, union or non-union basis, and the quote date. Worth $1.33M of swing.
B70: • | C70: Ask the mechanical engineer whether HVAC was priced on load or on area. The contractor used $40/SF over 120,000 SF against a 74,100 SF building. Worth $1M+.
B71: • | C71: Get the Con Ed feasibility letter. The $850,000 vault and feeder line is my estimate with no utility quote behind it, and the lead time drives the schedule.

Sheet Options
B2: HOW TO GET THIS NUMBER DOWN
B3: Six options, stacked. Each one includes everything above it.
B5: FIRST — LOOK AT THE MARKUP STACK
B6: Trade cost is $37.5M. Below the line sits $27.2M more — $11.3M of markups, a $5.0M contingency, $5.6M of FF&E and $5.4M of soft costs. The three markup RATES total 30% of trade cost and buy you no work at all, so every point negotiated off them is free money. Nothing here costs you scope.
B8: Rate | C8: As carried | D8: Target | E8: Worth | G8: Why the target is reasonable
B9: Escalation | C9: 0.1 | D9: 0.06 | E9: 1500053 | G9: 10% assumes a long gap between estimate and buyout. Buy out steel, switchgear, elevators and HVAC plant early and lock the price.
B10: General conditions | C10: 0.085 | D10: 0.078 | E10: 286246 | G10: ALREADY CUT from 11% to 8.5% on the Schimenti evidence. 7.80% is what he actually charged Eric on the full 555 Johnson scheme, so there is one more point in it.
B11: Overhead, profit & insurance | C11: 0.09 | D11: 0.065 | E11: 937533 | G11: Split it apart: insurance as an actual broker premium, overhead and profit as a FIXED FEE IN DOLLARS so it does not grow when scope grows.
B12: Total available on rates alone | E12: =SUM(E9:E11)
B14: THE SIX OPTIONS
B15: Option | C15: Total | D15: $/SF | E15: $/cap | F15: Step | G15: What it costs you
B16: 0. As it stands | C16: 73962877 | D16: 998 | E16: 9941 | G16: —
B17: 1. Take the free cuts | C17: 67244411 | D17: 907 | E17: 9038 | F17: -6718466 | G17: Nothing. Asbestos survey, Rooflifters answers, HVAC load basis, two arithmetic errors.
B18: 2. + negotiate the markups | C18: 59130282 | D18: 798 | E18: 7948 | F18: -8114129 | G18: Nothing in scope. Open-book GMP with shared savings, earlier buyout, contingency to 12%. THIS IS THE TARGET.
B19: 3. + landlord funds the roof lift | C19: 48836545 | D19: 659 | E19: 6564 | F19: -10293737 | G19: Negotiating capital with Eric. The lift is a permanent improvement to his building that outlives a 20-year lease.
B20: 4. + drop the lift 50ft to 40ft | C20: 46900000 | D20: 633 | E20: 6304 | F20: -1936545 | G20: THE MOAT. Not recommended — shown only so the number is visible. At 40 ft you lose flown production and the positioning argument.
B21: 5. + defer the mezzanine | C21: 43900000 | D21: 592 | E21: 8442 | F21: -3000000 | G21: 2,240 capacity and the compliance seating location. Opens floor-only at ~5,200. Structure must still go in later at a premium.
B22: 6. + owner-furnish, direct trades | C22: 40300000 | D22: 544 | E22: 7750 | F22: -3600000 | G22: Delivery risk moves to you. Buy switchgear, HVAC plant and elevators direct; fewer trades under GC markup.
B24: RECOMMENDED: Option 2 at $59.1M. It costs nothing in scope — it is arithmetic corrections, evidence-gathering and contract structure. Options 3 through 6 all trade something real away, and Option 4 trades the moat.

Sheet Questions to Ask
B2: QUESTIONS
B3: 49 questions, by who to ask. Each carries the evidence that makes it hard to deflect.
B5: ESTIMATOR / GENERAL CONTRACTOR
B6: No. | C6: Question | D6: Why it is hard to deflect | E6: $ at stake
B7: 1 | C7: The $1,000,000 black steel mounting structure at the stage — does that number include ANY steel spanning out over the crowd, or does it stop at the stage line? | D7: It is a one-line lump sum with no take-off behind it. Either it covers the room or it does not, and he has to say which. We are now carrying a separate $1,363,450 rigging grid over the crowd; if his $1M already reaches out over the floor, one of those two numbers comes out. | E7: 1363450
B8: 2 | C8: Is the new roof steel designed to carry ITSELF ONLY, or have you rated it to carry rigging as well? | D8: The whole logic of the ground-supported grid is that nothing hangs from the building. If he has also rated the roof for rigging load he has bought the same capacity twice. At 74,100 SF the difference between 15 lb/SF and 20 lb/SF is 185 tons of steel. | E8: 1110000
B9: 3 | C9: Can the rigging grid be erected during the roof-off window, picked straight down through the opening? | D9: Erecting 74 tons of steel by chain hoist inside a closed, finished room is a different price from craning it in from above. This is a sequencing decision that has to be made before the roof closes — after that it is not available at any price. | E9: 185000
B10: 4 | C10: Roughly two-thirds of your trade schedule carries a unit price against a QUANTITY OF ZERO. When are those quantities going in, and what is your own estimate of the total once they are? | D10: Structural steel is $0 on a project whose scope line reads 'Add Second Level'. Acoustic panels are $0 in a music venue. Millwork, doors, painting, fireproofing, tile — all $0. | E10: the whole estimate
B11: 5 | C11: Roofing row 193 prices 1,592 SF of pavers at $3,312.50/SF. The lines directly above and below, same product, are $31/SF. Is that an error? | D11: One cell. Marked up through 9% OH&P, 10% contractor contingency and 10% owner contingency. | E11: $6,890,129
B12: 6 | C12: Your escalation line for Building & Fit-Out is blank. The off-site parking garage carries 5%. Why the difference? | D12: The line exists in your file and was left empty. | E12: $3,591,389
B13: 7 | C13: Your abatement line is $8,750. Your demolition schedule says 74,000 SF of precast roof, 'abatement by others'. Who is 'others', and what have they quoted? | D13: 1948 building. 'By others' is not a scope exclusion the owner gets to keep — someone pays it. | E13: $555,750
B14: 8 | C14: You price HVAC at $40/SF over 120,000 SF. The building is 74,100 SF. Was this priced from a load calculation or from an area assumption? | D14: The tonnage may well be right. The pricing BASIS is applied to 62% more area than exists. | E14: $1,100,000+
B15: 9 | C15: Your electrical division is $558,750 and contains two switchboards, temporary power and firestopping. Where are the panels, secondary distribution and branch wiring? | D15: Every distribution line in your file is quantity zero. Nothing can plug in. | E15: $3,400,000+
B16: 10 | C16: What construction duration are your general conditions priced for? | D16: The only duration stated anywhere in your file is 60 weeks of portable toilets — about 14 months. The underwriting assumes 24. | E16: $1,200,000
B17: 11 | C17: Your summary carries General Conditions at $2,000,000. Your own hidden General Conditions tab totals $2,082,000. Which is right? | D17: Both numbers are in the file you sent. | E17: $82,000
B18: 12 | C18: You carry 9% overhead, profit and insurance plus a 10% contractor contingency you keep. Will you go open-book with a shared-savings split on unspent contingency? | D18: A fixed OH&P plus a retained contingency gives you no reason to underspend it. | E18: $2,400,000
B19: 13 | C19: Committed Costs, Invoices and Change Orders are all zero. Nothing has been bought. What would a competitive three-bid process return against this estimate? | D19: 5-10% is normal against a first-pass estimate in this market. | E19: $1,800,000-3,600,000
B20: 14 | C20: Your Project At-a-Glance and Project Summary tabs are broken with #REF!, the cost report is dated 2023-01-31 and the contingency log says March 2020. Is this built on a template from another project? | D20: It matters because the cost-control apparatus is not actually wired to this job. | E20: governance
B21: 15 | C21: Your Risk Report is empty and exposure is $0. Where do you carry the pending Phase I, the pending structural and MEP assessment, the pending Certificate of Occupancy and the pending FDNY approval? | D21: Those are the four largest uncertainties on the project and none of them appear in your risk register. | E21: governance
... B23: 17 | C23: Owner's project management is $520,000 — 1.2% of project cost against a 2-4% norm. Is that a real number or a placeholder? | D23: Under-resourced PM is how change orders get approved without challenge. | E23: $600,000
B25: ARCHITECT (Wake)
B26: No. | C26: Question | D26: Why it is hard to deflect | E26: $ at stake
B27: 18 | C27: Does the theater use-classification require seating on a specific floor, fixed or removable, and at what count? | D27: It carries the liquor licence and the cabaret licence. Everything downstream depends on the answer. | E27: $3,156,738
B28: 19 | C28: Do we actually need four levels? What does the classification require, as opposed to what the test fit proposes? | D28: Every added level multiplies accessible routes, egress stairs, vertical circulation and fire separation. | E28: $1,800,000-2,000,000
B29: 20 | C29: What is the EGRESS-driven capacity, as distinct from the area-driven capacity? | D29: Egress caps the room, not floor area. The mezzanine is already egress-capped at 2,240. | E29: capacity
B30: 21 | C30: Your test fit shows 3,714 seated at 7 SF/occ and 5,200 standing at 5 SF/occ. Does that make the floor 26,000 SF and the mezzanine 14,000 SF? | D30: We derived those areas from your own occupancy loads. Confirm or correct them. | E30: $1,851,016
B31: 22 | C31: Is the roof-deck, restaurant and VIP-lounge programme a client requirement or a design proposal? | D31: It is priced as though it were a requirement. If it is a proposal it can be deferred or deleted. | E31: $1,300,000+
B32: 23 | C32: Do your drawings assume a roof LIFT or a roof REPLACEMENT? | D32: The development budget schedules 74,000 SF of precast roof for demolition, which is a replacement. A lift keeps the roof. | E32: $4,947,067
B33: 24 | C33: What is the filing critical path, and which approval gates the Temporary Certificate of Occupancy? | D33: We need the sequence, not a fee proposal. DOB structural approval alone is 12-18 months. | E33: schedule
B34: 25 | C34: What fire separation between zones is actually required? | D34: Rooflifters excludes it 'if required'. Nobody has said whether it is. | E34: $200,000
B35: 26 | C35: Confirm the plumbing fixture calculation. The budget carries 189; the underwriting assumed 100. | D35: It is set by occupant load and occupancy group, so there is a right answer. | E35: $489,500
B36: 27 | C36: Your fee is $2,200,000 with MEP and structural engineering folded into one line. Can we see the breakdown by discipline? | D36: Factory Town's architect ran 3.9x its approved budget. We would like to see the shape of this one. | E36: $2,200,000
B37: 28 | C37: Does the acoustic treatment need blanket coverage, or targeted treatment on first-reflection and rear surfaces? | D37: 28,000 SF of wall panel at $40/SF is the assumption. It is also the licence-to-operate item, so we will not cut it without you. | E37: $400,000
B39: MECHANICAL ENGINEER
B40: No. | C40: Question | D40: Why it is hard to deflect | E40: $ at stake
B41: 29 | C41: What is the calculated cooling load in tons, from a real load calculation? | D41: 7,440 occupants alone are roughly 250 tons. We need the number, not a $/SF proxy. | E41: $1,100,000+
B42: 30 | C42: Do we need a building management system at $500,000, or will simpler controls serve a single-volume assembly space? | D42: A BMS is sized for a building with many zones. This is one big room. | E42: $250,000
B43: 31 | C43: Is mechanical smoke control required at this volume and height, and what does it cost? | D43: We carry $420,000 as an estimate. It is a code question with a definite answer. | E43: $420,000
B44: 32 | C44: What is the heating strategy at a 50 ft ceiling, and is radiant the right call? | D44: There is NO heating scope in the contractor's budget at all. | E44: $815,100
B45: 33 | C45: Does the mezzanine add conditioned volume, or only occupants and air distribution? | D45: It sits inside the existing envelope. It should be a minimal uplift, not a new building. | E45: $638,120
B47: ROOFLIFTERS
B48: No. | C48: Question | D48: Why it is hard to deflect | E48: $ at stake
B49: 34 | C49: Is the $3-4M lift-only, or does it include the external siding enclosure? | D49: Your published inclusions list siding. We need it confirmed for this project. | E49: $1,800,000
B50: 35 | C50: Are new column footings and underpinning inside the price? | D50: We carry $1,087,650 for foundations that may already be yours. | E50: $1,087,650
B51: 36 | C51: Who owns the roof-to-wall closure and its weatherproofing at the new joint? | D51: We carry $241,643 at $187/LF over 1,089 LF. It may be inside your enclosure scope. | E51: $241,643
B52: 37 | C52: Is the roof MEMBRANE included, or only the external siding? | D52: Different answers change the number by roughly $2.5M. | E52: $2,593,500
B53: 38 | C53: Union or non-union basis — and can you price both? | D53: Your rate card says non-union. This is New York. | E53: $1,500,000+
B54: 39 | C54: What is the quote date and how long is it held? | D54: Your published card is 2022. We are assuming 30-40% escalation and would rather not guess. | E54: $1,000,000
B55: 40 | C55: Can the existing roof structure take being lifted, and will you carry out the Stage 3 on-site structural analysis? | D55: Your own process says the fee credits against the contract. It decides whether this is a $5.7M lift or a $10.6M replacement. | E55: $4,947,067
B57: LANDLORD (Eric Cohen)
B58: No. | C58: Question | D58: Why it is hard to deflect | E58: $ at stake
B59: 41 | C59: Is the 260-space parking garage our scope or yours? | D59: $2,150,000 appears in the development budget and nowhere in the underwriting. | E59: $2,257,500
B60: 42 | C60: Will you fund the roof lift as base-building work, or provide a TI allowance against it? | D60: A 30 ft roof raise is a permanent improvement to your building that outlives a 20-year lease. | E60: $7,146,288
B61: 43 | C61: Is the $7.50/SF NNN a negotiated CAP or an estimate of actual charges? | D61: NYC Class 4 real estate tax alone plausibly runs $19-24/SF on the comps in your own deck. | E61: $926,250/yr
B62: 44 | C62: What build-period base rent abatement is available? | D62: Rent runs through a 12-18 month DOB approval we do not control, before a ticket is sold. | E62: $9,000,000+
B63: 45 | C63: Is there a renewal option at a pre-agreed rate, and a purchase option at a struck price? | D63: We are funding $45M+ of improvement on your building with no residual at year 20. | E63: structural
B64: 46 | C64: Will you commit unconditionally, and within a stated time limit, to signing DOB filings as owner of record? | D64: Every filing needs your signature. A promise to be reasonable is not a term. | E64: schedule
B66: COUNSEL
B67: No. | C67: Question | D67: Why it is hard to deflect | E67: $ at stake
B68: 47 | C68: Is this use as-of-right in M3-1 — and can we have the written determination with citations? | D68: The underwriting asserts it in one line. It is the largest binary risk in the deal. | E68: the deal
B69: 48 | C69: Does the mixed programme — venue plus restaurant plus rooftop assembly — create more than one use determination? | D69: The weakest one governs. | E69: the deal
B70: 49 | C70: What does the theater classification require physically: seat count, fixed vs removable, which floor? | D70: Every seating number we have is a placeholder until you answer. | E70: $3,156,738
B71: 50 | C71: Does the cabaret licence still exist? NYC repealed the cabaret law in 2017. | D71: If the team is designing around a repealed licence, that shapes the drawings wrongly. | E71: design
B72: 51 | C72: Does taking the IDA / ICAP sales-tax exemption trigger prevailing wage? | D72: The exemption is worth $1.1-1.5M. Prevailing wage could cost more than that. | E72: net negative
B73: 52 | C73: Does our liquor licence class carry a food-service requirement? | D73: We are planning to outsource the kitchen entirely. | E73: $215,000

Sheet Thomas Reconciliation
B2: THOMAS’S BUDGET — EVERY LINE, RECONCILED
B3: All 199 trade lines from the Master Development Budget dated 7 Sep 2026. Nothing dropped.
B5: GENERAL CONDITIONS — PICK ONE, NOT BOTH | F5: GC line items | G5: =SUMIF(I9:I238,"GC*",G9:G238) | I5: Thomas carries $1,696,000 of general conditions as TRADE LINES (013000 + 015800: site office, site security, safety plan, portable toilets, clean-up, rubbish, final clean, project labour, field technology). We also apply an 11%% general conditions markup on trade cost, which is $4,125,146. THAT IS THE SAME SITE COST TWICE. The toggle at the top of the Detailed Budget picks one: 1 = the percentage, 0 = his line items. His line items are $2,429,146 CHEAPER — but they are also incomplete, since all of 015800 sits at qty 0.
B6: ADD-BACKS TOGGLED ON | G6: =SUM(J9:J238) | I6: Live total of every non-GC line whose toggle is 1. Feeds the Detailed Budget below the line. Default is zero.
B8: CSI | C8: Description | D8: Qty | E8: Unit | F8: His rate | G8: His total | H8: ON=1 | I8: Status — where it lands in this model / why it is off
B9: 013000 PROJECT REQUIREMENTS
B10: 013000 | C10: 1. BIM Set Up & Coordination | D10: 1 | E10: LS | F10: 30000 | G10: 30000 | H10: 0 | I10: GC — GENERAL CONDITIONS CONTENT — see the master toggle above | J10: 0
B11: 013000 | C11: 2. Plans / Reprographics | D11: 1 | E11: LS | F11: 7500 | G11: 7500 | H11: 0 | I11: GC — GENERAL CONDITIONS CONTENT — see the master toggle above | J11: 0
B12: 013000 | C12: 3. Site Office & Equipment | D12: 1 | E12: LS | F12: 12000 | G12: 12000 | H12: 0 | I12: GC — GENERAL CONDITIONS CONTENT — see the master toggle above | J12: 0
B13: 013000 | C13: 4. Field Techonology | D13: 1 | E13: LS | F13: 200000 | G13: 200000 | H13: 0 | I13: GC — $200,000 of "field technology" is a general conditions item and a big one. Ask what it actually buys — Procore licences and a few tablets are not $200,000. | J13: 0
B14: 013000 | C14: 5. Construction Signage | D14: 1 | E14: LS | F14: 4500 | G14: 4500 | H14: 0 | I14: GC — GENERAL CONDITIONS CONTENT — see the master toggle above | J14: 0
B15: 013000 | C15: 6. Site Security | D15: 1 | E15: LS | F15: 13000 | G15: 13000 | H15: 0 | I15: GC — GENERAL CONDITIONS CONTENT — see the master toggle above | J15: 0
B16: 013000 | C16: 7. Site Safety Plan / First Aid / TPP / FE's / Safety Inspector | D16: 1 | E16: LS | F16: 250000 | G16: 250000 | H16: 0 | I16: GC — $250,000. NYC site safety is real and required, but it belongs in general conditions, not on top of a general conditions percentage. | J16: 0
B17: 013000 | C17: 8. Portable Toilets | D17: 60 | E17: WK | F17: 400 | G17: 24000 | H17: 0 | I17: GC — GENERAL CONDITIONS CONTENT — see the master toggle above | J17: 0
B18: 013000 | C18: 9. Clean up Materials | D18: 1 | E18: LS | F18: 45000 | G18: 45000 | H18: 0 | I18: GC — GENERAL CONDITIONS CONTENT — see the master toggle above | J18: 0
B19: 013000 | C19: 10. Protection Materials | D19: 1 | E19: LS | F19: 50000 | G19: 50000 | H19: 0 | I19: GC — GENERAL CONDITIONS CONTENT — see the master toggle above | J19: 0
B20: 013000 | C20: 11. Project Labor | D20: 1 | E20: LS | F20: 900000 | G20: 900000 | H20: 0 | I20: GC — $900,000 of "project labor" is the single largest general conditions line. This is GC labour on site. It is exactly what the 11% markup is for. Do not pay both. | J20: 0
B21: 013000 | C21: 12. Project Rubbish Removals | D21: 1 | E21: LS | F21: 60000 | G21: 60000 | H21: 0 | I21: GC — GENERAL CONDITIONS CONTENT — see the master toggle above | J21: 0
B22: 013000 | C22: 13. Final Clean | D22: 1 | E22: LS | F22: 100000 | G22: 100000 | H22: 0 | I22: GC — GENERAL CONDITIONS CONTENT — see the master toggle above | J22: 0
B23: 015800 SCAFFOLDING & HOARDING
B24: 015800 | C24: 1. Install sidewalk bridge around building | D24: 0 | E24: LS | F24: 250000 | G24: 0 | H24: 0 | I24: IN — Div 000 — we price the shed at $210/LF over 1,089 LF plus 24 months of rental, which is a build-up rather than his $250,000 lump. Ours is the more defensible number. | J24: =H24*G24
B25: 015800 | C25: 2. Roof Protection/Barriers after Demo of roof | D25: 0 | E25: LS | F25: 50000 | G25: 0 | H25: 0 | I25: GC — GENERAL CONDITIONS CONTENT — see the master toggle above | J25: 0
B26: 015800 | C26: 3. Site safety During Erection | D26: 0 | E26: LS | F26: 20000 | G26: 0 | H26: 0 | I26: GC — GENERAL CONDITIONS CONTENT — see the master toggle above | J26: 0
B27: 024100 DEMOLITION
B28: 024100 | C28: 1. Demo existing asonry walls at New Entry/Lobby area | D28: 2500 | E28: SF | F28: 12 | G28: 30000 | H28: 0 | I28: IN — Div 000 — Demolition, interior | J28: =H28*G28
B29: 024100 | C29: 1. Demo existing windows 1'x10' | D29: 34 | E29: EA | F29: 12 | G29: 408 | H29: 0 | I29: IN — Div 000 — Demolition, interior | J29: =H29*G29
B30: 024100 | C30: 2. Demo. Misc. Build out scattered thru out, e.g. piping, CMU, walls | D30: 0 | E30: SF | F30: 2 | G30: 0 | H30: 0 | I30: IN — Div 000 — Demolition, interior | J30: =H30*G30
B31: 024100 | C31: 3. Demo. Roofing, deck & framing to create new elevated roof area at Music Hall | D31: 0 | E31: SF | F31: 15 | G31: 0 | H31: 0 | I31: IN — Div 000 — Demolition, interior | J31: =H31*G31
B32: 024100 | C32: 4. Demo Floor for New Structural Columns/Footings | D32: 0 | E32: SF | F32: 10 | G32: 0 | H32: 0 | I32: IN — Div 000 — Demolition, interior | J32: =H32*G32
B33: 024100 | C33: 5. Allow for Floor trenching for MEPS | D33: 0 | E33: LS | F33: 50000 | G33: 0 | H33: 0 | I33: IN — Div 000 — Demolition, interior | J33: =H33*G33
B34: 024100 | C34: 6. Demo floor for Recessed floor - Include Excavation | D34: 0 | E34: SF | F34: 0 | G34: 0 | H34: 0 | I34: IN — Div 000 — Demolition, interior [his note: Included Above] | J34: =H34*G34
B35: 024100 | C35: 7. Misc Façade Demo Along Johnson Ave (Doors, Roll-ups, Windows, etc.) | D35: 0 | E35: LS | F35: 20000 | G35: 0 | H35: 0 | I35: IN — Div 000 — Demolition, interior | J35: =H35*G35
B36: 033000 CONCRETE
B37: 033000 | C37: 1. Excavation related to New Columns at Music hall | D37: 0 | E37: SF | F37: 6.5 | G37: 0 | H37: 0 | I37: IN — Div 200/300 foundations + Div 000 sitework [his note: Based on Footprint of New Roof] | J37: =H37*G37
B38: 033000 | C38: 2. CMU wall footing excavation allow 2' deep for new Load bearing wall at Music hall- East wall | D38: 0 | E38: LF | F38: 150 | G38: 0 | H38: 0 | I38: IN — Div 200/300 foundations + Div 000 sitework | J38: =H38*G38
B39: 033000 | C39: 3. Concrete at New footings | D39: 0 | E39: EA | F39: 7500 | G39: 0 | H39: 0 | I39: IN — Div 200/300 foundations + Div 000 sitework | J39: =H39*G39
B40: 033000 | C40: 4. Concrete at CMU footing | D40: 0 | E40: LF | F40: 100 | G40: 0 | H40: 0 | I40: IN — Div 200/300 foundations + Div 000 sitework | J40: =H40*G40
B41: 033000 | C41: 5. Patch slab due to New footing | D41: 0 | E41: SF | F41: 30 | G41: 0 | H41: 0 | I41: IN — Div 200/300 foundations + Div 000 sitework | J41: =H41*G41
B42: 033000 | C42: 6. Patch conc. At Trenching for MEPS | D42: 0 | E42: SF | F42: 30 | G42: 0 | H42: 0 | I42: IN — Div 200/300 foundations + Div 000 sitework | J42: =H42*G42
B43: 033000 | C43: 7. New slab Pour-back at Excavated Areas | D43: 0 | E43: SF | F43: 30 | G43: 0 | H43: 0 | I43: IN — Div 200/300 foundations + Div 000 sitework | J43: =H43*G43
B44: 033000 | C44: 8. New slab at Recessed floor | D44: 0 | E44: SF | F44: 0 | G44: 0 | H44: 0 | I44: IN — Div 200/300 foundations + Div 000 sitework [his note: Included Above] | J44: =H44*G44
B45: 033000 | C45: 9. Concrete on Deck for Mezz of Music Hall with Platforms | D45: 0 | E45: SF | F45: 25 | G45: 0 | H45: 0 | I45: IN — Div 200/300 foundations + Div 000 sitework | J45: =H45*G45
B46: 033000 | C46: 10. Concrete In-fill on New Pan Stairs | D46: 0 | E46: EA | F46: 4000 | G46: 0 | H46: 0 | I46: IN — Div 200/300 foundations + Div 000 sitework [his note: (2) Feature Stairs, (2) BOH Stairs] | J46: =H46*G46
B47: 033000 | C47: 11. Grouting at Steel Trusses & Column Base Plates | D47: 0 | E47: LS | F47: 15000 | G47: 0 | H47: 0 | I47: IN — Div 200/300 foundations + Div 000 sitework | J47: =H47*G47
B48: 033000 | C48: 12. Polished concrete | D48: 0 | E48: SF | F48: 8 | G48: 0 | H48: 0 | I48: IN — Div 200/300 foundations + Div 000 sitework | J48: =H48*G48
... B51: 033000 | C51: 16. Concrete at Stage Platform 4'6" H on Styrofoam | D51: 0 | E51: SF | F51: 50 | G51: 0 | H51: 0 | I51: IN — Div 200/300 foundations + Div 000 sitework | J51: =H51*G51
B52: 042000 MASONRY
B53: 042000 | C53: 1. Patch & Repair Existing Masonry Wall | D53: 9972 | E53: SF | F53: 10 | G53: 99720 | H53: 0 | I53: IN — Div 400 — Masonry | J53: =H53*G53
B54: 042000 | C54: 2. F&I Brick façade at music hall bump up | D54: 0 | E54: SF | F54: 35 | G54: 0 | H54: 0 | I54: IN — Div 400 — Masonry | J54: =H54*G54
B55: 042000 | C55: 3. CMU and Brick infills at old windows and door opening | D55: 0 | E55: SF | F55: 70 | G55: 0 | H55: 0 | I55: IN — Div 400 — Masonry | J55: =H55*G55
B56: 042000 | C56: 4. Repair/ cleaning and minor repointing of existing brick facade | D56: 0 | E56: SF | F56: 10 | G56: 0 | H56: 0 | I56: IN — Div 400 — Masonry | J56: =H56*G56
B57: 042000 | C57: 5. Misc. Patching allow at penetrations | D57: 0 | E57: LS | F57: 5000 | G57: 0 | H57: 0 | I57: IN — Div 400 — Masonry | J57: =H57*G57
B58: 055100 STRUCTURAL STEEL & MISC METALS
B59: 055100 | C59: 1. Disconnect roof framing for Demo & Shore at select areas | D59: 0 | E59: SF | F59: 5 | G59: 0 | H59: 0 | I59: IN — Div 100/200/300 — structural steel | J59: =H59*G59
B60: 055100 | C60: 2. F&I new Roof Trusses, girders, Columns at Music Hall area | D60: 0 | E60: TONS | F60: 6000 | G60: 0 | H60: 0 | I60: IN — Div 100/200/300 — structural steel | J60: =H60*G60
B61: 055100 | C61: 3. F&I Roof deck | D61: 0 | E61: SF | F61: 4 | G61: 0 | H61: 0 | I61: IN — Div 100/200/300 — structural steel | J61: =H61*G61
B62: 055100 | C62: 4. Steel Framing at Mezz area - Including Elevated Standing & Box Seating | D62: 0 | E62: TONS | F62: 6000 | G62: 0 | H62: 0 | I62: IN — Div 100/200/300 — structural steel | J62: =H62*G62
B63: 055100 | C63: 5. Steel Framing at upper balcony - incluing balcony seating | D63: 0 | E63: TONS | F63: 6000 | G63: 0 | H63: 0 | I63: ADD — UPPER BALCONY IS A THIRD LEVEL AND IS NOT IN THIS MODEL. We carry stage + one mezzanine. If the test fit keeps a balcony above the mezzanine it is new steel, new egress, new sprinkler and new seating. Priced at 0 by Thomas so its real cost is unknown. DECISION NEEDED. | J63: =H63*G63
B64: 055100 | C64: 6. Stage Lighting & AV support structure | D64: 0 | E64: LBS | F64: 8 | G64: 0 | H64: 0 | I64: IN — THE RIGGING GRID. His rate is $8/LB with qty 0, so he never priced it. Our ground-supported grid is $1,363,450 for roughly 74 tons — that is $9.21/LB, within 15% of his own rate. His rate corroborates ours. | J64: =H64*G64
B65: 055100 | C65: 7. Small stair to access Stage | D65: 0 | E65: EA | F65: 13000 | G65: 0 | H65: 0 | I65: IN — Div 100/200/300 — structural steel | J65: =H65*G65
B66: 055100 | C66: 8. Roof Dunnage for HVAC Equipment's | D66: 0 | E66: LOC | F66: 20000 | G66: 0 | H66: 0 | I66: IN — Div 100/200/300 — structural steel | J66: =H66*G66
B67: 055100 | C67: 9. Roof Penetrations framing for Toilet exhaust & Kitchen exhaust | D67: 0 | E67: LS | F67: 25000 | G67: 0 | H67: 0 | I67: IN — Div 100/200/300 — structural steel | J67: =H67*G67
B68: 055100 | C68: 10. Stairs | D68: 0 | E68: FL | F68: 30000 | G68: 0 | H68: 0 | I68: IN — Div 100/200/300 — structural steel | J68: =H68*G68
B69: 055100 | C69: 11. Allow for Unistrut at select area of stage | D69: 0 | E69: SF | F69: 35 | G69: 0 | H69: 0 | I69: IN — Div 100/200/300 — structural steel | J69: =H69*G69
B70: 055100 | C70: 12. Railing at Roof Deck | D70: 0 | E70: LF | F70: 500 | G70: 0 | H70: 0 | I70: ADD — Roof deck is outdoor terrace programme, not in this model. | J70: =H70*G70
... B73: 055100 | C73: 15. Allow for access Ladders at Stage Overhead lighting grid area | D73: 0 | E73: LS | F73: 15000 | G73: 0 | H73: 0 | I73: IN — Div 100/200/300 — structural steel | J73: =H73*G73
B74: 062000 Rough Carpentry/OSHA Protection
B75: 062000 | C75: 1. Safety Protection at Roof cut out | D75: 0 | E75: LS | F75: 35000 | G75: 0 | H75: 0 | I75: IN — Div 400 — Rough carpentry & protection | J75: =H75*G75
B76: 062000 | C76: 2. Safety Protection at Footings trenches | D76: 0 | E76: LS | F76: 30000 | G76: 0 | H76: 0 | I76: IN — Div 400 — Rough carpentry & protection | J76: =H76*G76
B77: 062000 | C77: 2. Entry Barricade | D77: 0 | E77: SF | F77: 40 | G77: 0 | H77: 0 | I77: IN — Div 400 — Rough carpentry & protection | J77: =H77*G77
B78: 062000 | C78: 3. Safety at New Mezz Build outs | D78: 0 | E78: SF | F78: 2 | G78: 0 | H78: 0 | I78: IN — Div 400 — Rough carpentry & protection | J78: =H78*G78
B79: 062000 | C79: 3. Rough Carpentry work at Stage area | D79: 0 | E79: SF | F79: 5 | G79: 0 | H79: 0 | I79: IN — Div 400 — Rough carpentry & protection | J79: =H79*G79
B80: 064000 MILLWORK
B81: 064000 | C81: 1. Lobby Bar/Back Bar - Complete | D81: 0 | E81: LF | F81: 900 | G81: 0 | H81: 0 | I81: IN — Div 400 — Millwork | J81: =H81*G81
B82: 064000 | C82: 2. VIP Bar/Back Bar - Complete | D82: 0 | E82: LF | F82: 900 | G82: 0 | H82: 0 | I82: IN — Div 400 — Millwork | J82: =H82*G82
B83: 064000 | C83: 3. Music Hall GA Bar/Back Bars - Complete | D83: 0 | E83: LF | F83: 900 | G83: 0 | H83: 0 | I83: IN — Div 400 — Millwork | J83: =H83*G83
B84: 064000 | C84: 4. Mezzanine Bar/Back Bars - Complete | D84: 0 | E84: LF | F84: 900 | G84: 0 | H84: 0 | I84: IN — Div 400 — Millwork | J84: =H84*G84
B85: 064000 | C85: 5. Balcony bar/back bar- complete | D85: 0 | E85: LF | F85: 900 | G85: 0 | H85: 0 | I85: IN — Div 400 — Millwork | J85: =H85*G85
B86: 064000 | C86: 6. Upper lounge bar/back bar- complete | D86: 0 | E86: LF | F86: 900 | G86: 0 | H86: 0 | I86: IN — Div 400 — Millwork | J86: =H86*G86
B87: 064000 | C87: 7. Lower lounge bar/back bar- complete | D87: 0 | E87: LF | F87: 900 | G87: 0 | H87: 0 | I87: IN — Div 400 — Millwork | J87: =H87*G87
B88: 064000 | C88: 8. Foundry bar/back bar- complete | D88: 0 | E88: LF | F88: 900 | G88: 0 | H88: 0 | I88: IN — Div 400 — Millwork | J88: =H88*G88
B89: 064000 | C89: 9. Decorative Features Above Each Back Bar | D89: 0 | E89: EA | F89: 10000 | G89: 0 | H89: 0 | I89: IN — Div 400 — Millwork | J89: =H89*G89
B90: 064000 | C90: 10. Green room Bathrooms & Counter tops | D90: 0 | E90: LF | F90: 350 | G90: 0 | H90: 0 | I90: IN — Div 400 — Millwork | J90: =H90*G90
B91: 064000 | C91: 11. Public Bathroom Counter top | D91: 0 | E91: LF | F91: 400 | G91: 0 | H91: 0 | I91: IN — Div 400 — Millwork | J91: =H91*G91
B92: 064000 | C92: 12. Millwork at Merchandise | D92: 0 | E92: LS | F92: 12000 | G92: 0 | H92: 0 | I92: IN — Div 400 — Millwork | J92: =H92*G92
... B98: 064000 | C98: 18. Millwork at BOX Office | D98: 0 | E98: LF | F98: 500 | G98: 0 | H98: 0 | I98: IN — Div 400 — Millwork | J98: =H98*G98
B99: 075000 ROOFING
B100: 075000 | C100: 1. 2nd Floor Terrace Roof Membrane | D100: 2041 | E100: SF | F100: 32.5 | G100: 66332.5 | H100: 0 | I100: ADD — OUTDOOR TERRACE. 2,041 SF of second-floor roof deck. Programme scope — it is not needed to open the room and it is not in this model. His price, $66,333. | J100: =H100*G100
B101: 075000 | C101: 2. 2nd Floor concrete pavers on pedestals | D101: 2041 | E101: SF | F101: 31 | G101: 63271 | H101: 0 | I101: ADD — OUTDOOR TERRACE paving on pedestals, 2,041 SF. Pairs with the line above. Note this is the line whose unit price is broken on his summary sheet — $31/SF here, but the summary carries $5,224,148 against it. The detail is right and the summary is wrong. | J101: =H101*G101
B102: 075000 | C102: 3. Remove and replace roof at lower areas | D102: 0 | E102: SF | F102: 35 | G102: 0 | H102: 0 | I102: IN — Div 100 — Roof reinstatement | J102: =H102*G102
B103: 075000 | C103: 4. Temp roof above music hall | D103: 0 | E103: SF | F103: 5 | G103: 0 | H103: 0 | I103: IN — Div 100 — Roof reinstatement | J103: =H103*G103
B104: 075000 | C104: 5. Patch roofing at Misc. Penetrations | D104: 0 | E104: LS | F104: 15000 | G104: 0 | H104: 0 | I104: IN — Div 100 — Roof reinstatement | J104: =H104*G104
B105: 078100 FIREPROOFING
B106: 078100 | C106: 1. Allow for fireproofing at New steel at Roof | D106: 0 | E106: SF | F106: 5 | G106: 0 | H106: 0 | I106: IN — Div 100/300 — Fireproofing | J106: =H106*G106
B107: 078100 | C107: 2. Allow for fireproofing at New steel at Mezzanine | D107: 0 | E107: SF | F107: 5 | G107: 0 | H107: 0 | I107: IN — Div 100/300 — Fireproofing | J107: =H107*G107
B108: 078100 | C108: 3. Add fireproofing to existing roof steel | D108: 0 | E108: SF | F108: 5 | G108: 0 | H108: 0 | I108: IN — Div 100/300 — Fireproofing | J108: =H108*G108
B109: 081000 DOORS, FRAMES & HARDWARE
B110: 081000 | C110: 1. Single Hollow Metal Doors - Non-Acoustical | D110: 0 | E110: EA | F110: 1800 | G110: 0 | H110: 0 | I110: IN — Div 400 — Doors, frames & hardware | J110: =H110*G110
B111: 081000 | C111: 2. Double Hollow Metal Doors - Non-Acoustical | D111: 0 | E111: EA | F111: 2500 | G111: 0 | H111: 0 | I111: IN — Div 400 — Doors, frames & hardware | J111: =H111*G111
B112: 081000 | C112: 3. Acoustical doors at Music Hall | D112: 0 | E112: EA | F112: 6500 | G112: 0 | H112: 0 | I112: IN — Div 400 — Doors, frames & hardware | J112: =H112*G112
...
