Workbook

Sheet MT QUESTIONS
B2: 165 RANDOLPH - QUESTIONS ON THE 16 SEP MASTER DEVELOPMENT BUDGET
B3: Matthew Teper, 17 Sep 2026. Every question is written beside the line it refers to, in a new right-hand column on each of your sheets. Highlighted cells are the ones asked about. None of your cells have been changed.
B5: WHERE THE NUMBERS STAND
B6: Master Development Budget, 16 Sep | C6: 89084591 | D6: $1,202/SF on 74,100 SF; your sheet shows $655/SF on 135,953
B7: Our V3, rebuilt on the measured RFEM steel | C7: 77897555 | D7: $1,051/SF. Same programme, 997.2 short tons priced by the ton
B8: Yours after the corrections that survive the takeoff | C8: 77247828 | D8: 0.8% from ours
B9: Trade cost reconciliation, our extract vs your D25 | C9: 0 | D9: 309 lines, variance $0.00
B11: THE FIVE WE NEED FIRST
B12: -1. | C12: Budget Summary D67 - the contingency formula is 10% of the whole project, not of soft costs and FF&E as labelled.
B13: 0. | C13: Budget Summary D30 - escalation on the building is blank.
B14: 1. | C14: Budget Summary D26 - what is in the $12,000,000 and when is it priced? We expect it to go UP.
B15: 2. | C15: General Conditions tab vs Breakdown division 013000 - the same function in two places, $6,175,000 combined.
B16: 3. | C16: Breakdown 015800-1 - the $4,000,000 lump vs the $2,589,800 of backup beneath it.
B18: TWO THINGS WE HAD WRONG AND ARE WITHDRAWING
C19: The roof: we had assumed a lift. The RFEM model is a rebuild - 62.4% of column steel starts at grade, all 517 truss members are new at +56.5 to +64.5 ft. Your 74,000 SF of roof demolition is the method, not an error.
C20: The area: we had called 135,953 SF wrong. We can no longer prove that - the model carries 146,508 SF gross. We are now only asking where the number comes from, and for one agreed area schedule derived from the test fit.
B22: INDEX OF EVERY QUESTION
B23: Sheet | C23: Cell | D23: Your line | E23: Our question
B24: Budget Summary | C24: D21 | D24: Parking Garage - 260/spaces | E24: Formula is =86*25000 but the label says 260 spaces. Which is right? And is off-site parking in this deal at all? We carry none.
B25: Budget Summary | C25: D26 | D25: Trade Costs To Be Priced | E25: What scope is inside the $12,000,000, and when can it be priced? Our measured structure alone is $16,710,249 (997.2 short tons off the RFEM takeoff), and this plug also has to cover millwork, doors, glazing, tile, fireproofing and drywall. We expect it to go UP when priced.
B26: Budget Summary | C26: D27 | D26: General Conditions | E26: $3,141,000 here PLUS $3,034,000 of division 013000 inside the trade cost = $6,175,000, 12.36% of trade. Schimenti ran 7.80% and 8.90% at 555 Johnson. Which is the one we are paying? We hold 8.5%.
B27: Budget Summary | C27: D28 | D27: OH&P 9% | E27: =SUM(D25:D27)*0.09 charges the 9% on trade + the $12M plug + general conditions. Fee on your own GC is $555,750; fee on unpriced scope is $1,080,000. Can the fee be a fixed dollar amount, and come off both?
B28: Budget Summary | C28: D29 | D28: Contractor Contingency 10% | E28: =SUM(D25:D28)*0.1 is 10% on a base that already holds the 9% OH&P. Intentional? We hold ONE owner contingency of $5,000,000 below the line.
B29: Budget Summary | C29: D30 | D29: Escalation | E29: Blank in all three versions of this file, while the parking garage gets 5% on D22. On a 20-month programme what should the building carry? We hold 10%.
B30: Budget Summary | C30: I31 | D30: $/SF | E30: I31 divides by 135,953. On the 74,100 SF footprint this is $859/SF.
B31: Budget Summary | C31: D45 | D31: Project Management (Live Nation) | E31: This is our own team, not Live Nation. Same $520,000 in our budget - just the label.
B32: Budget Summary | C32: D67 | D32: Soft Costs & FFE Contingency 10% | E32: Label says Soft Costs & FFE. Formula is =(D23+D31+D47+D65)*0.1 = 10% of the WHOLE PROJECT, on top of the contractor contingency already inside D31. As labelled it would be $1,507,723. $578,648 of it is contingency on contingency. Which is intended?
B33: Budget Summary | C33: D69 | D33: Total Capital | E33: Ours: V3 $77,897,555 on the same programme, measured steel. Apply only the corrections that survive the takeoff and this cell becomes about $77,247,828 - 0.8% from ours.
B34: Budget Summary | C34: D71 | D34: $ PER SF | E34: Divides by 135,953 SF. Where does that number come from? We cannot find a schedule or calculation behind it. On 74,100 SF this total is $1,202/SF. Both are true; please label which.
B35: Budget Summary | C35: B8 | D35: SF: 135,953 | E35: 135,953 SF appears here and in 6 formula cells. Source? The RFEM model has 146,508 SF gross / 120,119 SF enclosed floor; the test fit governs at 74,100 SF footprint. 555 Johnson at $208.63/SF is 134,993 SF - please rule that out.
B36: Budget Summary | C36: A9 | E36: Dated 7 Sep; the Breakdown tab says 16 Sep. Which is current?
B37: General Conditions | C37: E13 | E37: This tab is the best-evidenced page in the file and we would rather build on it than argue with it. Is the $3,141,000 the ONLY place general conditions lives? Division 013000 on the Breakdown carries site office, field tech, safety, toilets, protection, clean-up, rubbish and final clean for another $3,034,000.
B38: General Conditions | C38: C4 | E38: 90 weeks - is that construction only, or does it include pre-con and closeout? Can we see it as a rate x duration so that shortening the programme visibly shortens the cost?
B39: General Conditions | C39: C9 | E39: Three superintendents for the full 90 weeks each - all three for the whole period, or overlapping phases?
B40: Building & Fit-out Breakdown | C40: F23 | D40: Project Labor $2,000,000 | E40: Crew, rate and weeks? The General Conditions tab already funds three supers + a general super for 90 weeks. No quantity behind this line.
B41: Building & Fit-out Breakdown | C41: F16 | E41: What is included in Field Technology at $200,000?
B42: Building & Fit-out Breakdown | C42: F27 | D42: 013000 subtotal $3,034,000 | E42: All of this division reads as general conditions. Is it meant to sit inside trade cost AND under the GC line on the summary? We think it is one function in two places.
B43: Building & Fit-out Breakdown | C43: F30 | D43: Sidewalk bridge $4,000,000 | E43: The lump says $4,000,000. The two rows beneath it - 1,126 LF @ $500 and 27,024 SF @ $75 - foot to $2,589,800. Which is right? And how many LF of PUBLIC sidewalk does the building front? A shed is only required where there is one; the alleys and lot lines have none. We carry 1,089 LF perimeter x $210 erected + 24 months rental.
B44: Building & Fit-out Breakdown | C44: F33 | D44: Interior scaffolding $2,000,000 | E44: What is being staged, at what rate, for how many weeks? The high roof is only 8.65 lb/SF of short-span W12/W6 framing - not a heavy erection. And the ground-supported stage and production towers are erected FIRST; can they carry the access instead of renting it twice?
B45: Building & Fit-out Breakdown | C45: F58 | D45: Demo pre-cast roof 74,000 SF | E45: Confirms the REBUILD method, which the RFEM model also uses and which we now accept. Separate question: is the existing roof genuinely pre-cast concrete? It decides whether a PARTIAL lift over the 27,393 SF high-roof zone is even possible.
B46: Building & Fit-out Breakdown | C46: F93 | D46: 033000 subtotal $177,450 | E46: Nearly every line zero quantity - no footings, no stage slab, no mezzanine deck pour, no base-plate grout. The takeoff gives 124 footing locations (up from 81 in Rev 43). We carry $2,543,000 of foundations.
B47: Building & Fit-out Breakdown | C47: F151 | D47: 055100 STRUCTURAL STEEL $0 | E47: ALL 19 LINES ZERO. The RFEM takeoff (VE1) gives 997.2 SHORT TONS: beams/girders 508.4, columns 360.6, trusses 67.7, braces 40.2, CFS 20.3 (11,557 LF). Please price off the lb column - the file's 't' column is metric tonnes (904.6) and using it understates steel by 10.2%. Your own $6,000/TON on line 2 is right for rolled framing.
B48: Building & Fit-out Breakdown | C48: E131 | D48: Trusses/girders/columns @ $6,000/TON | E48: 202.0 tons of the columns are BUILT-UP PLATE GIRDERS (I 48/24 through I 69.023/24, 60 LF each on grids B and E), not rolled shapes. Does $6,000/TON apply to shop-welded plate? We carry $8,400.
B49: Building & Fit-out Breakdown | C49: E140 | D49: Stage lighting & AV support @ $8/LB | E49: Your $8.00/LB here corroborates our ground-supported rigging grid, which works out to $9.21/LB. Note: the stage carries the rigging, not the roof. Please confirm the roof design loads EXCLUDE production rigging.
B50: Building & Fit-out Breakdown | C50: F182 | D50: 064000 MILLWORK $0 | E50: Every bar and back bar at $2,000/LF with no linear feet - but 220000 already carries NINE bars roughed at $30,000 each. Nate can give you the LF off the test fit. We carry $510,500 of millwork.
B51: Building & Fit-out Breakdown | C51: F204 | D51: 078100 FIREPROOFING $0 | E51: All three lines zero at $5.00/SF. On ~107,000 SF of new deck and roof that is about $536,000 at your own rate.
B52: Building & Fit-out Breakdown | C52: F213 | D52: 081000 DOORS $0 | E52: Zero, including every acoustical door and pair into the music hall at $10,000 / $20,000. We carry $546,800.
B53: Building & Fit-out Breakdown | C53: F229 | D53: 084100 STOREFRONT $0 | E53: Zero. We carry $292,000 for storefront and glazing together.
... B58: Building & Fit-out Breakdown | C58: C366 | D58: 2nd floor sprinklers 50,000 SF | E58: 50,000 SF. The RFEM model measures the mezzanine at 32,942 SF + 13,077 SF tiered seating = 46,019 SF. Close - can you confirm the basis?
B59: Building & Fit-out Breakdown | C59: C365 | E59: 69,000 SF - the footprint is 74,100 SF. Should this be higher?
B60: Building & Fit-out Breakdown | C60: C383 | D60: Fixture counts | E60: 178 WC + 154 lavs + 51 urinals across the building at $4,000 each. Can we see the CODE FIXTURE CALCULATION behind the count? We are at $1,757,502 vs your $3,717,250 and one of us is wrong - settleable in an afternoon.
B61: Building & Fit-out Breakdown | C61: C398 | E61: Nine bars roughed here - so the building knows it has nine bars, but 064000 prices none of them.
B62: Building & Fit-out Breakdown | C62: F415 | D62: HVAC 132,542 SF @ $45 | E62: ONE LINE, 132,542 SF x $45.00, no tonnage. Was this priced on a LOAD or an AREA? A 64 ft clear room with 7,440 people is a volume and occupancy load. Can we see tons and the basis? Ours is $5,950,650 built from load - almost the same total, which is a coincidence not agreement.
B63: Building & Fit-out Breakdown | C63: F427 | D63: I/O lighting package $1,631,436 | E63: 'PROVIDED BY OTHERS' - is this yours or ours? FF&E line 310 separately carries $1,750,000 of Architectural & Exterior Lighting. That is $3,381,436 of architectural lighting in one budget. Keep the conduit and wiring here, delete the fixtures?
B64: Building & Fit-out Breakdown | C64: F447 | E64: Two 4,000A boards = 8,000A service, matches our sizing. Is this confirmed with Con Ed - is there a feasibility letter?
B65: Building & Fit-out Breakdown | C65: F451 | E65: $250,000 allowance - has Con Ed responded on the 8,000A service and the vault?
B66: Building & Fit-out Breakdown | C66: F478 | E66: Adopting this. We had not carried VESDA and you are right that a 64 ft volume with haze and pyro needs it.
B67: Building & Fit-out Breakdown | C67: C477 | E67: 135,953 SF basis - see the area question on the summary sheet.
B68: Soft Cost & FF&E Budget Detail | C68: E14 | D68: Roof Abatement | E68: 70,000 SF @ $21 = $1,470,000. Where does $21/SF come from, and has anyone SAMPLED the roof? No ACP-5 exists. We carry $7.50/SF. Also: this sits in soft costs; we carry abatement as a trade.
B69: Soft Cost & FF&E Budget Detail | C69: E26 | D69: A&E $3,100,000 | E69: One $3,100,000 lump with architecture, MEP and structural all 'carried in line #3'. Can it be split? We cannot tell whether structural is funded at the level the RFEM model needs.
B70: Soft Cost & FF&E Budget Detail | C70: E54 | D70: Acoustical $15,000 | E70: $15,000 is testing. Is there an acoustic DESIGN fee anywhere? We carry $200,000 - next to residential it is the licence to operate.
B71: Soft Cost & FF&E Budget Detail | C71: E74 | D71: Permit fees 1.3% | E71: 1.3% of trade cost - understood, so this falls automatically as trade moves. Is 1.3% right for a project filing an ST structural permit at +64 ft 6 in? We carry a separate $120,000 for the ST filing and expediting; we cannot find it here.
B72: Soft Cost & FF&E Budget Detail | C72: E93 | D72: Attorney Fees $0 | E72: Attorney fees $0. Is the SLA application, the cabaret question and the theater use-classification filing genuinely inside the $342,000 already spent? On a comparable project the liquor licence was approved at zero and came in at $250,000. We carry $250,000.
B73: Soft Cost & FF&E Budget Detail | C73: E101 | D73: Controlled inspections $50,000 | E73: $50,000 on a job with new structural steel, welding, fireproofing, sprinklers and a new 8,000A service. We carry $140,000. Does this cover NYC special inspections?
B74: Soft Cost & FF&E Budget Detail | C74: E105 | D74: Project Management | E74: Same $500,000 in our budget - no question on the number. Only the '(Live Nation)' label on the summary sheet; this is our team.
B75: Soft Cost & FF&E Budget Detail | C75: E128 | D75: GA folding chairs | E75: 3,714 @ $125 = $464,250, plus 657 box chairs @ $300 below. HOLDING - seat count is a licensing determination (theater classification drives the liquor licence) and counsel has not ruled. Not a pricing disagreement. We carry 720 removable @ $25.
B76: Soft Cost & FF&E Budget Detail | C76: E156 | D76: Bar & kitchen equipment | E76: Your note above - '* BPT: 26 POS / Prep Kitchen / 1 Walk-in Cooler $837K' - is the most useful line in the file. Against it, 74 bar positions here at $9,000 = $666,000 looks LIGHT to us, and so do our 53. Is it?
B77: Soft Cost & FF&E Budget Detail | C77: E168 | D77: Freight & Installation $375,000 | E77: $375,000 is 40% of the equipment above it. Freight and install only, or does it carry something else?
B78: Soft Cost & FF&E Budget Detail | C78: E222 | D78: Metal Detectors | E78: 1 allowance, $70,000 - how many screening lanes does that buy? We carry 12 walk-through units for a 7,440 house.
B79: Soft Cost & FF&E Budget Detail | C79: E289 | D79: Soft goods $500,000 | E79: $500,000, and the note excludes the mezzanine-edge cutdown drape. Your own benchmark note on the Production subtotal says Soft Goods $725k. Which is right? We are at $220,000 and think we are light.
... B84: Building & Fit-outBudget Detail | C84: C50 | D84: GL / Builder's Risk $0 | E84: G.L. $0 and Builder's Risk $0 - both genuinely inside the 9% combined? Schimenti's equivalent line at 555 Johnson says 'Builder's Risk - Excluded' in writing. Can your broker quote both SEPARATELY, and quote an owner-controlled programme? We carry $385,000.
B85: Building & Fit-outBudget Detail | C85: C47 | E85: 'Carried in budget summary' - and also carried as division 013000 in trade cost. One function, two places.

Sheet Budget Summary
A1: 165 Randolph St. Brooklyn NY
A2: Warehouse Conversion / Add Second Level & Roof Deck
A3: Theater GA Standing: 7,440
A4: Theater GA Seated: 5,954
A5: Eating & Drinking : 769
A6: VIP Lounge
A8: SF: | B8: 135, 953 | J8: =130000*600 | L8: 135,953 SF appears here and in 6 formula cells. Source? The RFEM model has 146,508 SF gross / 120,119 SF enclosed floor; the test fit governs at 74,100 SF footprint. 555 Johnson at $208.63/SF is 134,993 SF - please rule that out.
A9: 46272 | L9: Dated 7 Sep; the Breakdown tab says 16 Sep. Which is current?
A10: Version #: 1
A13: Construction Duration: 20 Months
A14: Expected Certificate of Occupancy: TBD
A15: Expected Frist Show:
A16: Project Completion:
D19: Budget Total | F19: 2023 | G19: 2024 | H19: 2025 | L19: OUR QUESTION / ANALYSIS (MT, 17 Sep)
A20: 000 | B20: OFF SITE COSTS
B21: Parking Garage - 260/spaces | D21: =86*25000 | F21: 0 | G21: 0 | H21: 0 | L21: Formula is =86*25000 but the label says 260 spaces. Which is right? And is off-site parking in this deal at all? We carry none.
B22: Escalation (Calculated at 5%) | D22: =D21*0.05 | F22: 0 | G22: 0 | H22: 0
D23: =SUM(D21:D22) | F23: 0 | G23: 0 | H23: 0
A24: 100 | B24: Building & Fit-Out Costs
B25: Trade Costs | D25: ='Building & Fit-outBudget Detail'!C49-'Building & Fit-outBudget Detail'!C47 | F25: 0 | G25: 0 | H25: 0
B26: Trade Costs To Be Priced | D26: 12000000 | L26: What scope is inside the $12,000,000, and when can it be priced? Our measured structure alone is $16,710,249 (997.2 short tons off the RFEM takeoff), and this plug also has to cover millwork, doors, glazing, tile, fireproofing and drywall. We expect it to go UP when priced.
B27: General Conditions and General Requirements | D27: 3141000 | F27: 0 | G27: 0 | H27: 0 | I27: 90 wks | L27: $3,141,000 here PLUS $3,034,000 of division 013000 inside the trade cost = $6,175,000, 12.36% of trade. Schimenti ran 7.80% and 8.90% at 555 Johnson. Which is the one we are paying? We hold 8.5%.
B28: Overhead, Profit & Insurance (9% Combined) | D28: =SUM(D25:D27)*0.09 | F28: 0 | G28: 0 | H28: 0 | L28: =SUM(D25:D27)*0.09 charges the 9% on trade + the $12M plug + general conditions. Fee on your own GC is $555,750; fee on unpriced scope is $1,080,000. Can the fee be a fixed dollar amount, and come off both?
B29: Contractor Contingency 10% | D29: =SUM(D25:D28)*0.1 | F29: 0 | G29: 0 | H29: 0 | L29: =SUM(D25:D28)*0.1 is 10% on a base that already holds the 9% OH&P. Intentional? We hold ONE owner contingency of $5,000,000 below the line.
B30: Escalation (Calculated at 5%) | F30: 0 | G30: 0 | H30: 0 | L30: Blank in all three versions of this file, while the parking garage gets 5% on D22. On a 20-month programme what should the building carry? We hold 10%.
D31: =SUM(D25:D30) | F31: 0 | G31: 0 | H31: 0 | I31: =D31/135953 | L31: I31 divides by 135,953. On the 74,100 SF footprint this is $859/SF.
A32: 200 | B32: Soft Costs
B33: Abatement | D33: ='Soft Cost & FF&E Budget Detail'!E16 | F33: 0 | G33: 0 | H33: 0
B34: Feasibility Study | D34: ='Soft Cost & FF&E Budget Detail'!E21
B35: Architectural / Engineering / Consultant Fees | D35: ='Soft Cost & FF&E Budget Detail'!E38 | F35: 0 | G35: 0 | H35: 0
B36: Site & Civil | D36: ='Soft Cost & FF&E Budget Detail'!E43 | F36: 0 | G36: 0 | H36: 0
B37: Traffic Engineering | D37: ='Soft Cost & FF&E Budget Detail'!E51
B38: Acousticsl Engineering | D38: ='Soft Cost & FF&E Budget Detail'!E58
B39: Geotechnical Engineering | D39: ='Soft Cost & FF&E Budget Detail'!E66
B40: Enviromental Studies | D40: ='Soft Cost & FF&E Budget Detail'!E71
B41: Zoning/Permit Fees | D41: ='Soft Cost & FF&E Budget Detail'!E82 | F41: 0 | G41: 0 | H41: 0
B42: Utility Connection Fees | D42: ='Soft Cost & FF&E Budget Detail'!E90
B43: Attorney Fees | D43: ='Soft Cost & FF&E Budget Detail'!E98
B44: Testing / Quality Control | D44: ='Soft Cost & FF&E Budget Detail'!E103 | F44: ='Soft Cost & FF&E Budget Detail'!E103 | G44: 0 | H44: 0
B45: Project Management (Live Nation) | D45: ='Soft Cost & FF&E Budget Detail'!E109 | F45: 0 | G45: 0 | H45: 0 | L45: This is our own team, not Live Nation. Same $520,000 in our budget - just the label.
B46: Reimbursable Expenses | D46: ='Soft Cost & FF&E Budget Detail'!E118 | F46: 0 | G46: 0 | H46: 0
D47: =SUM(D33:D46) | F47: =SUM(F33:F46) | G47: =SUM(G33:G46) | H47: =SUM(H33:H46) | I47: =D47/135953
A48: 300 | B48: FF&E Costs
B49: Seating & Furniture | D49: ='Soft Cost & FF&E Budget Detail'!E152 | F49: 0 | G49: 0 | H49: 0
B50: Kitchen & Bar Equipment | D50: ='Soft Cost & FF&E Budget Detail'!E174-'Soft Cost & FF&E Budget Detail'!E171 | F50: 0 | G50: 0 | H50: 0
B51: POS | D51: ='Soft Cost & FF&E Budget Detail'!E171 | F51: 0 | G51: 0 | H51: 0
B52: CCTV | D52: ='Soft Cost & FF&E Budget Detail'!E180 | F52: 0 | G52: 0 | H52: 0
B53: Data (Wifi & Network) Systems | D53: ='Soft Cost & FF&E Budget Detail'!E181-'Soft Cost & FF&E Budget Detail'!E180 | F53: 0 | G53: 0 | H53: 0
B54: Office Furniture | D54: ='Soft Cost & FF&E Budget Detail'!E195 | F54: 0 | G54: 0 | H54: 0
B55: Exterior Signage / Wayfinding | D55: ='Soft Cost & FF&E Budget Detail'!E206+'Soft Cost & FF&E Budget Detail'!E201 | F55: 0 | G55: 0 | H55: 0
B56: Interior Art & Décor "Warehouse Scope" | D56: ='Soft Cost & FF&E Budget Detail'!E210 | F56: 0 | G56: 0 | H56: 0
B57: Administration | D57: ='Soft Cost & FF&E Budget Detail'!E226 | F57: 0 | G57: 0 | H57: 0
B58: Facility | D58: ='Soft Cost & FF&E Budget Detail'!E241
B59: Operations | D59: ='Soft Cost & FF&E Budget Detail'!E271
B60: Production - FF&E | D60: ='Soft Cost & FF&E Budget Detail'!E286 | F60: 0 | G60: 0 | H60: 0
B61: Production - Soft Goods | D61: ='Soft Cost & FF&E Budget Detail'!E290 | F61: 0 | G61: 0 | H61: 0
B62: Production - Audio & Video System | D62: ='Soft Cost & FF&E Budget Detail'!E302+'Soft Cost & FF&E Budget Detail'!E298 | F62: 0 | G62: 0 | H62: 0
B63: Production - Performance Lighting | D63: ='Soft Cost & FF&E Budget Detail'!E307
B64: Architectural Lighting | D64: ='Soft Cost & FF&E Budget Detail'!E316 | F64: 0 | G64: 0 | H64: 0
D65: =SUM(D49:D64) | F65: =SUM(F49:F64) | G65: =SUM(G49:G64) | H65: =SUM(H49:H64) | I65: =D65/135953
A67: 400 | B67: Soft Costs & FFE Contingency 10% | D67: =(D23+D31+D47+D65)*0.1 | F67: 0 | G67: 0 | H67: 0 | I67: =D67/135953 | L67: Label says Soft Costs & FFE. Formula is =(D23+D31+D47+D65)*0.1 = 10% of the WHOLE PROJECT, on top of the contractor contingency already inside D31. As labelled it would be $1,507,723. $578,648 of it is contingency on contingency. Which is intended?
B68: \
B69: Total Capital | D69: =D23+D67+D65+D47+D31 | F69: =F67+F65+F47+F31 | G69: =G67+G65+G47+G31 | H69: =H67+H65+H47+H31 | L69: Ours: V3 $77,897,555 on the same programme, measured steel. Apply only the corrections that survive the takeoff and this cell becomes about $77,247,828 - 0.8% from ours.
B71: $ PER SF | D71: =D69/135953 | I71: =SUM(I67+I65+I47+I31) | L71: Divides by 135,953 SF. Where does that number come from? We cannot find a schedule or calculation behind it. On 74,100 SF this total is $1,202/SF. Both are true; please label which.

Sheet Soft Cost & FF&E Budget Detail
A1: 165 Randolph St Brooklyn NY
A2: Scope : | B2: Warehouse Conversion / Add Second Level & Roof Decks
A3: Capacity: | B3: ##
A4: SF: | B4: 135953
A5: Date:
A6: Version: | B6: 1
A10: 200 | B10: SOFT COSTS
A11: 201 | B11: DESCRIPTION | C11: QTY | D11: UNIT PRICE | E11: BUDGET TOTAL | F11: NOTES | G11: OUR QUESTION / ANALYSIS (MT, 17 Sep)
B12: Abatement
A13: 1 | B13: Pipe Insulation Abatement | C13: 190 | D13: 72 | E13: =C13*D13
A14: 2 | B14: Roof Abatement | C14: 70000 | D14: 21 | E14: =C14*D14 | G14: 70,000 SF @ $21 = $1,470,000. Where does $21/SF come from, and has anyone SAMPLED the roof? No ACP-5 exists. We carry $7.50/SF. Also: this sits in soft costs; we carry abatement as a trade.
B16: Total Abatement | E16: =SUM(E13:E15)
A17: 202 | B17: DESCRIPTION | C17: QTY | D17: UNIT PRICE | E17: BUDGET TOTAL | F17: NOTES
B18: Feasibility Study
A19: 1 | B19: Due Diligence & Feasibility Study | C19: 1 | D19: 342000 | E19: =C19*D19
B21: Total Feasibility Study | E21: =E19
A22: 203 | B22: DESCRIPTION | C22: QTY | D22: UNIT PRICE | E22: BUDGET TOTAL | F22: NOTES
B23: Architectural Fees
A24: 1 | B24: Conceptual & Brand Development | C24: 1 | D24: 45000 | E24: =C24*D24
A25: =A24+1 | B25: Interior Design | C25: 1 | D25: 90000 | E25: =C25*D25
A26: =A25+1 | B26: Architecture & Engineering | C26: 1 | D26: 3100000 | E26: =C26*D26 | G26: One $3,100,000 lump with architecture, MEP and structural all 'carried in line #3'. Can it be split? We cannot tell whether structural is funded at the level the RFEM model needs.
A27: =A26+1 | B27: Architecture | D27: 0 | E27: =C27*D27 | F27: Carried in line #3
A28: =A27+1 | B28: MEP Engineering | D28: 0 | E28: =C28*D28 | F28: Carried in line #3
A29: =A28+1 | B29: Structural Engineering | D29: 0 | E29: =C29*D29 | F29: Carried in line #3
A30: =A29+1 | B30: MEP Consultant | C30: 1 | D30: 30000 | E30: =C30*D30
A31: =A30+1 | B31: Lighting Design (Bandit) | C31: 1 | D31: 51000 | E31: =C31*D31
A32: =A31+1 | B32: Kitchen Equipment Design (TriMark) | C32: 1 | D32: 20000 | E32: =C32*D32
A33: =A32+1 | B33: LV/AV Design | C33: 1 | D33: 35000 | E33: =C33*D33
A34: =A33+1 | B34: Signage & Way Finding Design | C34: 1 | D34: 75000 | E34: =C34*D34
A35: =A34+1 | B35: Renderings | C35: 1 | D35: 50000 | E35: =C35*D35
A36: =A35+1 | B36: Reimbursables | C36: 1 | D36: 30000 | E36: =C36*D36
B38: Total Architectural Fees | E38: =SUM(E24:E37)
A39: 204 | B39: DESCRIPTION | C39: QTY | D39: UNIT PRICE | E39: BUDGET TOTAL | F39: NOTES
B40: Civil Engineering
A41: 1 | B41: Civil Engineering | C41: 1 | D41: 10000 | E41: =C41*D41 | F41: Exterior work: New Sidewalks, Street Work
B43: Total Civil Engineering | E43: =SUM(E41:E41)
A44: 205 | B44: DESCRIPTION | C44: QTY | D44: UNIT PRICE | E44: BUDGET TOTAL | F44: NOTES
B45: Traffic Engineering
A46: 1 | B46: Traffic Engineering | C46: 1 | D46: 10000 | E46: =C46*D46 | F46: Verify w/ Traffic Consultant Report
A47: 2 | D47: 0 | E47: =C47*D47
B51: Total Traffic Engineering | E51: =SUM(E46:E50)
A52: 206 | B52: DESCRIPTION | C52: QTY | D52: UNIT PRICE | E52: BUDGET TOTAL | F52: NOTES
B53: Acoustical Engineering
A54: 1 | B54: Sound and Vibration Testing | C54: 1 | D54: 15000 | E54: =C54*D54 | F54: Sound & Vibration Testing / Design Documentation & Consulting | G54: $15,000 is testing. Is there an acoustic DESIGN fee anywhere? We carry $200,000 - next to residential it is the licence to operate.
A56: 4 | D56: 0 | E56: =C56*D56
A57: 5 | D57: 0 | E57: =C57*D57
B58: Total Acoustical Engineering | E58: =SUM(E54:E57)
A59: 207 | B59: DESCRIPTION | C59: QTY | D59: UNIT PRICE | E59: BUDGET TOTAL | F59: NOTES
B60: Geotechnical Engineering
A61: 1 | B61: Geotechnical Engineering | C61: 1 | D61: 150000 | E61: =C61*D61 | F61: 13 Borings 50' deep required for ST Permit
B66: Total Geotechnical Engineering | E66: =SUM(E61:E65)
A67: 208 | B67: DESCRIPTION | C67: QTY | D67: UNIT PRICE | E67: BUDGET TOTAL | F67: NOTES
B68: Environmental Studies
A69: 1 | B69: Carried in Feasibility Study | E69: =C69*D69
B71: Total Environmental Studies | E71: =SUM(E69:E70)
A72: 209 | B72: DESCRIPTION | C72: QTY | D72: UNIT PRICE | E72: BUDGET TOTAL | F72: NOTES
B73: Zoning / Permit Fees
A74: 1 | B74: Permit fees & plan review fees | C74: 1 | D74: ='Budget Summary'!D25*0.013 | E74: =C74*D74 | F74: 1.3% Trade Costs | G74: 1.3% of trade cost - understood, so this falls automatically as trade moves. Is 1.3% right for a project filing an ST structural permit at +64 ft 6 in? We carry a separate $120,000 for the ST filing and expediting; we cannot find it here.
A75: =A74+1 | B75: Special Projects Program | C75: 1 | D75: 50000 | E75: =C75*D75
A76: 3 | B76: MEP and misc. permit fees | C76: 1 | D76: 10000 | E76: =C76*D76
A77: 4 | B77: Expeditor (allowance for Addt'l services) | C77: 0 | E77: =C77*D77
A78: 5 | B78: FA Consultant & Expediting Services | C78: 1 | D78: 35000 | E78: =C78*D78 | F78: Consulting/ Filing/ FA Inspection Filing & Inspection Scheduling/ TCO Affidavit/ FDNY NOD
A79: 6 | B79: Fire Safety & Emergency Action Plan | C79: 1 | D79: 21500 | E79: =C79*D79
A80: 7 | B80: Fire Protection Plan & Filing with FDNY | C80: 1 | D80: 18500 | E80: =C80*D80
B82: Total Zoning / Permit Fees | E82: =SUM(E74:E80)
A83: 210 | B83: DESCRIPTION | C83: QTY | D83: UNIT PRICE | E83: BUDGET TOTAL | F83: NOTES
B84: Utility Connection Fees
A85: 1 | B85: Electrical Service Upgrade | C85: 1 | D85: 50000 | E85: =C85*D85 | F85: Service upgrade required. Vault located in street, new conduit and feeders from vault into MPOE electrical room. Only Con Ed costs carried.
B90: Total Utility Connection Fees | E90: =SUM(E85:E89)
A91: 211 | B91: DESCRIPTION | C91: QTY | D91: UNIT PRICE | E91: BUDGET TOTAL | F91: NOTES
B92: Attorney Fees
A93: 1 | B93: SLA Legal Fees carried in Feasibility DD | C93: 0 | D93: 0 | E93: =C93*D93 | G93: Attorney fees $0. Is the SLA application, the cabaret question and the theater use-classification filing genuinely inside the $342,000 already spent? On a comparable project the liquor licence was approved at zero and came in at $250,000. We carry $250,000.
B98: Total Attorney Fees | E98: =SUM(E93:E97)
A99: 212 | B99: DESCRIPTION | C99: QTY | D99: UNIT PRICE | E99: BUDGET TOTAL | F99: NOTES
B100: Testing / Quality Control
A101: 1 | B101: Controlled inspections | C101: 1 | D101: 50000 | E101: =C101*D101 | G101: $50,000 on a job with new structural steel, welding, fireproofing, sprinklers and a new 8,000A service. We carry $140,000. Does this cover NYC special inspections?
A102: 2
B103: Total Testing / Quality Control | E103: =SUM(E101:E102)
A104: 213 | B104: DESCRIPTION | C104: QTY | D104: UNIT PRICE | E104: BUDGET TOTAL | F104: NOTES
B105: Project Management | G105: Same $500,000 in our budget - no question on the number. Only the '(Live Nation)' label on the summary sheet; this is our team.
A106: 1 | B106: Project Management | C106: 1 | D106: 500000 | E106: =C106*D106
A107: =A106+1 | B107: Estimating Services | C107: 1 | D107: 20000 | E107: =C107*D107
A108: =A107+1 | D108: 0 | E108: =C108*D108
B109: Total Miscellaneous | E109: =SUM(E106:E108)
A110: 214 | B110: DESCRIPTION | C110: QTY | D110: UNIT PRICE | E110: BUDGET TOTAL | F110: NOTES
B111: Reimbursable Expenses
A112: 1 | C112: 0 | D112: 0 | E112: =C112*D112
A114: =A113+1 | D114: 0 | E114: =C114*D114
A115: 4 | D115: 0 | E115: =C115*D115
A116: =A115+1 | D116: 0 | E116: =C116*D116
A117: =A116+1 | D117: 0 | E117: =C117*D117
B118: Total Reimbursable Expenses | E118: =SUM(E112:E117)
B120: TOTAL SOFT COSTS | E120: =E109+E103+E98+E90+E82+E71+E66+E58+E51+E43+E38+E21+E16+E118
A124: 300 | B124: FF&E COSTS
A125: SEATING & FURNITURE
A126: 301 | B126: DESCRIPTION | C126: QTY | D126: UNIT PRICE | E126: BUDGET TOTAL | F126: VENDOR | G126: NOTES
B127: Seating and Accessories
A128: =A127+1 | B128: Theater Ground Floor GA Cushioned Folding Chairs | C128: 3714 | D128: 125 | E128: =D128*C128 | G128: 3,714 @ $125 = $464,250, plus 657 box chairs @ $300 below. HOLDING - seat count is a licensing determination (theater classification drives the liquor licence) and counsel has not ruled. Not a pricing disagreement. We carry 720 removable @ $25.
A129: =A128+1 | B129: Mezzanine Level Box Chairs | C129: 657 | D129: 300 | E129: =D129*C129
A130: =A129+1 | B130: Mezzanine Level Elevated Chairs | C130: 63 | D130: 300 | E130: =D130*C130
...

Sheet Building & Fit-outBudget Detail
A1: Venue
A2: Scope : | B2: ='Soft Cost & FF&E Budget Detail'!B2
A3: Capacity: | B3: 7440
A4: SF: | B4: ='Soft Cost & FF&E Budget Detail'!B4
A5: Date: | B5: 46281
A6: Version: | B6: ='Soft Cost & FF&E Budget Detail'!B6
A9: 100 | B9: BUILDING & FIT-OUT COSTS
A10: CSI # | B10: TRADE | C10: BUDGET | D10: COST/SF | E10: NOTES | G10: OUR QUESTION / ANALYSIS (MT, 17 Sep)
A11: 013000 | B11: PROJECT REQUIREMENTS | C11: ='Building & Fit-out Breakdown'!F27 | D11: =C11/$B$4
A12: 015800 | B12: SCAFFOLDING & STAGING | C12: ='Building & Fit-out Breakdown'!F37 | D12: =C12/$B$4
A13: 024100 | B13: DEMOLITION | C13: ='Building & Fit-out Breakdown'!F63 | D13: =C13/$B$4
A14: 033000 | B14: CONCRETE | C14: ='Building & Fit-out Breakdown'!F93 | D14: =C14/$B$4
A15: 042000 | B15: MASONRY | C15: ='Building & Fit-out Breakdown'!F119 | D15: =C15/$B$4
A16: 044000 | B16: STONE & CERAMICS | C16: ='Building & Fit-out Breakdown'!F127 | D16: =C16/$B$4
A17: 055100 | B17: STRUCTURAL STEEL & MISC METALS | C17: ='Building & Fit-out Breakdown'!F151 | D17: =C17/$B$4
A18: 061000 | B18: ROUGH CARPENTRY | C18: ='Building & Fit-out Breakdown'!F160 | D18: =C18/$B$4
A19: 064000 | B19: MILLWORK AND FURNITURE INSTALL | C19: ='Building & Fit-out Breakdown'!F182 | D19: =C19/$B$4
A20: 075000 | B20: ROOFING | C20: ='Building & Fit-out Breakdown'!F196 | D20: =C20/$B$4
A21: 078100 | B21: FIREPROOFING | C21: ='Building & Fit-out Breakdown'!F204 | D21: =C21/$B$4
A22: 081000 | B22: DOORS, FRAMES & HARDWARE | C22: ='Building & Fit-out Breakdown'!F213 | D22: =C22/$B$4
A23: 083000 | B23: SPECIAL DOORS | C23: ='Building & Fit-out Breakdown'!F219 | D23: =C23/$B$4
A24: 084100 | B24: STOREFRONT | C24: ='Building & Fit-out Breakdown'!F229 | D24: =C24/$B$4
A25: 088000 | B25: GLASS/GLAZING | C25: ='Building & Fit-out Breakdown'!F237 | D25: =C25/$B$4
A26: 092000 | B26: DRYWALL | C26: ='Building & Fit-out Breakdown'!F270 | D26: =C26/$B$4
A27: 092300 | B27: TILE/BRICK TILE | C27: ='Building & Fit-out Breakdown'!F279 | D27: =C27/$B$4
A28: 096000 | B28: CARPET/RESILIENT FLOORING | C28: ='Building & Fit-out Breakdown'!F294 | D28: =C28/$B$4
A29: 096050 | B29: FLOOR PREPARATION | C29: ='Building & Fit-out Breakdown'!F302 | D29: =C29/$B$4
A30: 096400 | B30: WOOD FLOORING | C30: ='Building & Fit-out Breakdown'!F308 | D30: =C30/$B$4
A31: 099000 | B31: PAINTING/PLASTER | C31: ='Building & Fit-out Breakdown'!F316 | D31: =C31/$B$4
A32: 100000 | B32: SPECIALITIES | C32: ='Building & Fit-out Breakdown'!F328 | D32: =C32/$B$4
A33: 100500 | B33: ACOUSTICAL PANELS/K13 | C33: ='Building & Fit-out Breakdown'!F334 | D33: =C33/$B$4
A34: 101400 | B34: SIGNAGE | C34: ='Building & Fit-out Breakdown'!F341 | D34: =C34/$B$4
A35: 120000 | B35: FF&E INSTALL | C35: ='Building & Fit-out Breakdown'!F346 | D35: =C35/$B$4
A36: 114000 | B36: FOOD SERVICE AND BAR EQUIPMENT | C36: ='Building & Fit-out Breakdown'!F354 | D36: =C36/$B$4
A37: 142000 | B37: ELEVATOR | C37: ='Building & Fit-out Breakdown'!F361 | D37: =C37/$B$4
A38: 210000 | B38: FIRE PROTECTION | C38: ='Building & Fit-out Breakdown'!F371 | D38: =C38/$B$4
A39: 220000 | B39: PLUMBING | C39: ='Building & Fit-out Breakdown'!F412 | D39: =C39/$B$4
A40: 230000 | B40: HVAC | C40: ='Building & Fit-out Breakdown'!F417 | D40: =C40/$B$4
A41: 260000 | B41: ELECTRIC | C41: ='Building & Fit-out Breakdown'!F456 | D41: =C41/$B$4
A42: 270000 | B42: LOW VOLTAGE CABLING | C42: ='Building & Fit-out Breakdown'!F464 | D42: =C42/$B$4
A43: 265000 | B43: LIGHTING | C43: ='Building & Fit-out Breakdown'!F474 | D43: =C43/$B$4
A44: 283100 | B44: FIRE ALARM | C44: ='Building & Fit-out Breakdown'!F480 | D44: =C44/$B$4
A45: 320000 | B45: SITEWORK | C45: ='Building & Fit-out Breakdown'!F488 | D45: =C45/$B$4
A46: 001000 | B46: PRECONSTRUCTION | C46: 60000 | D46: =C46/$B$4
A47: 010000 | B47: GENERAL CONDITIONS | C47: 0 | D47: =C47/$B$4 | E47: Carried in budget summary | G47: 'Carried in budget summary' - and also carried as division 013000 in trade cost. One function, two places.
A48: 010001 | B48: BONDS | C48: 0 | D48: =C48/$B$4 | E48: NIC
B49: SUB TOTAL | C49: =SUM(C11:C47) | D49: =C49/$B$4
A50: 500005 | B50: G.L. INSURANCE | C50: 0 | D50: =C50/$B$4 | G50: G.L. $0 and Builder's Risk $0 - both genuinely inside the 9% combined? Schimenti's equivalent line at 555 Johnson says 'Builder's Risk - Excluded' in writing. Can your broker quote both SEPARATELY, and quote an owner-controlled programme? We carry $385,000.
A51: 500006 | B51: BUILDERS RISK INSURANCE | C51: 0 | D51: =C51/$B$4
B52: C.M. OVERHEAD & FEE | C52: 0 | D52: =C52/$B$4
B53: SUB TOTAL | C53: =SUM(C49:C52)
A54: 500010 | B54: STATE/PROJECT TAX (IF APPLICABLE) | C54: 0 | D54: =C54/$B$4
A55: 700002 | B55: DESIGN CONTINGENCY | C55: 0 | D55: =C55/$B$4
A56: 700003 | B56: CONSTRUCTION CONTINGENCY | C56: 0 | D56: =C56/$B$4
A57: 700004 | B57: EXPEDITING/OVERTIME CONTINGENCY | C57: 0 | D57: =C57/$B$4
B58: TOTAL | C58: =SUM(C53:C57)

Sheet Building & Fit-out Breakdown
A1: Venue
A2: Scope: | B2: ='Building & Fit-outBudget Detail'!B2
A3: Capacity: | B3: 7440
A4: SF: | B4: =3500+69722+53379+9352
A5: Date: | B5: ='Building & Fit-outBudget Detail'!B5
A6: Architect: | B6: Wake
A7: Version: | B7: ='Building & Fit-outBudget Detail'!B6
A10: ITEM | B10: DESCRIPTION | C10: QTY | D10: UNIT | E10: UNIT PRICE | F10: TOTAL | G10: NOTES | K10: OUR QUESTION / ANALYSIS (MT, 17 Sep)
A12: 013000 | B12: PROJECT REQUIREMENTS
A13: 1 | B13: BIM Set Up & Coordination | C13: 1 | D13: LS | E13: 30000 | F13: =C13*E13
A14: =A13+1 | B14: Plans / Reprographics | C14: 1 | D14: LS | E14: 7500 | F14: =C14*E14
A15: =A14+1 | B15: Site Office & Equipment | C15: 1 | D15: LS | E15: 12000 | F15: =C15*E15
A16: =A15+1 | B16: Field Techonology | C16: 1 | D16: LS | E16: 200000 | F16: =C16*E16 | K16: What is included in Field Technology at $200,000?
A17: =A16+1 | B17: Construction Signage | C17: 1 | D17: LS | E17: 4500 | F17: =C17*E17
A18: =A17+1 | B18: Site Security | C18: 1 | D18: LS | E18: 13000 | F18: =C18*E18
A19: =A18+1 | B19: Site Safety Plan / First Aid / TPP / FE's / Safety Inspector | C19: 1 | D19: LS | E19: 400000 | F19: =C19*E19
A20: =A19+1 | B20: Portable Toilets | C20: 80 | D20: WK | E20: 400 | F20: =C20*E20
A21: =A20+1 | B21: Clean up Materials | C21: 1 | D21: LS | E21: 65000 | F21: =C21*E21
A22: =A21+1 | B22: Protection Materials | C22: 1 | D22: LS | E22: 50000 | F22: =C22*E22
A23: =A22+1 | B23: Project Labor | C23: 1 | D23: LS | E23: 2000000 | F23: =C23*E23 | K23: Crew, rate and weeks? The General Conditions tab already funds three supers + a general super for 90 weeks. No quantity behind this line.
A24: =A23+1 | B24: Project Rubbish Removals | C24: 1 | D24: LS | E24: 120000 | F24: =C24*E24
A25: =A24+1 | B25: Final Clean | C25: 1 | D25: LS | E25: 100000 | F25: =C25*E25
A27: Sub Total | B27: =B12 | F27: =SUM(F11:F26) | K27: All of this division reads as general conditions. Is it meant to sit inside trade cost AND under the GC line on the summary? We think it is one function in two places.
A29: 015800 | B29: SCAFFOLDING & HOARDING
A30: 1 | B30: Install sidewalk bridge and scaffolding around building | C30: 1 | D30: LS | E30: 4000000 | F30: =E30*C30 | I30: 500/LF bridge | K30: The lump says $4,000,000. The two rows beneath it - 1,126 LF @ $500 and 27,024 SF @ $75 - foot to $2,589,800. Which is right? And how many LF of PUBLIC sidewalk does the building front? A shed is only required where there is one; the alleys and lot lines have none. We carry 1,089 LF perimeter x $210 erected + 24 months rental.
C31: 1126 | D31: LF | E31: 500
C32: =(1126*6)*4 | D32: SF | E32: 75
A33: 2 | B33: Interior scaffolding | C33: 1 | D33: LS | E33: 2000000 | F33: =E33*C33 | I33: $75/SF for scaffolding | K33: What is being staged, at what rate, for how many weeks? The high roof is only 8.65 lb/SF of short-span W12/W6 framing - not a heavy erection. And the ground-supported stage and production towers are erected FIRST; can they carry the access instead of renting it twice?
A34: 3 | B34: Barricades | C34: 1 | D34: LS | E34: 150000 | F34: =E34*C34
B35: Site safety During Erection | C35: 1 | D35: LS | E35: 20000 | F35: =E35*C35
A36: 4
A37: Sub Total | B37: =B29 | F37: =SUM(F28:F36)
A39: 024100 | B39: DEMOLITION
A40: 1 | B40: Demo existing CMU/masonry walls at new Entry/Lobby area | C40: 2500 | D40: SF | E40: 12 | F40: =C40*E40
A41: =A40+1 | B41: Demo 8" CMU interior wall 20' tall | C41: 1975 | D41: SF | E41: 12 | F41: =C41*E41
A42: =A41+1 | B42: Demo 8" CMU interior wall 12' tall | C42: =628*12 | D42: SF | E42: 12 | F42: =C42*E42
A43: =A42+1 | B43: Demo office area partitions, ceilings, doors, flooring MEP's, (CMU walls line above) | C43: 6825 | D43: SF | E43: 5 | F43: =C43*E43
A44: =A43+1 | B44: Demo existing exterior roll up doors | C44: 8 | D44: EA | E44: 5000 | F44: =C44*E44
A45: =A44+1 | B45: Demo existing exterior doors | C45: 7 | D45: EA | E45: 250 | F45: =C45*E45
A46: =A45+1 | B46: Demo existing windows 1'x10' | C46: 34 | D46: EA | E46: 300 | F46: =C46*E46
A47: =A46+1 | B47: Demo ceiling mount steam heaters and associated piping | C47: 28 | D47: EA | E47: 750 | F47: =C47*E47
A48: =A47+1 | B48: Demo 5,250MBH boiler and piping (15'x6'x7' 13,000lbs) | C48: 2 | D48: EA | E48: 20000 | F48: =C48*E48
A49: =A48+1 | B49: Demo misc. piping, lighting, electrical panels / switchgear / appurtenances throughout space | C49: 1 | D49: SF | E49: 74000 | F49: =C49*E49
A50: =A49+1 | B50: Demo dock levelers | C50: 3 | D50: EA | E50: 2500 | F50: =C50*E50
A51: =A50+1 | B51: Demo slab at load-in ramp plan west | C51: 1423 | D51: SF | E51: 10 | F51: =C51*E51
A52: =A51+1 | B52: Trench slab for new grade beams at new façade | C52: 132 | D52: LF | E52: 100 | F52: =C52*E52 | H52: $2,500/cy
A53: =A52+1 | B53: Demo / excavate 6" slab 4' tall at load-in area | C53: =890+1750 | D53: SF | E53: 12 | F53: =C53*E53 | H53: $2,500/cy
A54: =A53+1 | B54: Trench slab for below grade sanitary line for bars and bathrooms | C54: 800 | D54: LF | E54: 80 | F54: =C54*E54 | H54: Trenching $150/LF Pour back $50K/LF
A55: =A54+1 | B55: Demo / excavate elevator pits | C55: 2 | D55: EA | E55: 25000 | F55: =C55*E55 | H55: New Elvator 4' pit $50K excavate and concrete
A56: =A55+1 | B56: Shoring Demo of Steel | C56: 1 | D56: LS | E56: 50000 | F56: =C56*E56
A57: =A56+1 | B57: Demo Steel Columns / Roof Steel | C57: 1 | D57: EA | E57: 100000 | F57: =C57*E57
A58: =A57+1 | B58: Demo Pre-cast concrete roof | C58: 74000 | D58: SF | E58: 8 | F58: =C58*E58 | G58: Abatement by others | K58: Confirms the REBUILD method, which the RFEM model also uses and which we now accept. Separate question: is the existing roof genuinely pre-cast concrete? It decides whether a PARTIAL lift over the 27,393 SF high-roof zone is even possible.
A59: =A58+1 | B59: Allow for Floor trenching for MEPS | C59: 0 | D59: LS | E59: 50000 | F59: =C59*E59
A60: =A59+1 | B60: Demo floor for Recessed floor - Include Excavation | C60: 0 | D60: SF | E60: 0 | F60: =C60*E60 | G60: Included Above
A61: =A60+1 | B61: Misc Façade Demo Along Johnson Ave (Doors, Roll-ups, Windows, etc.) | C61: 0 | D61: LS | E61: 20000 | F61: =C61*E61
A63: Sub Total | B63: =B39 | F63: =SUM(F38:F62) | G63: $10/SF
A65: 033000 | B65: CONCRETE
A66: 1 | B66: Excavation related to New Columns at Music hall | C66: 0 | D66: SF | E66: 6.5 | F66: =E66*C66 | G66: Based on Footprint of New Roof
A67: 2 | B67: CMU wall footing excavation allow 2' deep for new Load bearing wall at Music hall- East wall | C67: 0 | D67: LF | E67: 150 | F67: =E67*C67
A68: 3 | B68: Concrete at New footings | C68: 0 | D68: EA | E68: 7500 | F68: =E68*C68
B69: Excavate & Install New Footings at Stage | F69: =E69*C69
F70: =E70*C70 | H70: 4
B71: 1st Floor Raised Slab - Concrete on Styrofoam 24" | C71: 1500 | D71: CY | E71: 70 | F71: =E71*C71 | G71: 20,314 SF (Includes two ramps down to GA)
B72: Concrete ramp stage | F72: =E72*C72
B73: Concrete 4'6" H on Styrofoam | C73: 0 | D73: SF | E73: 50 | F73: =E73*C73
B74: Concrete at Stage Platform 4'6" H on Styrofoam | C74: 0 | D74: SF | E74: 50 | F74: =E74*C74
F75: =E75*C75
F76: =E76*C76
B77: F/I new foundation wall / perimeter grade beam | C77: 132 | D77: LF | E77: 300 | F77: =E77*C77 | H77: $750/CY
B78: F/I new retaining wall at load-in area excavate slab 4' tall | C78: 219 | D78: LF | E78: 150 | F78: =E78*C78 | G78: 877 SF | H78: $100/CY
A79: 4 | B79: Concrete at CMU footing | C79: 0 | D79: LF | E79: 100 | F79: =E79*C79
A80: 5 | B80: Patch slab due to New footing | C80: 0 | D80: SF | E80: 30 | F80: =E80*C80
A81: 6 | B81: Patch conc. At Trenching for MEPS | C81: 0 | D81: SF | E81: 30 | F81: =E81*C81
A82: =A81+1 | B82: New slab Pour-back at Excavated Areas | C82: 0 | D82: SF | E82: 30 | F82: =E82*C82
A83: =A82+1 | B83: New slab at Recessed floor | C83: 0 | D83: SF | E83: 0 | F83: =E83*C83 | G83: Included Above
A84: =A83+1 | B84: Concrete on Deck for Mezz of Music Hall with Platforms | C84: 0 | D84: SF | E84: 25 | F84: =E84*C84
A85: =A84+1 | B85: Concrete In-fill on New Pan Stairs | C85: 0 | D85: EA | E85: 4000 | F85: =E85*C85 | G85: (2) Feature Stairs, (2) BOH Stairs
A86: =A85+1 | B86: Grouting at Steel Trusses & Column Base Plates | C86: 0 | D86: LS | E86: 15000 | F86: =E86*C86
A87: =A86+1 | B87: Polished concrete | C87: 0 | D87: SF | E87: 8 | F87: =E87*C87
A88: =A87+1 | B88: Concrete pads | C88: 0 | D88: LS | E88: 10000 | F88: =E88*C88
A89: =A88+1 | B89: Patch sidewalk | C89: 0 | D89: LS | E89: 35000 | F89: =E89*C89
A90: =A89+1 | B90: Misc. Equipment Pads | C90: 0 | D90: LS | E90: 25000 | F90: =E90*C90
A91: =A90+1 | B91: Concrete at Stage Platform 4'6" H on Styrofoam | C91: 0 | D91: SF | E91: 50 | F91: =E91*C91
A93: Sub Total | B93: =B65 | F93: =SUM(F64:F92) | K93: Nearly every line zero quantity - no footings, no stage slab, no mezzanine deck pour, no base-plate grout. The takeoff gives 124 footing locations (up from 81 in Rev 43). We carry $2,543,000 of foundations.
A95: 042000 | B95: MASONRY
B96: FIRST FLOOR
A97: 1 | B97: Patch & Repair Existing Masonry Wall | C97: 9972 | D97: SF | E97: 10 | F97: =C97*E97
B98: New Masonry Wall at Entry Lobby Area | C98: 2022 | D98: SF
B99: CMU and Brick façade at removed windows | C99: 34 | D99: SF
B100: CMU and Brick façade at removed doors
B101: CMU and Brick façade at removed rolling grilles
B102: Patch masonry at new exterior doors
B103: Patch Masonry at louver openings
B105: F&I CMU wall vestibule stair tower 1 1st FL | C105: 0 | D105: SF | E105: 35
B106: F&I CMU wall vestibule stair tower 2 1st Fl
B107: F&I CMU wall vestibule stair tower 1 2nd FL
B108: F&I CMU wall vestibule stair tower 2 2nd FL
B109: F&I CMU wall vestibule stair tower 1 3rd Fl
B110: F&I CMU wall vestibule stair tower 2 3rd Fl
B111: F&I CMU elevator tower entrance | C111: 3220 | D111: SF | E111: 35 | F111: =C111*E111
...

Sheet General Conditions
G2: OUR QUESTION / ANALYSIS (MT, 17 Sep)
B3: Exec | C3: 10 | D3: 9200 | E3: =C3*D3 | G3: This tab is the best-evidenced page in the file and we would rather build on it than argue with it. Is the $3,141,000 the ONLY place general conditions lives? Division 013000 on the Breakdown carries site office, field tech, safety, toilets, protection, clean-up, rubbish and final clean for another $3,034,000.
B4: PM | C4: 90 | D4: 6400 | E4: =C4*D4 | G4: 90 weeks - is that construction only, or does it include pre-con and closeout? Can we see it as a rate x duration so that shortening the programme visibly shortens the cost?
B5: APM | C5: 90 | D5: 4600 | E5: =C5*D5
B6: Engineer | C6: 90 | D6: 3900 | E6: =C6*D6
B7: Accoutnant | C7: 10 | D7: 2800 | E7: =C7*D7
E8: =C8*D8
B9: Super | C9: 90 | D9: 6000 | E9: =C9*D9 | G9: Three superintendents for the full 90 weeks each - all three for the whole period, or overlapping phases?
B10: Super | C10: 90 | D10: 6000 | E10: =C10*D10
B11: Super | C11: 90 | D11: 6000 | E11: =C11*D11
B12: General Super | C12: 10 | D12: 6000 | E12: =C12*D12
E13: =SUM(E3:E12)

Sheet Project At-a-Glance
B8: Cost Report Date: | C8: 44957 | F8: Venue Capacity: | G8: TBD
B9: Project Name: | F9: Landlord Work Start Date: | G9: TBD
B10: Location: | F10: LNE Work Start Date: | G10: TBD
B11: Address: | F11: Certificate of Occupancy: | G11: TBD
B12: Project Number: | F12: First Show Date: | G12: TBD
B13: Budget: | C13: =C25 | F13: Project Completion Date: | G13: TBD
B14: Venue EVP: | C14: TBD | F14: Project Manager: | G14: TBD
B17: Description | C17: Budget | D17: Committed Costs Total | E17: Costs to Date Total | F17: Remaining Estimate | G17: Estimated Final Cost | H17: Budget vs EFC Variance
B19: ='Project Detail'!D4 | C19: ='Project Summary '!C9 | D19: ='Project Summary '!D9 | E19: ='Project Summary '!E9 | F19: ='Project Summary '!F9 | G19: ='Project Summary '!G9 | H19: ='Project Summary '!H9
B20: ='Project Detail'!D33 | C20: ='Project Summary '!C15 | D20: ='Project Summary '!D15 | E20: ='Project Summary '!E15 | F20: ='Project Summary '!F15 | G20: ='Project Summary '!G15 | H20: ='Project Summary '!H15
B21: FF&E Costs | C21: ='Project Summary '!C27 | D21: ='Project Summary '!D27 | E21: ='Project Summary '!E27 | F21: ='Project Summary '!F27 | G21: ='Project Summary '!G27 | H21: ='Project Summary '!H27
B23: ='Project Summary '!B29 | C23: =SUM(C19:C21) | D23: =SUM(D19:D21) | E23: =SUM(E19:E21) | F23: =SUM(F19:F21) | G23: =SUM(G19:G21) | H23: =SUM(H19:H21)
B24: Total Contingency | C24: ='Project Summary '!C30 | F24: =Contingency!G9 | G24: =Contingency!G9 | H24: =C24-G24
B25: TOTAL | C25: =SUM(C23:C24) | D25: =SUM(D23:D24) | E25: =SUM(E23:E24) | F25: =SUM(F23:F24) | G25: =SUM(G23:G24) | H25: =SUM(H23:H24)
B28: Risk Summary
B29: Risk Report Total | D29: ='Risk Report'!G15
B30: Remaining Contingency | D30: ='Risk Report'!G19
B31: Exposure | D31: ='Risk Report'!G23
B32: Estimated Final Cost (Including Risk Items) | D32: =G25+D31

Sheet Project Summary 
B2: Description | C2: Budget | D2: Committed Costs | E2: Costs to Date | F2: Remaining Estimate | G2: Estimated Final Cost | H2: Budget vs EFC Variance
D3: Total | E3: Total
B4: ='Project Detail'!D4
B5: ='Project Detail'!D5 | C5: ='Project Detail'!F10 | D5: ='Project Detail'!G10 | E5: ='Project Detail'!K10 | F5: ='Project Detail'!L10 | G5: ='Project Detail'!M10 | H5: ='Project Detail'!N10
B6: ='Project Detail'!D11 | C6: ='Project Detail'!F16 | D6: ='Project Detail'!G16 | E6: ='Project Detail'!K16 | F6: ='Project Detail'!L16 | G6: ='Project Detail'!M16 | H6: ='Project Detail'!N16
B7: ='Project Detail'!D17 | C7: ='Project Detail'!F22 | D7: ='Project Detail'!G22 | E7: ='Project Detail'!K22 | F7: ='Project Detail'!L22 | G7: ='Project Detail'!M22 | H7: ='Project Detail'!N22
B8: ='Project Detail'!D23 | C8: ='Project Detail'!F28 | D8: ='Project Detail'!G28 | E8: ='Project Detail'!K28 | F8: ='Project Detail'!L28 | G8: ='Project Detail'!M28 | H8: ='Project Detail'!N28
B9: Building Costs Total | C9: =SUM(C5:C8) | D9: =SUM(D5:D8) | E9: =SUM(E5:E8) | F9: =SUM(F5:F8) | G9: =SUM(G5:G8) | H9: =SUM(H5:H8)
B11: ='Project Detail'!D33
B12: ='Project Detail'!D34 | C12: ='Project Detail'!F39 | D12: ='Project Detail'!G39 | E12: ='Project Detail'!K39 | F12: ='Project Detail'!L39 | G12: ='Project Detail'!M39 | H12: ='Project Detail'!N39
B13: ='Project Detail'!D40 | C13: ='Project Detail'!F45 | D13: ='Project Detail'!G45 | E13: ='Project Detail'!K45 | F13: ='Project Detail'!L45 | G13: ='Project Detail'!M45 | H13: ='Project Detail'!N45
B14: ='Project Detail'!D46 | C14: ='Project Detail'!F57 | D14: ='Project Detail'!G57 | E14: ='Project Detail'!K57 | F14: ='Project Detail'!L57 | G14: ='Project Detail'!M57 | H14: ='Project Detail'!N57
B15: Soft Costs Total | C15: =SUM(C12:C14) | D15: =SUM(D12:D14) | E15: =SUM(E12:E14) | F15: =SUM(F12:F14) | G15: =SUM(G12:G14) | H15: =SUM(H12:H14)
B17: ='Project Detail'!D62
B18: ='Project Detail'!D63 | C18: ='Project Detail'!F82 | D18: ='Project Detail'!G82 | E18: ='Project Detail'!K82 | F18: ='Project Detail'!L82 | G18: ='Project Detail'!M82 | H18: ='Project Detail'!N82
B19: ='Project Detail'!D83 | C19: ='Project Detail'!F88 | D19: ='Project Detail'!G88 | E19: ='Project Detail'!K88 | F19: ='Project Detail'!L88 | G19: ='Project Detail'!M88 | H19: ='Project Detail'!N88
B20: ='Project Detail'!D89 | C20: ='Project Detail'!F92 | D20: ='Project Detail'!G92 | E20: ='Project Detail'!K92 | F20: ='Project Detail'!L92 | G20: ='Project Detail'!M92 | H20: ='Project Detail'!N92
B21: ='Project Detail'!D93 | C21: ='Project Detail'!F99 | D21: ='Project Detail'!G99 | E21: ='Project Detail'!K99 | F21: ='Project Detail'!L99 | G21: ='Project Detail'!M99 | H21: ='Project Detail'!N99
B22: ='Project Detail'!D100 | C22: ='Project Detail'!F118 | D22: ='Project Detail'!G118 | E22: ='Project Detail'!K118 | F22: ='Project Detail'!L118 | G22: ='Project Detail'!M118 | H22: ='Project Detail'!N118
B23: ='Project Detail'!D119 | C23: ='Project Detail'!F130 | D23: ='Project Detail'!G130 | E23: ='Project Detail'!K130 | F23: ='Project Detail'!L130 | G23: ='Project Detail'!M130 | H23: ='Project Detail'!N130
B24: ='Project Detail'!D131 | C24: ='Project Detail'!F138 | D24: ='Project Detail'!G138 | E24: ='Project Detail'!K138 | F24: ='Project Detail'!L138 | G24: ='Project Detail'!M138 | H24: ='Project Detail'!N138
B25: ='Project Detail'!D139 | C25: ='Project Detail'!F150 | D25: ='Project Detail'!G150 | E25: ='Project Detail'!K150 | F25: ='Project Detail'!L150 | G25: ='Project Detail'!M150 | H25: ='Project Detail'!N150
B26: ='Project Detail'!D151 | C26: ='Project Detail'!F166 | D26: ='Project Detail'!G166 | E26: ='Project Detail'!K166 | F26: ='Project Detail'!L166 | G26: ='Project Detail'!M166 | H26: ='Project Detail'!N166
B27: FF&E Costs Total | C27: =SUM(C18:C26) | D27: =SUM(D18:D26) | E27: =SUM(E18:E26) | F27: =SUM(F18:F26) | G27: =SUM(G18:G26) | H27: =SUM(H18:H26)
B29: Sub-Total | C29: =+C9+C15+C27 | D29: =+D9+D15+D27 | E29: =+E9+E15+E27 | F29: =+F9+F15+F27 | G29: =+G9+G15+G27 | H29: =+H9+H15+H27
B30: Contingency | C30: ='Project Detail'!F170 | F30: =Contingency!G9 | G30: =Contingency!G9 | H30: =C30-G30
B31: GRAND TOTAL | C31: =SUM(C29:C30) | D31: =SUM(D29:D30) | E31: =SUM(E29:E30) | F31: =SUM(F29:F30) | G31: =SUM(G29:G30) | H31: =SUM(H29:H30)

Sheet Project Detail
B2: Code | C2: Cost Code | D2: Vendor | E2: Description | F2: Budget | G2: Committed Costs | H2: Change Orders | I2: Costs to Date (Gross) | J2: Retention | K2: Costs to Date | L2: Remaining Estimate | M2: Estimated Final Cost | N2: Budget vs EFC Variance | O2: Notes | Q2: Remaining to Invoice | S2: P11-21 (Fcst) | T2: P12-21 (Fcst) | U2: Q4-21 TOTAL (Fcst) | W2: P01-22 (Fcst) | X2: P02-22 (Fcst) | Y2: P03-22 (Fcst) | Z2: Q1-22 TOTAL (Fcst) | AB2: Q4-21/Q1-22 TOTAL | AD2: Remaining to Allocate
B4: 100 | D4: Building Costs
B5: 101 | D5: Building & Fit-Out Costs
B6: 101-1 | D6: General Contractor | F6: ='Budget Summary'!D31 | G6: =SUMIF('Committed Costs '!C:C,B6,'Committed Costs '!G:G) | H6: =SUMIF('Change Orders'!F:F,'Project Detail'!B6,'Change Orders'!E:E) | I6: =SUMIF(Invoices!B:B,B6,Invoices!G:G) | J6: 0 | K6: =I6-J6 | L6: =+M6-G6 | M6: =IF((F6+H6)>G6,F6+H6,G6) | N6: =F6-M6
B7: 101-2 | F7: 0 | G7: =SUMIF('Committed Costs '!C:C,B7,'Committed Costs '!G:G) | H7: =SUMIF('Change Orders'!F:F,'Project Detail'!B7,'Change Orders'!E:E) | I7: =SUMIF(Invoices!B:B,B7,Invoices!G:G) | J7: 0 | K7: =I7-J7 | L7: =+M7-G7 | M7: =IF((F7+H7)>G7,F7+H7,G7) | N7: =F7-M7
B8: 101-3 | F8: 0 | G8: =SUMIF('Committed Costs '!C:C,B8,'Committed Costs '!G:G) | H8: =SUMIF('Change Orders'!F:F,'Project Detail'!B8,'Change Orders'!E:E) | I8: =SUMIF(Invoices!B:B,B8,Invoices!G:G) | J8: 0 | K8: =I8-J8 | L8: =+M8-G8 | M8: =IF((F8+H8)>G8,F8+H8,G8) | N8: =F8-M8
B9: 101-4 | F9: 0 | G9: =SUMIF('Committed Costs '!C:C,B9,'Committed Costs '!G:G) | H9: =SUMIF('Change Orders'!F:F,'Project Detail'!B9,'Change Orders'!E:E) | I9: =SUMIF(Invoices!B:B,B9,Invoices!G:G) | J9: 0 | K9: =I9-J9 | L9: =+M9-G9 | M9: =IF((F9+H9)>G9,F9+H9,G9) | N9: =F9-M9 | Q9: =M9-K9 | U9: =S9+T9 | Z9: =W9+X9+Y9 | AB9: =U9+Z9 | AD9: =Q9-AB9
C10: 101 | E10: Total Building & Fit-Out Costs | F10: =SUM(F6:F9) | G10: =SUM(G6:G9) | H10: =SUM(H6:H9) | I10: =SUM(I6:I9) | J10: =SUM(J6:J9) | K10: =SUM(K6:K9) | L10: =SUM(L6:L9) | M10: =SUM(M6:M9) | N10: =SUM(N6:N9) | Q10: =Q9 | S10: =S9 | T10: =T9 | U10: =U9 | W10: =W9 | X10: =X9 | Y10: =Y9 | Z10: =Z9 | AB10: =AB9 | AD10: =AD9
B11: 102 | D11: Secondary Contractors
B12: 102-1 | F12: 0 | G12: =SUMIF('Committed Costs '!C:C,B12,'Committed Costs '!G:G) | H12: =SUMIF('Change Orders'!F:F,'Project Detail'!B12,'Change Orders'!E:E) | I12: =SUMIF(Invoices!B:B,B12,Invoices!G:G) | J12: 0 | K12: =I12-J12 | L12: =+M12-G12 | M12: =IF((F12+H12)>G12,F12+H12,G12) | N12: =F12-M12
B13: 102-2 | F13: 0 | G13: =SUMIF('Committed Costs '!C:C,B13,'Committed Costs '!G:G) | H13: =SUMIF('Change Orders'!F:F,'Project Detail'!B13,'Change Orders'!E:E) | I13: =SUMIF(Invoices!B:B,B13,Invoices!G:G) | J13: 0 | K13: =I13-J13 | L13: =+M13-G13 | M13: =IF((F13+H13)>G13,F13+H13,G13) | N13: =F13-M13
B14: 102-3 | F14: 0 | G14: =SUMIF('Committed Costs '!C:C,B14,'Committed Costs '!G:G) | H14: =SUMIF('Change Orders'!F:F,'Project Detail'!B14,'Change Orders'!E:E) | I14: =SUMIF(Invoices!B:B,B14,Invoices!G:G) | J14: 0 | K14: =I14-J14 | L14: =+M14-G14 | M14: =IF((F14+H14)>G14,F14+H14,G14) | N14: =F14-M14
B15: 102-4 | F15: 0 | G15: =SUMIF('Committed Costs '!C:C,B15,'Committed Costs '!G:G) | H15: =SUMIF('Change Orders'!F:F,'Project Detail'!B15,'Change Orders'!E:E) | I15: =SUMIF(Invoices!B:B,B15,Invoices!G:G) | J15: 0 | K15: =I15-J15 | L15: =+M15-G15 | M15: =IF((F15+H15)>G15,F15+H15,G15) | N15: =F15-M15 | Q15: =M15-K15 | U15: =S15+T15 | Z15: =W15+X15+Y15 | AB15: =U15+Z15 | AD15: =Q15-AB15
C16: 102 | E16: Total Secondary Contractors | F16: =SUM(F12:F15) | G16: =SUM(G12:G15) | H16: =SUM(H12:H15) | I16: =SUM(I12:I15) | J16: =SUM(J12:J15) | K16: =SUM(K12:K15) | L16: =SUM(L12:L15) | M16: =SUM(M12:M15) | N16: =SUM(N12:N15) | Q16: =Q15 | S16: =S15 | T16: =T15 | U16: =U15 | W16: =W15 | X16: =X15 | Y16: =Y15 | Z16: =Z15 | AB16: =AB15 | AD16: =AD15
B17: 103 | D17: Miscellaneous
B18: 103-1 | F18: 0 | G18: =SUMIF('Committed Costs '!C:C,B18,'Committed Costs '!G:G) | H18: =SUMIF('Change Orders'!F:F,'Project Detail'!B18,'Change Orders'!E:E) | I18: =SUMIF(Invoices!B:B,B18,Invoices!G:G) | J18: 0 | K18: =I18-J18 | L18: =+M18-G18 | M18: =IF((F18+H18)>G18,F18+H18,G18) | N18: =F18-M18
B19: 103-2 | F19: 0 | G19: =SUMIF('Committed Costs '!C:C,B19,'Committed Costs '!G:G) | H19: =SUMIF('Change Orders'!F:F,'Project Detail'!B19,'Change Orders'!E:E) | I19: =SUMIF(Invoices!B:B,B19,Invoices!G:G) | J19: 0 | K19: =I19-J19 | L19: =+M19-G19 | M19: =IF((F19+H19)>G19,F19+H19,G19) | N19: =F19-M19
B20: 103-3 | F20: 0 | G20: =SUMIF('Committed Costs '!C:C,B20,'Committed Costs '!G:G) | H20: =SUMIF('Change Orders'!F:F,'Project Detail'!B20,'Change Orders'!E:E) | I20: =SUMIF(Invoices!B:B,B20,Invoices!G:G) | J20: 0 | K20: =I20-J20 | L20: =+M20-G20 | M20: =IF((F20+H20)>G20,F20+H20,G20) | N20: =F20-M20
B21: 103-4 | F21: 0 | G21: =SUMIF('Committed Costs '!C:C,B21,'Committed Costs '!G:G) | H21: =SUMIF('Change Orders'!F:F,'Project Detail'!B21,'Change Orders'!E:E) | I21: =SUMIF(Invoices!B:B,B21,Invoices!G:G) | J21: 0 | K21: =I21-J21 | L21: =+M21-G21 | M21: =IF((F21+H21)>G21,F21+H21,G21) | N21: =F21-M21 | Q21: =M21-K21 | U21: =S21+T21 | Z21: =W21+X21+Y21 | AB21: =U21+Z21 | AD21: =Q21-AB21
C22: 103 | E22: Total Mics. | F22: =SUM(F18:F21) | G22: =SUM(G18:G21) | H22: =SUM(H18:H21) | I22: =SUM(I18:I21) | J22: =SUM(J18:J21) | K22: =SUM(K18:K21) | L22: =SUM(L18:L21) | M22: =SUM(M18:M21) | N22: =SUM(N18:N21) | Q22: =Q21 | S22: =S21 | T22: =T21 | U22: =U21 | W22: =W21 | X22: =X21 | Y22: =Y21 | Z22: =Z21 | AB22: =AB21 | AD22: =AD21
B23: 104
B24: 104-1 | F24: 0 | G24: =SUMIF('Committed Costs '!C:C,B24,'Committed Costs '!G:G) | H24: =SUMIF('Change Orders'!F:F,'Project Detail'!B24,'Change Orders'!E:E) | I24: =SUMIF(Invoices!B:B,B24,Invoices!G:G) | J24: 0 | K24: =I24-J24 | L24: =+M24-G24 | M24: =K24 | N24: =F24-M24
B25: 104-2 | F25: 0 | G25: =SUMIF('Committed Costs '!C:C,B25,'Committed Costs '!G:G) | H25: =SUMIF('Change Orders'!F:F,'Project Detail'!B25,'Change Orders'!E:E) | I25: =SUMIF(Invoices!B:B,B25,Invoices!G:G) | J25: 0 | K25: =I25-J25 | L25: =+M25-G25 | M25: =IF((F25+H25)>G25,F25+H25,G25) | N25: =F25-M25
B26: 104-3 | F26: 0 | G26: =SUMIF('Committed Costs '!C:C,B26,'Committed Costs '!G:G) | H26: =SUMIF('Change Orders'!F:F,'Project Detail'!B26,'Change Orders'!E:E) | I26: =SUMIF(Invoices!B:B,B26,Invoices!G:G) | J26: 0 | K26: =I26-J26 | L26: =+M26-G26 | M26: =IF((F26+H26)>G26,F26+H26,G26) | N26: =F26-M26
B27: 104-4 | F27: 0 | G27: =SUMIF('Committed Costs '!C:C,B27,'Committed Costs '!G:G) | H27: =SUMIF('Change Orders'!F:F,'Project Detail'!B27,'Change Orders'!E:E) | I27: =SUMIF(Invoices!B:B,B27,Invoices!G:G) | J27: 0 | K27: =I27-J27 | L27: =+M27-G27 | M27: =IF((F27+H27)>G27,F27+H27,G27) | N27: =F27-M27 | Q27: =M27-K27 | U27: =S27+T27 | Z27: =W27+X27+Y27 | AB27: =U27+Z27 | AD27: =Q27-AB27
C28: 104 | E28: Total | F28: =SUM(F24:F27) | G28: =SUM(G24:G27) | H28: =SUM(H24:H27) | I28: =SUM(I24:I27) | J28: =SUM(J24:J27) | K28: =SUM(K24:K27) | L28: =SUM(L24:L27) | M28: =SUM(M24:M27) | N28: =SUM(N24:N27) | Q28: =Q27 | S28: =S27 | T28: =T27 | U28: =U27 | W28: =W27 | X28: =X27 | Y28: =Y27 | Z28: =Z27 | AB28: =AB27 | AD28: =AD27
E30: TOTAL BUILDING COSTS | F30: =SUM(F10,F16,F22,F28) | G30: =SUM(G10,G16,G22,G28) | H30: =SUM(H10,H16,H22,H28) | I30: =SUM(I10,I16,I22,I28) | J30: =SUM(J10,J16,J22,J28) | K30: =SUM(K10,K16,K22,K28) | L30: =SUM(L10,L16,L22,L28) | M30: =SUM(M10,M16,M22,M28) | N30: =SUM(N10,N16,N22,N28) | Q30: =SUM(Q10,Q16,Q22,Q28) | S30: =SUM(S10,S16,S22,S28) | T30: =SUM(T10,T16,T22,T28) | U30: =SUM(U10,U16,U22,U28) | W30: =SUM(W10,W16,W22,W28) | X30: =SUM(X10,X16,X22,X28) | Y30: =SUM(Y10,Y16,Y22,Y28) | Z30: =SUM(Z10,Z16,Z22,Z28) | AB30: =SUM(AB10,AB16,AB22,AB28) | AD30: =SUM(AD10,AD16,AD22,AD28)
B33: 200 | D33: Soft Costs
B34: 201 | D34: Project Management
B35: 201-1 | D35: LNE | E35: Project Management | F35: ='Budget Summary'!D45 | G35: =SUMIF('Committed Costs '!C:C,B35,'Committed Costs '!G:G) | H35: =SUMIF('Change Orders'!F:F,'Project Detail'!B35,'Change Orders'!E:E) | I35: =SUMIF(Invoices!B:B,B35,Invoices!G:G) | J35: 0 | K35: =I35-J35 | L35: =+M35-G35 | M35: =G35 | N35: =F35-M35 | Q35: =M35-K35 | U35: =S35+T35 | Z35: =W35+X35+Y35 | AB35: =U35+Z35 | AD35: =Q35-AB35
B36: 201-2 | D36: TBD | E36: Project Management (3rd Party) | F36: ='Budget Summary'!#REF! | G36: =SUMIF('Committed Costs '!C:C,B36,'Committed Costs '!G:G) | H36: =SUMIF('Change Orders'!F:F,'Project Detail'!B36,'Change Orders'!E:E) | I36: =SUMIF(Invoices!B:B,B36,Invoices!G:G) | J36: 0 | K36: =I36-J36 | L36: =+M36-G36 | M36: =IF((F36+H36)>G36,F36+H36,G36) | N36: =F36-M36
B37: 201-3 | F37: 0 | G37: =SUMIF('Committed Costs '!C:C,B37,'Committed Costs '!G:G) | H37: =SUMIF('Change Orders'!F:F,'Project Detail'!B37,'Change Orders'!E:E) | I37: =SUMIF(Invoices!B:B,B37,Invoices!G:G) | J37: 0 | K37: =I37-J37 | L37: =+M37-G37 | M37: =IF((F37+H37)>G37,F37+H37,G37) | N37: =F37-M37
B38: 201-4 | F38: 0 | G38: =SUMIF('Committed Costs '!C:C,B38,'Committed Costs '!G:G) | H38: =SUMIF('Change Orders'!F:F,'Project Detail'!B38,'Change Orders'!E:E) | I38: =SUMIF(Invoices!B:B,B38,Invoices!G:G) | J38: 0 | K38: =I38-J38 | L38: =+M38-G38 | M38: =IF((F38+H38)>G38,F38+H38,G38) | N38: =F38-M38
C39: 201 | E39: Total Project Management | F39: =SUM(F35:F38) | G39: =SUM(G35:G38) | H39: =SUM(H35:H38) | I39: =SUM(I35:I38) | J39: =SUM(J35:J38) | K39: =SUM(K35:K38) | L39: =SUM(L35:L38) | M39: =SUM(M35:M38) | N39: =SUM(N35:N38) | Q39: =Q35 | S39: =S35 | T39: =T35 | U39: =U35 | W39: =W35 | X39: =X35 | Y39: =Y35 | Z39: =Z35 | AB39: =AB35 | AD39: =AD35
B40: 202 | D40: Architectural Fees
B41: 202-1 | D41: TBD | E41: Architectural Fees | F41: ='Budget Summary'!D35 | G41: =SUMIF('Committed Costs '!C:C,B41,'Committed Costs '!G:G) | H41: =SUMIF('Change Orders'!F:F,'Project Detail'!B41,'Change Orders'!E:E) | I41: =SUMIF(Invoices!B:B,B41,Invoices!G:G) | J41: 0 | K41: =I41-J41 | L41: =+M41-G41 | M41: =G41 | N41: =F41-M41 | Q41: =M41-K41 | U41: =S41+T41 | Z41: =W41+X41+Y41 | AB41: =U41+Z41 | AD41: =Q41-AB41
B42: 202-2 | F42: 0 | G42: =SUMIF('Committed Costs '!C:C,B42,'Committed Costs '!G:G) | H42: =SUMIF('Change Orders'!F:F,'Project Detail'!B42,'Change Orders'!E:E) | I42: =SUMIF(Invoices!B:B,B42,Invoices!G:G) | J42: 0 | K42: =I42-J42 | L42: =+M42-G42 | M42: =IF((F42+H42)>G42,F42+H42,G42) | N42: =F42-M42 | Q42: =M42-K42 | U42: =S42+T42 | Z42: =W42+X42+Y42 | AB42: =U42+Z42 | AD42: =Q42-AB42
B43: 202-3 | F43: 0 | G43: =SUMIF('Committed Costs '!C:C,B43,'Committed Costs '!G:G) | H43: =SUMIF('Change Orders'!F:F,'Project Detail'!B43,'Change Orders'!E:E) | I43: =SUMIF(Invoices!B:B,B43,Invoices!G:G) | J43: 0 | K43: =I43-J43 | L43: =+M43-G43 | M43: 0 | N43: =F43-M43 | Q43: =M43-K43 | U43: =S43+T43 | Z43: =W43+X43+Y43 | AB43: =U43+Z43 | AD43: =Q43-AB43
B44: 202-4 | F44: 0 | G44: =SUMIF('Committed Costs '!C:C,B44,'Committed Costs '!G:G) | H44: =SUMIF('Change Orders'!F:F,'Project Detail'!B44,'Change Orders'!E:E) | I44: =SUMIF(Invoices!B:B,B44,Invoices!G:G) | J44: 0 | K44: =I44-J44 | L44: =+M44-G44 | M44: =IF((F44+H44)>G44,F44+H44,G44) | N44: =F44-M44
C45: 202 | E45: Total Architectural Fees | F45: =SUM(F41:F44) | G45: =SUM(G41:G44) | H45: =SUM(H41:H44) | I45: =SUM(I41:I44) | J45: =SUM(J41:J44) | K45: =SUM(K41:K44) | L45: =SUM(L41:L44) | M45: =SUM(M41:M44) | N45: =SUM(N41:N44) | Q45: =SUM(Q41:Q43) | S45: =SUM(S41:S43) | T45: =SUM(T41:T43) | U45: =SUM(U41:U43) | W45: =SUM(W41:W43) | X45: =SUM(X41:X43) | Y45: =SUM(Y41:Y43) | Z45: =SUM(Z41:Z43) | AB45: =SUM(AB41:AB43) | AD45: =SUM(AD41:AD43)
B46: 203 | D46: Design, Engineering & Misc.
B47: 203-1 | D47: K2 | E47: AV/LV Design | F47: ='Budget Summary'!#REF! | G47: =SUMIF('Committed Costs '!C:C,B47,'Committed Costs '!G:G) | H47: =SUMIF('Change Orders'!F:F,'Project Detail'!B47,'Change Orders'!E:E) | I47: =SUMIF(Invoices!B:B,B47,Invoices!G:G) | J47: 0 | K47: =I47-J47 | L47: =+M47-G47 | M47: =G47 | N47: =F47-M47 | Q47: =M47-K47 | U47: =S47+T47 | Z47: =W47+X47+Y47 | AB47: =U47+Z47 | AD47: =Q47-AB47
B48: 203-2 | D48: Trimark | E48: Kitchen Design | F48: ='Budget Summary'!#REF! | G48: =SUMIF('Committed Costs '!C:C,B48,'Committed Costs '!G:G) | H48: =SUMIF('Change Orders'!F:F,'Project Detail'!B48,'Change Orders'!E:E) | I48: =SUMIF(Invoices!B:B,B48,Invoices!G:G) | J48: 0 | K48: =I48-J48 | L48: =+M48-G48 | M48: =G48 | N48: =F48-M48 | Q48: =M48-K48 | U48: =S48+T48 | Z48: =W48+X48+Y48 | AB48: =U48+Z48 | AD48: =Q48-AB48
B49: 203-3 | D49: Bandit Lites | E49: Lighting Design | F49: ='Budget Summary'!#REF! | G49: =SUMIF('Committed Costs '!C:C,B49,'Committed Costs '!G:G) | H49: =SUMIF('Change Orders'!F:F,'Project Detail'!B49,'Change Orders'!E:E) | I49: =SUMIF(Invoices!B:B,B49,Invoices!G:G) | J49: 0 | K49: =I49-J49 | L49: =+M49-G49 | M49: =G49 | N49: =F49-M49 | Q49: =M49-K49 | U49: =S49+T49 | Z49: =W49+X49+Y49 | AB49: =U49+Z49 | AD49: =Q49-AB49
B50: 203-4 | D50: TBD | E50: Branding | F50: ='Budget Summary'!D33 | G50: =SUMIF('Committed Costs '!C:C,B50,'Committed Costs '!G:G) | H50: =SUMIF('Change Orders'!F:F,'Project Detail'!B50,'Change Orders'!E:E) | I50: =SUMIF(Invoices!B:B,B50,Invoices!G:G) | J50: 0 | K50: =I50-J50 | L50: =+M50-G50 | M50: =G50 | N50: =F50-M50
B51: 203-5 | D51: TBD | E51: Civil Engineering | F51: ='Budget Summary'!D36 | G51: =SUMIF('Committed Costs '!C:C,B51,'Committed Costs '!G:G) | H51: =SUMIF('Change Orders'!F:F,'Project Detail'!B51,'Change Orders'!E:E) | I51: =SUMIF(Invoices!B:B,B51,Invoices!G:G) | J51: 0 | K51: =I51-J51 | L51: =+M51-G51 | M51: =G51 | N51: =F51-M51
B52: 203-6 | D52: K2 / Metro Acoustics | E52: Acoustic Design | F52: ='Budget Summary'!#REF! | G52: =SUMIF('Committed Costs '!C:C,B52,'Committed Costs '!G:G) | H52: =SUMIF('Change Orders'!F:F,'Project Detail'!B52,'Change Orders'!E:E) | I52: =SUMIF(Invoices!B:B,B52,Invoices!G:G) | J52: 0 | K52: =I52-J52 | L52: =+M52-G52 | M52: =G52 | N52: =F52-M52
B53: 203-7 | D53: TBD | E53: Signage / Wayfinding Design | F53: ='Budget Summary'!#REF! | G53: =SUMIF('Committed Costs '!C:C,B53,'Committed Costs '!G:G) | H53: =SUMIF('Change Orders'!F:F,'Project Detail'!B53,'Change Orders'!E:E) | I53: =SUMIF(Invoices!B:B,B53,Invoices!G:G) | J53: 0 | K53: =I53-J53 | L53: =+M53-G53 | M53: =G53 | N53: =F53-M53
B54: 203-8 | D54: TBD | E54: Zoning & Permit Fees | F54: ='Budget Summary'!D41 | G54: =SUMIF('Committed Costs '!C:C,B54,'Committed Costs '!G:G) | H54: =SUMIF('Change Orders'!F:F,'Project Detail'!B54,'Change Orders'!E:E) | I54: =SUMIF(Invoices!B:B,B54,Invoices!G:G) | J54: 0 | K54: =I54-J54 | L54: =+M54-G54 | M54: =G54 | N54: =F54-M54
B55: 203-9 | D55: TBD | E55: Testing / Quality Control | F55: ='Budget Summary'!D44 | G55: =SUMIF('Committed Costs '!C:C,B55,'Committed Costs '!G:G) | H55: =SUMIF('Change Orders'!F:F,'Project Detail'!B55,'Change Orders'!E:E) | I55: =SUMIF(Invoices!B:B,B55,Invoices!G:G) | J55: 0 | K55: =I55-J55 | L55: =+M55-G55 | M55: =G55 | N55: =F55-M55
B56: 203-10 | D56: TBD | E56: Reimbursable Expenses | F56: ='Budget Summary'!D46 | G56: =SUMIF('Committed Costs '!C:C,B56,'Committed Costs '!G:G) | H56: =SUMIF('Change Orders'!F:F,'Project Detail'!B56,'Change Orders'!E:E) | I56: =SUMIF(Invoices!B:B,B56,Invoices!G:G) | J56: 0 | K56: =I56-J56 | L56: =+M56-G56 | M56: =G56 | N56: =F56-M56 | Q56: =M56-K56 | U56: =S56+T56 | Z56: =W56+X56+Y56 | AB56: =U56+Z56 | AD56: =Q56-AB56
C57: 203 | E57: Total Design, Engineering & Misc. | F57: =SUM(F47:F56) | G57: =SUM(G47:G56) | H57: =SUM(H47:H56) | I57: =SUM(I47:I56) | J57: =SUM(J47:J56) | K57: =SUM(K47:K56) | L57: =SUM(L47:L56) | M57: =SUM(M47:M56) | N57: =SUM(N47:N56) | Q57: =SUM(Q47:Q56) | S57: =SUM(S47:S56) | T57: =SUM(T47:T56) | U57: =SUM(U47:U56) | W57: =SUM(W47:W56) | X57: =SUM(X47:X56) | Y57: =SUM(Y47:Y56) | Z57: =SUM(Z47:Z56) | AB57: =SUM(AB47:AB56) | AD57: =SUM(AD47:AD56)
E59: TOTAL SOFT COSTS | F59: =SUM(F39,F45,F57) | G59: =SUM(G39,G45,G57) | H59: =SUM(H39,H45,H57) | I59: =SUM(I39,I45,I57) | J59: =SUM(J39,J45,J57) | K59: =SUM(K39,K45,K57) | L59: =SUM(L39,L45,L57) | M59: =SUM(M39,M45,M57) | N59: =SUM(N39,N45,N57) | Q59: =SUM(Q39,Q45,Q57) | S59: =SUM(S39,S45,S57) | T59: =SUM(T39,T45,T57) | U59: =SUM(U39,U45,U57) | W59: =SUM(W39,W45,W57) | X59: =SUM(X39,X45,X57) | Y59: =SUM(Y39,Y45,Y57) | Z59: =SUM(Z39,Z45,Z57) | AB59: =SUM(AB39,AB45,AB57) | AD59: =SUM(AD39,AD45,AD57)
B62: 300 | D62: FF&E Costs
B63: 301 | D63: Seating
B64: 301-1 | D64: TBD | E64: Fixed Seating | F64: ='Budget Summary'!D49 | G64: =SUMIF('Committed Costs '!C:C,B64,'Committed Costs '!G:G) | H64: =SUMIF('Change Orders'!F:F,'Project Detail'!B64,'Change Orders'!E:E) | I64: =SUMIF(Invoices!B:B,B64,Invoices!G:G) | J64: 0 | K64: =I64-J64 | L64: =+M64-G64 | M64: =IF((F64+H64)>G64,F64+H64,G64) | N64: =F64-M64 | Q64: =M64-K64 | U64: =S64+T64 | Z64: =W64+X64+Y64 | AB64: =U64+Z64 | AD64: =Q64-AB64
B65: 301-2 | D65: N/A | E65: Chairs - Gasser Bar Stools | F65: =46800-46800 | G65: =SUMIF('Committed Costs '!C:C,B65,'Committed Costs '!G:G) | H65: =SUMIF('Change Orders'!F:F,'Project Detail'!B65,'Change Orders'!E:E) | I65: =SUMIF(Invoices!B:B,B65,Invoices!G:G) | J65: 0 | K65: =I65-J65 | L65: =+M65-G65 | M65: =IF((F65+H65)>G65,F65+H65,G65) | N65: =F65-M65 | Q65: =M65-K65 | U65: =S65+T65+#REF! | Z65: =W65+X65+Y65 | AB65: =U65+Z65 | AD65: =Q65-AB65
B66: 301-3 | D66: N/A | E66: Chairs - Gasser | F66: =90000-90000 | G66: =SUMIF('Committed Costs '!C:C,B66,'Committed Costs '!G:G) | H66: =SUMIF('Change Orders'!F:F,'Project Detail'!B66,'Change Orders'!E:E) | I66: =SUMIF(Invoices!B:B,B66,Invoices!G:G) | J66: 0 | K66: =I66-J66 | L66: =+M66-G66 | M66: =IF((F66+H66)>G66,F66+H66,G66) | N66: =F66-M66 | Q66: =M66-K66 | U66: =S66+T66+#REF! | Z66: =W66+X66+Y66 | AB66: =U66+Z66 | AD66: =Q66-AB66
B67: 301-4 | D67: N/A | E67: Ottoman - Boxes | F67: =18720-18720 | G67: =SUMIF('Committed Costs '!C:C,B67,'Committed Costs '!G:G) | H67: =SUMIF('Change Orders'!F:F,'Project Detail'!B67,'Change Orders'!E:E) | I67: =SUMIF(Invoices!B:B,B67,Invoices!G:G) | J67: 0 | K67: =I67-J67 | L67: =+M67-G67 | M67: =IF((F67+H67)>G67,F67+H67,G67) | N67: =F67-M67 | Q67: =M67-K67 | U67: =S67+T67+#REF! | Z67: =W67+X67+Y67 | AB67: =U67+Z67 | AD67: =Q67-AB67
B68: 301-5 | D68: N/A | E68: Side Tables - Boxes | F68: =18000-18000 | G68: =SUMIF('Committed Costs '!C:C,B68,'Committed Costs '!G:G) | H68: =SUMIF('Change Orders'!F:F,'Project Detail'!B68,'Change Orders'!E:E) | I68: =SUMIF(Invoices!B:B,B68,Invoices!G:G) | J68: 0 | K68: =I68-J68 | L68: =+M68-G68 | M68: =IF((F68+H68)>G68,F68+H68,G68) | N68: =F68-M68 | Q68: =M68-K68 | U68: =S68+T68+#REF! | Z68: =W68+X68+Y68 | AB68: =U68+Z68 | AD68: =Q68-AB68
B69: 301-6 | D69: N/A | E69: VIP - Cocktail Table | F69: =5300-5300 | G69: =SUMIF('Committed Costs '!C:C,B69,'Committed Costs '!G:G) | H69: =SUMIF('Change Orders'!F:F,'Project Detail'!B69,'Change Orders'!E:E) | I69: =SUMIF(Invoices!B:B,B69,Invoices!G:G) | J69: 0 | K69: =I69-J69 | L69: =+M69-G69 | M69: =IF((F69+H69)>G69,F69+H69,G69) | N69: =F69-M69 | Q69: =M69-K69 | U69: =S69+T69+#REF! | Z69: =W69+X69+Y69 | AB69: =U69+Z69 | AD69: =Q69-AB69
B70: 301-7 | D70: N/A | E70: VIP - Stools | F70: =12000-12000 | G70: =SUMIF('Committed Costs '!C:C,B70,'Committed Costs '!G:G) | H70: =SUMIF('Change Orders'!F:F,'Project Detail'!B70,'Change Orders'!E:E) | I70: =SUMIF(Invoices!B:B,B70,Invoices!G:G) | J70: 0 | K70: =I70-J70 | L70: =+M70-G70 | M70: =IF((F70+H70)>G70,F70+H70,G70) | N70: =F70-M70 | Q70: =M70-K70 | U70: =S70+T70+#REF! | Z70: =W70+X70+Y70 | AB70: =U70+Z70 | AD70: =Q70-AB70
B71: 301-8 | D71: N/A | E71: VIP - Coffee Tables | F71: =12000-12000 | G71: =SUMIF('Committed Costs '!C:C,B71,'Committed Costs '!G:G) | H71: =SUMIF('Change Orders'!F:F,'Project Detail'!B71,'Change Orders'!E:E) | I71: =SUMIF(Invoices!B:B,B71,Invoices!G:G) | J71: 0 | K71: =I71-J71 | L71: =+M71-G71 | M71: =IF((F71+H71)>G71,F71+H71,G71) | N71: =F71-M71 | Q71: =M71-K71 | U71: =S71+T71+#REF! | Z71: =W71+X71+Y71 | AB71: =U71+Z71 | AD71: =Q71-AB71
B72: 301-9 | D72: N/A | E72: VIP - Hightop | F72: =5000-5000 | G72: =SUMIF('Committed Costs '!C:C,B72,'Committed Costs '!G:G) | H72: =SUMIF('Change Orders'!F:F,'Project Detail'!B72,'Change Orders'!E:E) | I72: =SUMIF(Invoices!B:B,B72,Invoices!G:G) | J72: 0 | K72: =I72-J72 | L72: =+M72-G72 | M72: =IF((F72+H72)>G72,F72+H72,G72) | N72: =F72-M72 | Q72: =M72-K72 | U72: =S72+T72+#REF! | Z72: =W72+X72+Y72 | AB72: =U72+Z72 | AD72: =Q72-AB72
B73: 301-10 | D73: N/A | E73: VIP - Sofa | F73: =12000-12000 | G73: =SUMIF('Committed Costs '!C:C,B73,'Committed Costs '!G:G) | H73: =SUMIF('Change Orders'!F:F,'Project Detail'!B73,'Change Orders'!E:E) | I73: =SUMIF(Invoices!B:B,B73,Invoices!G:G) | J73: 0 | K73: =I73-J73 | L73: =+M73-G73 | M73: =IF((F73+H73)>G73,F73+H73,G73) | N73: =F73-M73 | Q73: =M73-K73 | U73: =S73+T73+#REF! | Z73: =W73+X73+Y73 | AB73: =U73+Z73 | AD73: =Q73-AB73
B74: 301-11 | D74: N/A | E74: VIP - Banquet | F74: =21000-21000 | G74: =SUMIF('Committed Costs '!C:C,B74,'Committed Costs '!G:G) | H74: =SUMIF('Change Orders'!F:F,'Project Detail'!B74,'Change Orders'!E:E) | I74: =SUMIF(Invoices!B:B,B74,Invoices!G:G) | J74: 0 | K74: =I74-J74 | L74: =+M74-G74 | M74: =IF((F74+H74)>G74,F74+H74,G74) | N74: =F74-M74 | Q74: =M74-K74 | U74: =S74+T74+#REF! | Z74: =W74+X74+Y74 | AB74: =U74+Z74 | AD74: =Q74-AB74
B75: 301-12 | D75: N/A | E75: Artist Lounge | F75: =15000-15000 | G75: =SUMIF('Committed Costs '!C:C,B75,'Committed Costs '!G:G) | H75: =SUMIF('Change Orders'!F:F,'Project Detail'!B75,'Change Orders'!E:E) | I75: =SUMIF(Invoices!B:B,B75,Invoices!G:G) | J75: 0 | K75: =I75-J75 | L75: =+M75-G75 | M75: =IF((F75+H75)>G75,F75+H75,G75) | N75: =F75-M75 | Q75: =M75-K75 | U75: =S75+T75+#REF! | Z75: =W75+X75+Y75 | AB75: =U75+Z75 | AD75: =Q75-AB75
B76: 301-13 | D76: N/A | E76: Dressing Room | F76: =15000-15000 | G76: =SUMIF('Committed Costs '!C:C,B76,'Committed Costs '!G:G) | H76: =SUMIF('Change Orders'!F:F,'Project Detail'!B76,'Change Orders'!E:E) | I76: =SUMIF(Invoices!B:B,B76,Invoices!G:G) | J76: 0 | K76: =I76-J76 | L76: =+M76-G76 | M76: =IF((F76+H76)>G76,F76+H76,G76) | N76: =F76-M76 | Q76: =M76-K76 | U76: =S76+T76+#REF! | Z76: =W76+X76+Y76 | AB76: =U76+Z76 | AD76: =Q76-AB76
B77: 301-14 | D77: N/A | E77: Rugs | F77: =5000-5000 | G77: =SUMIF('Committed Costs '!C:C,B77,'Committed Costs '!G:G) | H77: =SUMIF('Change Orders'!F:F,'Project Detail'!B77,'Change Orders'!E:E) | I77: =SUMIF(Invoices!B:B,B77,Invoices!G:G) | J77: 0 | K77: =I77-J77 | L77: =+M77-G77 | M77: =IF((F77+H77)>G77,F77+H77,G77) | N77: =F77-M77 | Q77: =M77-K77 | U77: =S77+T77+#REF! | Z77: =W77+X77+Y77 | AB77: =U77+Z77 | AD77: =Q77-AB77
B78: 301-15 | D78: N/A | E78: Catering Room Chairs | F78: =8000-6820.3-1179.7 | G78: =SUMIF('Committed Costs '!C:C,B78,'Committed Costs '!G:G) | H78: =SUMIF('Change Orders'!F:F,'Project Detail'!B78,'Change Orders'!E:E) | I78: =SUMIF(Invoices!B:B,B78,Invoices!G:G) | J78: 0 | K78: =I78-J78 | L78: =+M78-G78 | M78: 0 | N78: =F78-M78 | Q78: =M78-K78 | U78: =S78+T78+#REF! | Z78: =W78+X78+Y78 | AB78: =U78+Z78 | AD78: =Q78-AB78
B79: 301-16 | D79: N/A | E79: Catering Room Tables | F79: =4000-4000 | G79: =SUMIF('Committed Costs '!C:C,B79,'Committed Costs '!G:G) | H79: =SUMIF('Change Orders'!F:F,'Project Detail'!B79,'Change Orders'!E:E) | I79: =SUMIF(Invoices!B:B,B79,Invoices!G:G) | J79: 0 | K79: =I79-J79 | L79: =+M79-G79 | M79: 0 | N79: =F79-M79 | Q79: =M79-K79 | U79: =S79+T79+#REF! | Z79: =W79+X79+Y79 | AB79: =U79+Z79 | AD79: =Q79-AB79
B80: 301-17 | D80: Multiple Vendors | E80: Box & VIP Seats | F80: ='Budget Summary'!#REF! | G80: =SUMIF('Committed Costs '!C:C,B80,'Committed Costs '!G:G) | H80: =SUMIF('Change Orders'!F:F,'Project Detail'!B80,'Change Orders'!E:E) | I80: =SUMIF(Invoices!B:B,B80,Invoices!G:G) | J80: 0 | K80: =I80-J80 | L80: =+M80-G80 | M80: =IF((F80+H80)>G80,F80+H80,G80) | N80: =F80-M80 | Q80: =M80-K80 | U80: =S80+T80 | Z80: =W80+X80+Y80 | AB80: =U80+Z80 | AD80: =Q80-AB80
B81: 301-18 | F81: 0 | G81: =SUMIF('Committed Costs '!C:C,B81,'Committed Costs '!G:G) | H81: =SUMIF('Change Orders'!F:F,'Project Detail'!B81,'Change Orders'!E:E) | I81: =SUMIF(Invoices!B:B,B81,Invoices!G:G) | J81: 0 | K81: =I81-J81 | L81: =+M81-G81 | M81: =IF((F81+H81)>G81,F81+H81,G81) | N81: =F81-M81
C82: 301 | E82: Total Seating | F82: =SUM(F64:F81) | G82: =SUM(G64:G81) | H82: =SUM(H64:H81) | I82: =SUM(I64:I81) | J82: =SUM(J64:J81) | K82: =SUM(K64:K81) | L82: =SUM(L64:L81) | M82: =SUM(M64:M81) | N82: =SUM(N64:N81) | Q82: =SUM(Q64:Q80) | S82: =SUM(S64:S80) | T82: =SUM(T64:T80) | U82: =U64+U80 | W82: =SUM(W64:W80) | X82: =SUM(X64:X80) | Y82: =SUM(Y64:Y80) | Z82: =SUM(Z64:Z80) | AB82: =AB64+AB80 | AD82: =AD64+AD80
B83: 302 | D83: Concessions
B84: 302-1 | D84: TriMark | E84: Kitchen and Bars | F84: ='Budget Summary'!D50 | G84: =SUMIF('Committed Costs '!C:C,B84,'Committed Costs '!G:G) | H84: =SUMIF('Change Orders'!F:F,'Project Detail'!B84,'Change Orders'!E:E) | I84: =SUMIF(Invoices!B:B,B84,Invoices!G:G) | J84: 0 | K84: =I84-J84 | L84: =+M84-G84 | M84: =G84 | N84: =F84-M84 | Q84: =M84-K84 | U84: =S84+T84 | Z84: =W84+X84+Y84 | AB84: =U84+Z84 | AD84: =Q84-AB84
B85: 302-2 | D85: TBD | E85: Miscellaneous Equipment (POS) | F85: ='Budget Summary'!D51 | G85: =SUMIF('Committed Costs '!C:C,B85,'Committed Costs '!G:G) | H85: =SUMIF('Change Orders'!F:F,'Project Detail'!B85,'Change Orders'!E:E) | I85: =SUMIF(Invoices!B:B,B85,Invoices!G:G) | J85: 0 | K85: =I85-J85 | L85: =+M85-G85 | M85: =G85 | N85: =F85-M85 | Q85: =M85-K85 | U85: =S85+T85 | Z85: =W85+X85+Y85 | AB85: =U85+Z85 | AD85: =Q85-AB85
B86: 302-3 | D86: TBD | E86: Portable Bars | F86: ='Budget Summary'!#REF! | G86: =SUMIF('Committed Costs '!C:C,B86,'Committed Costs '!G:G) | H86: =SUMIF('Change Orders'!F:F,'Project Detail'!B86,'Change Orders'!E:E) | I86: =SUMIF(Invoices!B:B,B86,Invoices!G:G) | J86: 0 | K86: =I86-J86 | L86: =+M86-G86 | M86: 0 | N86: =F86-M86 | Q86: =M86-K86 | U86: =S86+T86 | Z86: =W86+X86+Y86 | AB86: =U86+Z86 | AD86: =Q86-AB86
B87: 302-4 | F87: 0 | G87: =SUMIF('Committed Costs '!C:C,B87,'Committed Costs '!G:G) | H87: =SUMIF('Change Orders'!F:F,'Project Detail'!B87,'Change Orders'!E:E) | I87: =SUMIF(Invoices!B:B,B87,Invoices!G:G) | J87: 0 | K87: =I87-J87 | L87: =+M87-G87 | M87: =IF((F87+H87)>G87,F87+H87,G87) | N87: =F87-M87 | Q87: =M87-K87 | U87: =S87+T87 | Z87: =W87+X87+Y87 | AB87: =U87+Z87 | AD87: =Q87-AB87
C88: 302 | E88: Total Concession | F88: =SUM(F84:F87) | G88: =SUM(G84:G87) | H88: =SUM(H84:H87) | I88: =SUM(I84:I87) | J88: =SUM(J84:J87) | K88: =SUM(K84:K87) | L88: =SUM(L84:L87) | M88: =SUM(M84:M87) | N88: =SUM(N84:N87) | Q88: =SUM(Q84:Q87) | S88: =SUM(S84:S87) | T88: =SUM(T84:T87) | U88: =SUM(U84:U87) | W88: =SUM(W84:W87) | X88: =SUM(X84:X87) | Y88: =SUM(Y84:Y87) | Z88: =SUM(Z84:Z87) | AB88: =SUM(AB84:AB87) | AD88: =SUM(AD84:AD87)
B89: 303 | D89: Phone & Data Systems
B90: 303-1 | D90: Multiple Vendors | E90: CCTV | F90: ='Budget Summary'!D52 | G90: =SUMIF('Committed Costs '!C:C,B90,'Committed Costs '!G:G) | H90: =SUMIF('Change Orders'!F:F,'Project Detail'!B90,'Change Orders'!E:E) | I90: =SUMIF(Invoices!B:B,B90,Invoices!G:G) | J90: 0 | K90: =I90-J90 | L90: =+M90-G90 | M90: =IF((F90+H90)>G90,F90+H90,G90) | N90: =F90-M90 | Q90: =M90-K90 | U90: =S90+T90 | Z90: =W90+X90+Y90 | AB90: =U90+Z90 | AD90: =Q90-AB90
B91: 303-2 | D91: Entisys, Insight, Multi-Link | E91: Data /Wifi Systems | F91: ='Budget Summary'!D53 | G91: =SUMIF('Committed Costs '!C:C,B91,'Committed Costs '!G:G) | H91: =SUMIF('Change Orders'!F:F,'Project Detail'!B91,'Change Orders'!E:E) | I91: =SUMIF(Invoices!B:B,B91,Invoices!G:G) | J91: 0 | K91: =I91-J91 | L91: =+M91-G91 | M91: =IF((F91+H91)>G91,F91+H91,G91) | N91: =F91-M91 | Q91: =M91-K91 | U91: =S91+T91 | Z91: =W91+X91+Y91 | AB91: =U91+Z91 | AD91: =Q91-AB91
C92: 303 | E92: Total Phone & Data | F92: =SUM(F90:F91) | G92: =SUM(G90:G91) | H92: =SUM(H90:H91) | I92: =SUM(I90:I91) | J92: =SUM(J90:J91) | K92: =SUM(K90:K91) | L92: =SUM(L90:L91) | M92: =SUM(M90:M91) | N92: =SUM(N90:N91) | Q92: =SUM(Q90:Q91) | S92: =SUM(S90:S91) | T92: =SUM(T90:T91) | U92: =SUM(U90:U91) | W92: =SUM(W90:W91) | X92: =SUM(X90:X91) | Y92: =SUM(Y90:Y91) | Z92: =SUM(Z90:Z91) | AB92: =SUM(AB90:AB91) | AD92: =SUM(AD90:AD91)
B93: 304 | D93: Office Furniture
B94: 304-1 | D94: Pivot / YE Co. | E94: Office Furniture (From Furniture Tracker) | F94: ='Budget Summary'!D54 | G94: =SUMIF('Committed Costs '!C:C,B94,'Committed Costs '!G:G) | H94: =SUMIF('Change Orders'!F:F,'Project Detail'!B94,'Change Orders'!E:E) | I94: =SUMIF(Invoices!B:B,B94,Invoices!G:G) | J94: 0 | K94: =I94-J94 | L94: =+M94-G94 | M94: =G94 | N94: =F94-M94 | Q94: =M94-K94 | U94: =S94+T94 | Z94: =W94+X94+Y94 | AB94: =U94+Z94 | AD94: =Q94-AB94
B95: 304-2 | D95: N/A | E95: Administration Refrigerator | F95: =600-600 | G95: =SUMIF('Committed Costs '!C:C,B95,'Committed Costs '!G:G) | H95: =SUMIF('Change Orders'!F:F,'Project Detail'!B95,'Change Orders'!E:E) | I95: =SUMIF(Invoices!B:B,B95,Invoices!G:G) | J95: 0 | K95: =I95-J95 | L95: =+M95-G95 | M95: =IF((F95+H95)>G95,F95+H95,G95) | N95: =F95-M95 | Q95: =G95-K95 | U95: =S95+T95+#REF! | Z95: =W95+X95+Y95 | AB95: =U95+Z95
B96: 304-3 | D96: N/A | E96: Desks-Production | F96: =1000-1000 | G96: =SUMIF('Committed Costs '!C:C,B96,'Committed Costs '!G:G) | H96: =SUMIF('Change Orders'!F:F,'Project Detail'!B96,'Change Orders'!E:E) | I96: =SUMIF(Invoices!B:B,B96,Invoices!G:G) | J96: 0 | K96: =I96-J96 | L96: =+M96-G96 | M96: =IF((F96+H96)>G96,F96+H96,G96) | N96: =F96-M96 | Q96: =G96-K96 | U96: =S96+T96+#REF! | Z96: =W96+X96+Y96 | AB96: =U96+Z96
B97: 304-4 | D97: N/A | E97: Desk Chairs-Production | F97: =800-800 | G97: =SUMIF('Committed Costs '!C:C,B97,'Committed Costs '!G:G) | H97: =SUMIF('Change Orders'!F:F,'Project Detail'!B97,'Change Orders'!E:E) | I97: =SUMIF(Invoices!B:B,B97,Invoices!G:G) | J97: 0 | K97: =I97-J97 | L97: =+M97-G97 | M97: =IF((F97+H97)>G97,F97+H97,G97) | N97: =F97-M97 | Q97: =G97-K97 | U97: =S97+T97+#REF! | Z97: =W97+X97+Y97 | AB97: =U97+Z97
B98: 304-5 | D98: N/A | E98: File Cabinets-Production | F98: =800-800 | G98: =SUMIF('Committed Costs '!C:C,B98,'Committed Costs '!G:G) | H98: =SUMIF('Change Orders'!F:F,'Project Detail'!B98,'Change Orders'!E:E) | I98: =SUMIF(Invoices!B:B,B98,Invoices!G:G) | J98: 0 | K98: =I98-J98 | L98: =+M98-G98 | M98: =IF((F98+H98)>G98,F98+H98,G98) | N98: =F98-M98 | Q98: =G98-K98 | U98: =S98+T98+#REF! | Z98: =W98+X98+Y98 | AB98: =U98+Z98
C99: 304 | E99: Total Office Furniture | F99: =SUM(F94:F98) | G99: =SUM(G94:G98) | H99: =SUM(H94:H98) | I99: =SUM(I94:I98) | J99: =SUM(J94:J98) | K99: =SUM(K94:K98) | L99: =SUM(L94:L98) | M99: =SUM(M94:M98) | N99: =SUM(N94:N98) | Q99: =SUM(Q94:Q98) | S99: =SUM(S94:S98) | T99: =SUM(T94:T98) | U99: =U94 | W99: =SUM(W94:W98) | X99: =SUM(X94:X98) | Y99: =SUM(Y94:Y98) | Z99: =SUM(Z94:Z98) | AB99: =AB94 | AD99: =SUM(AD94:AD98)
B100: 305 | D100: Signage/Graphics
B101: 305-1 | D101: TBD | E101: Exterior Signage / Wayfinding | F101: 0 | G101: =SUMIF('Committed Costs '!C:C,B101,'Committed Costs '!G:G) | H101: =SUMIF('Change Orders'!F:F,'Project Detail'!B101,'Change Orders'!E:E) | I101: =SUMIF(Invoices!B:B,B101,Invoices!G:G) | J101: 0 | K101: =I101-J101 | L101: =+M101-G101 | M101: 0 | N101: =F101-M101 | Q101: =M101-K101 | U101: =S101+T101 | Z101: =W101+X101+Y101 | AB101: =U101+Z101 | AD101: =Q101-AB101
B102: 305-2 | D102: TBD | E102: Interior Art & Décor "Warehouse Scope" | F102: 0 | G102: =SUMIF('Committed Costs '!C:C,B102,'Committed Costs '!G:G) | H102: =SUMIF('Change Orders'!F:F,'Project Detail'!B102,'Change Orders'!E:E) | I102: =SUMIF(Invoices!B:B,B102,Invoices!G:G) | J102: 0 | K102: =I102-J102 | L102: =+M102-G102 | M102: =G102 | N102: =F102-M102 | Q102: =M102-K102 | U102: =S102+T102 | Z102: =W102+X102+Y102 | AB102: =U102+Z102 | AD102: =Q102-AB102
B103: 305-3 | F103: =35000-35000 | G103: =SUMIF('Committed Costs '!C:C,B103,'Committed Costs '!G:G) | H103: =SUMIF('Change Orders'!F:F,'Project Detail'!B103,'Change Orders'!E:E) | I103: =SUMIF(Invoices!B:B,B103,Invoices!G:G) | J103: 0 | K103: =I103-J103 | L103: =+M103-G103 | M103: =IF((F103+H103)>G103,F103+H103,G103) | N103: =F103-M103 | Q103: =M103-K103 | U103: =S103+T103 | Z103: =W103+X103+Y103 | AB103: =U103+Z103 | AD103: =Q103-AB103
B104: 305-4 | F104: =1000-1000 | G104: =SUMIF('Committed Costs '!C:C,B104,'Committed Costs '!G:G) | H104: =SUMIF('Change Orders'!F:F,'Project Detail'!B104,'Change Orders'!E:E) | I104: =SUMIF(Invoices!B:B,B104,Invoices!G:G) | J104: 0 | K104: =I104-J104 | L104: =+M104-G104 | M104: =IF((F104+H104)>G104,F104+H104,G104) | N104: =F104-M104 | Q104: =M104-K104 | U104: =S104+T104 | Z104: =W104+X104+Y104 | AB104: =U104+Z104 | AD104: =Q104-AB104
B105: 305-5 | F105: =20000-20000 | G105: =SUMIF('Committed Costs '!C:C,B105,'Committed Costs '!G:G) | H105: =SUMIF('Change Orders'!F:F,'Project Detail'!B105,'Change Orders'!E:E) | I105: =SUMIF(Invoices!B:B,B105,Invoices!G:G) | J105: 0 | K105: =I105-J105 | L105: =+M105-G105 | M105: =IF((F105+H105)>G105,F105+H105,G105) | N105: =F105-M105 | Q105: =M105-K105 | U105: =S105+T105 | Z105: =W105+X105+Y105 | AB105: =U105+Z105 | AD105: =Q105-AB105
B106: 305-6 | F106: =1500-1500 | G106: =SUMIF('Committed Costs '!C:C,B106,'Committed Costs '!G:G) | H106: =SUMIF('Change Orders'!F:F,'Project Detail'!B106,'Change Orders'!E:E) | I106: =SUMIF(Invoices!B:B,B106,Invoices!G:G) | J106: 0 | K106: =I106-J106 | L106: =+M106-G106 | M106: =IF((F106+H106)>G106,F106+H106,G106) | N106: =F106-M106 | Q106: =M106-K106 | U106: =S106+T106 | Z106: =W106+X106+Y106 | AB106: =U106+Z106 | AD106: =Q106-AB106
B107: 305-7 | F107: =1500-1500 | G107: =SUMIF('Committed Costs '!C:C,B107,'Committed Costs '!G:G) | H107: =SUMIF('Change Orders'!F:F,'Project Detail'!B107,'Change Orders'!E:E) | I107: =SUMIF(Invoices!B:B,B107,Invoices!G:G) | J107: 0 | K107: =I107-J107 | L107: =+M107-G107 | M107: =IF((F107+H107)>G107,F107+H107,G107) | N107: =F107-M107 | Q107: =M107-K107 | U107: =S107+T107 | Z107: =W107+X107+Y107 | AB107: =U107+Z107 | AD107: =Q107-AB107
B108: 305-8 | F108: =10000-10000 | G108: =SUMIF('Committed Costs '!C:C,B108,'Committed Costs '!G:G) | H108: =SUMIF('Change Orders'!F:F,'Project Detail'!B108,'Change Orders'!E:E) | I108: =SUMIF(Invoices!B:B,B108,Invoices!G:G) | J108: 0 | K108: =I108-J108 | L108: =+M108-G108 | M108: =IF((F108+H108)>G108,F108+H108,G108) | N108: =F108-M108 | Q108: =M108-K108 | U108: =S108+T108 | Z108: =W108+X108+Y108 | AB108: =U108+Z108 | AD108: =Q108-AB108
...

Sheet Committed Costs 
B2: Committed Costs
B3: Executed Date | C3: Cost Code | D3: Vendor | E3: Description | F3: P.O. Number | G3: Contract Value | H3: Notes
F9: Total Commitments | G9: =SUBTOTAL(9,G4:G6)
G10: =G9='Project At-a-Glance'!D25

Sheet Invoices
B2: Invoices
B3: Cost Code | C3: Vendor | D3: Description | E3: Invoice # | F3: Invoice Date | G3: Invoice Amount | H3: GL Period | I3: Notes | J3: Payment Status
B5: 2022 Invoices
F10: March Invoices Total | G10: =SUBTOTAL(9,G6:G9)
F13: INVOICES GRAND TOTAL | G13: =SUM(G10)
G14: =G13='Project At-a-Glance'!E25

Sheet Change Orders
B2: Date Issued | C2: C.O. Number | D2: Vendor | E2: Amount | F2: Cost Code | G2: Description | H2: Notes
D29: Total Change Orders | E29: =SUM(E3:E28)

Sheet Contingency
B2: Date | C2: Cost Code | D2: Vendor | E2: Description | F2: Amount Applied | G2: Remaining Balance | H2: Notes
B4: March 2020 Contingency | J4: Contingency
B5: 43921 | C5: N/A | D5: N/A | E5: Initial Contingency Amount | F5: 0 | G5: =+J5-F5 | J5: ='Project Detail'!F170
E6: March Contingency Totals | F6: =SUBTOTAL(9,F5) | G6: =G5
E9: CONTINGENCY TOTALS | F9: =SUM(F6) | G9: =G6

Sheet Risk Report
A1: Risk Report
A3: Requestor | C3: Item | E3: High | G3: Expected Settlement Value | I3: Low | K3: Notes
A4: Project Team
A5: Project Team
A6: Project Team
A7: Project Team
A8: Project Team
A9: Project Team
A10: Project Team
A11: Project Team
A12: Project Team
A13: Project Team
A14: Project Team
E15: =SUM(E4:E14) | G15: =SUM(G4:G14) | I15: =SUM(I4:I14)
C19: Current Sources (as of 01/31/2023) | E19: Remaining Contingency | G19: =Contingency!G9
E21: Contingency Balance | G21: =G19-G15
E23: Exposure | G23: =IF(G15>G19,G19-G15,0)
C26: *Sources reflect over budget items pending resolution.
