Workbook

Sheet Budget Summary
A1: 165 Randolph St. Brooklyn NY
A2: Warehouse Conversion / Add Second Level & Roof Deck
A3: Theater GA Standing: 7,440
A4: Theater GA Seated: 5,954
A5: Eating & Drinking : 769
A6: VIP Lounge
A8: SF: | B8: 135, 953 | J8: =130000*600 -> 78000000
A9: 46272
A10: Version #: 1
A13: Construction Duration: 20 Months
A14: Expected Certificate of Occupancy: TBD
A15: Expected Frist Show:
A16: Project Completion:
D19: Budget Total | F19: 2023 | G19: 2024 | H19: 2025
A20: 000 | B20: OFF SITE COSTS
B21: Parking Garage - 260/spaces | D21: =86*25000 -> 2150000 | F21: 0 | G21: 0 | H21: 0
B22: Escalation (Calculated at 5%) | D22: =D21*0.05 -> 107500 | F22: 0 | G22: 0 | H22: 0
D23: =SUM(D21:D22) -> 2257500 | F23: 0 | G23: 0 | H23: 0
A24: 100 | B24: Building & Fit-Out Costs
B25: Trade Costs | D25: ='Building & Fit-outBudget Detail'!C49-'Building & Fit-outBudget Detail'!C47 -> 37945960 | F25: 0 | G25: 0 | H25: 0
B26: Trade Costs To Be Priced | D26: 12000000
B27: General Conditions and General Requirements | D27: 3141000 | F27: 0 | G27: 0 | H27: 0 | I27: 90 wks
B28: Overhead, Profit & Insurance (9% Combined) | D28: =SUM(D25:D27)*0.09 -> 4777826.4 | F28: 0 | G28: 0 | H28: 0
B29: Contractor Contingency 10% | D29: =SUM(D25:D28)*0.1 -> 5786478.6 | F29: 0 | G29: 0 | H29: 0
B30: Escalation (Calculated at 5%) | F30: 0 | G30: 0 | H30: 0
D31: =SUM(D25:D30) -> 63651265 | F31: 0 | G31: 0 | H31: 0 | I31: =D31/135953 -> 468.1858
A32: 200 | B32: Soft Costs
B33: Abatement | D33: ='Soft Cost & FF&E Budget Detail'!E16 -> 1483680 | F33: 0 | G33: 0 | H33: 0
B34: Feasibility Study | D34: ='Soft Cost & FF&E Budget Detail'!E21 -> 342000
B35: Architectural / Engineering / Consultant Fees | D35: ='Soft Cost & FF&E Budget Detail'!E38 -> 3526000 | F35: 0 | G35: 0 | H35: 0
B36: Site & Civil | D36: ='Soft Cost & FF&E Budget Detail'!E43 -> 10000 | F36: 0 | G36: 0 | H36: 0
B37: Traffic Engineering | D37: ='Soft Cost & FF&E Budget Detail'!E51 -> 10000
B38: Acousticsl Engineering | D38: ='Soft Cost & FF&E Budget Detail'!E58 -> 15000
B39: Geotechnical Engineering | D39: ='Soft Cost & FF&E Budget Detail'!E66 -> 150000
B40: Enviromental Studies | D40: ='Soft Cost & FF&E Budget Detail'!E71 -> 0
B41: Zoning/Permit Fees | D41: ='Soft Cost & FF&E Budget Detail'!E82 -> 628297.48 | F41: 0 | G41: 0 | H41: 0
B42: Utility Connection Fees | D42: ='Soft Cost & FF&E Budget Detail'!E90 -> 50000
B43: Attorney Fees | D43: ='Soft Cost & FF&E Budget Detail'!E98 -> 0
B44: Testing / Quality Control | D44: ='Soft Cost & FF&E Budget Detail'!E103 -> 50000 | F44: ='Soft Cost & FF&E Budget Detail'!E103 -> 50000 | G44: 0 | H44: 0
B45: Project Management (Live Nation) | D45: ='Soft Cost & FF&E Budget Detail'!E109 -> 520000 | F45: 0 | G45: 0 | H45: 0
B46: Reimbursable Expenses | D46: ='Soft Cost & FF&E Budget Detail'!E118 -> 0 | F46: 0 | G46: 0 | H46: 0
D47: =SUM(D33:D46) -> 6784977.5 | F47: =SUM(F33:F46) -> 50000 | G47: =SUM(G33:G46) -> 0 | H47: =SUM(H33:H46) -> 0 | I47: =D47/135953 -> 49.906787
A48: 300 | B48: FF&E Costs
B49: Seating & Furniture | D49: ='Soft Cost & FF&E Budget Detail'!E152 -> 1043750 | F49: 0 | G49: 0 | H49: 0
B50: Kitchen & Bar Equipment | D50: ='Soft Cost & FF&E Budget Detail'!E174-'Soft Cost & FF&E Budget Detail'!E171 -> 1317000 | F50: 0 | G50: 0 | H50: 0
B51: POS | D51: ='Soft Cost & FF&E Budget Detail'!E171 -> 0 | F51: 0 | G51: 0 | H51: 0
B52: CCTV | D52: ='Soft Cost & FF&E Budget Detail'!E180 -> 220000 | F52: 0 | G52: 0 | H52: 0
B53: Data (Wifi & Network) Systems | D53: ='Soft Cost & FF&E Budget Detail'!E181-'Soft Cost & FF&E Budget Detail'!E180 -> 200000 | F53: 0 | G53: 0 | H53: 0
B54: Office Furniture | D54: ='Soft Cost & FF&E Budget Detail'!E195 -> 65000 | F54: 0 | G54: 0 | H54: 0
B55: Exterior Signage / Wayfinding | D55: ='Soft Cost & FF&E Budget Detail'!E206+'Soft Cost & FF&E Budget Detail'!E201 -> 500000 | F55: 0 | G55: 0 | H55: 0
B56: Interior Art & Décor "Warehouse Scope" | D56: ='Soft Cost & FF&E Budget Detail'!E210 -> 150000 | F56: 0 | G56: 0 | H56: 0
B57: Administration | D57: ='Soft Cost & FF&E Budget Detail'!E226 -> 93000 | F57: 0 | G57: 0 | H57: 0
B58: Facility | D58: ='Soft Cost & FF&E Budget Detail'!E241 -> 26000
B59: Operations | D59: ='Soft Cost & FF&E Budget Detail'!E271 -> 29000
B60: Production - FF&E | D60: ='Soft Cost & FF&E Budget Detail'!E286 -> 193500 | F60: 0 | G60: 0 | H60: 0
B61: Production - Soft Goods | D61: ='Soft Cost & FF&E Budget Detail'!E290 -> 500000 | F61: 0 | G61: 0 | H61: 0
B62: Production - Audio & Video System | D62: ='Soft Cost & FF&E Budget Detail'!E302+'Soft Cost & FF&E Budget Detail'!E298 -> 1685000 | F62: 0 | G62: 0 | H62: 0
B63: Production - Performance Lighting | D63: ='Soft Cost & FF&E Budget Detail'!E307 -> 520000
B64: Architectural Lighting | D64: ='Soft Cost & FF&E Budget Detail'!E316 -> 1750000 | F64: 0 | G64: 0 | H64: 0
D65: =SUM(D49:D64) -> 8292250 | F65: =SUM(F49:F64) -> 0 | G65: =SUM(G49:G64) -> 0 | H65: =SUM(H49:H64) -> 0 | I65: =D65/135953 -> 60.993505
A67: 400 | B67: Soft Costs & FFE Contingency 10% | D67: =(D23+D31+D47+D65)*0.1 -> 8098599.2 | F67: 0 | G67: 0 | H67: 0 | I67: =D67/135953 -> 59.56911
B68: \
B69: Total Capital | D69: =D23+D67+D65+D47+D31 -> 89084591 | F69: =F67+F65+F47+F31 -> 50000 | G69: =G67+G65+G47+G31 -> 0 | H69: =H67+H65+H47+H31 -> 0
B71: $ PER SF | D71: =D69/135953 -> 655.26021 | I71: =SUM(I67+I65+I47+I31) -> 638.65521

Sheet Soft Cost & FF&E Budget Detail
A1: 165 Randolph St Brooklyn NY
A2: Scope : | B2: Warehouse Conversion / Add Second Level & Roof Decks
A3: Capacity: | B3: ##
A4: SF: | B4: 135953
A5: Date:
A6: Version: | B6: 1
A10: 200 | B10: SOFT COSTS
A11: 201 | B11: DESCRIPTION | C11: QTY | D11: UNIT PRICE | E11: BUDGET TOTAL | F11: NOTES
B12: Abatement
A13: 1 | B13: Pipe Insulation Abatement | C13: 190 | D13: 72 | E13: =C13*D13 -> 13680
A14: 2 | B14: Roof Abatement | C14: 70000 | D14: 21 | E14: =C14*D14 -> 1470000
B16: Total Abatement | E16: =SUM(E13:E15) -> 1483680
A17: 202 | B17: DESCRIPTION | C17: QTY | D17: UNIT PRICE | E17: BUDGET TOTAL | F17: NOTES
B18: Feasibility Study
A19: 1 | B19: Due Diligence & Feasibility Study | C19: 1 | D19: 342000 | E19: =C19*D19 -> 342000
B21: Total Feasibility Study | E21: =E19 -> 342000
A22: 203 | B22: DESCRIPTION | C22: QTY | D22: UNIT PRICE | E22: BUDGET TOTAL | F22: NOTES
B23: Architectural Fees
A24: 1 | B24: Conceptual & Brand Development | C24: 1 | D24: 45000 | E24: =C24*D24 -> 45000
A25: =A24+1 -> 2 | B25: Interior Design | C25: 1 | D25: 90000 | E25: =C25*D25 -> 90000
A26: =A25+1 -> 3 | B26: Architecture & Engineering | C26: 1 | D26: 3100000 | E26: =C26*D26 -> 3100000
A27: =A26+1 -> 4 | B27: Architecture | D27: 0 | E27: =C27*D27 -> 0 | F27: Carried in line #3
A28: =A27+1 -> 5 | B28: MEP Engineering | D28: 0 | E28: =C28*D28 -> 0 | F28: Carried in line #3
A29: =A28+1 -> 6 | B29: Structural Engineering | D29: 0 | E29: =C29*D29 -> 0 | F29: Carried in line #3
A30: =A29+1 -> 7 | B30: MEP Consultant | C30: 1 | D30: 30000 | E30: =C30*D30 -> 30000
A31: =A30+1 -> 8 | B31: Lighting Design (Bandit) | C31: 1 | D31: 51000 | E31: =C31*D31 -> 51000
A32: =A31+1 -> 9 | B32: Kitchen Equipment Design (TriMark) | C32: 1 | D32: 20000 | E32: =C32*D32 -> 20000
A33: =A32+1 -> 10 | B33: LV/AV Design | C33: 1 | D33: 35000 | E33: =C33*D33 -> 35000
A34: =A33+1 -> 11 | B34: Signage & Way Finding Design | C34: 1 | D34: 75000 | E34: =C34*D34 -> 75000
A35: =A34+1 -> 12 | B35: Renderings | C35: 1 | D35: 50000 | E35: =C35*D35 -> 50000
A36: =A35+1 -> 13 | B36: Reimbursables | C36: 1 | D36: 30000 | E36: =C36*D36 -> 30000
B38: Total Architectural Fees | E38: =SUM(E24:E37) -> 3526000
A39: 204 | B39: DESCRIPTION | C39: QTY | D39: UNIT PRICE | E39: BUDGET TOTAL | F39: NOTES
B40: Civil Engineering
A41: 1 | B41: Civil Engineering | C41: 1 | D41: 10000 | E41: =C41*D41 -> 10000 | F41: Exterior work: New Sidewalks, Street Work
B43: Total Civil Engineering | E43: =SUM(E41:E41) -> 10000
A44: 205 | B44: DESCRIPTION | C44: QTY | D44: UNIT PRICE | E44: BUDGET TOTAL | F44: NOTES
B45: Traffic Engineering
A46: 1 | B46: Traffic Engineering | C46: 1 | D46: 10000 | E46: =C46*D46 -> 10000 | F46: Verify w/ Traffic Consultant Report
A47: 2 | D47: 0 | E47: =C47*D47 -> 0
B51: Total Traffic Engineering | E51: =SUM(E46:E50) -> 10000
A52: 206 | B52: DESCRIPTION | C52: QTY | D52: UNIT PRICE | E52: BUDGET TOTAL | F52: NOTES
B53: Acoustical Engineering
A54: 1 | B54: Sound and Vibration Testing | C54: 1 | D54: 15000 | E54: =C54*D54 -> 15000 | F54: Sound & Vibration Testing / Design Documentation & Consulting
A56: 4 | D56: 0 | E56: =C56*D56 -> 0
A57: 5 | D57: 0 | E57: =C57*D57 -> 0
B58: Total Acoustical Engineering | E58: =SUM(E54:E57) -> 15000
A59: 207 | B59: DESCRIPTION | C59: QTY | D59: UNIT PRICE | E59: BUDGET TOTAL | F59: NOTES
B60: Geotechnical Engineering
A61: 1 | B61: Geotechnical Engineering | C61: 1 | D61: 150000 | E61: =C61*D61 -> 150000 | F61: 13 Borings 50' deep required for ST Permit
B66: Total Geotechnical Engineering | E66: =SUM(E61:E65) -> 150000
A67: 208 | B67: DESCRIPTION | C67: QTY | D67: UNIT PRICE | E67: BUDGET TOTAL | F67: NOTES
B68: Environmental Studies
A69: 1 | B69: Carried in Feasibility Study | E69: =C69*D69 -> 0
B71: Total Environmental Studies | E71: =SUM(E69:E70) -> 0
A72: 209 | B72: DESCRIPTION | C72: QTY | D72: UNIT PRICE | E72: BUDGET TOTAL | F72: NOTES
B73: Zoning / Permit Fees
A74: 1 | B74: Permit fees & plan review fees | C74: 1 | D74: ='Budget Summary'!D25*0.013 -> 493297.48 | E74: =C74*D74 -> 493297.48 | F74: 1.3% Trade Costs
A75: =A74+1 -> 2 | B75: Special Projects Program | C75: 1 | D75: 50000 | E75: =C75*D75 -> 50000
A76: 3 | B76: MEP and misc. permit fees | C76: 1 | D76: 10000 | E76: =C76*D76 -> 10000
A77: 4 | B77: Expeditor (allowance for Addt'l services) | C77: 0 | E77: =C77*D77 -> 0
A78: 5 | B78: FA Consultant & Expediting Services | C78: 1 | D78: 35000 | E78: =C78*D78 -> 35000 | F78: Consulting/ Filing/ FA Inspection Filing & Inspection Scheduling/ TCO Affidavit/ FDNY NOD
A79: 6 | B79: Fire Safety & Emergency Action Plan | C79: 1 | D79: 21500 | E79: =C79*D79 -> 21500
A80: 7 | B80: Fire Protection Plan & Filing with FDNY | C80: 1 | D80: 18500 | E80: =C80*D80 -> 18500
B82: Total Zoning / Permit Fees | E82: =SUM(E74:E80) -> 628297.48
A83: 210 | B83: DESCRIPTION | C83: QTY | D83: UNIT PRICE | E83: BUDGET TOTAL | F83: NOTES
B84: Utility Connection Fees
A85: 1 | B85: Electrical Service Upgrade | C85: 1 | D85: 50000 | E85: =C85*D85 -> 50000 | F85: Service upgrade required. Vault located in street, new conduit and feeders from vault into MPOE electrical room. Only Con Ed costs carried.
B90: Total Utility Connection Fees | E90: =SUM(E85:E89) -> 50000
A91: 211 | B91: DESCRIPTION | C91: QTY | D91: UNIT PRICE | E91: BUDGET TOTAL | F91: NOTES
B92: Attorney Fees
A93: 1 | B93: SLA Legal Fees carried in Feasibility DD | C93: 0 | D93: 0 | E93: =C93*D93 -> 0
B98: Total Attorney Fees | E98: =SUM(E93:E97) -> 0
A99: 212 | B99: DESCRIPTION | C99: QTY | D99: UNIT PRICE | E99: BUDGET TOTAL | F99: NOTES
B100: Testing / Quality Control
A101: 1 | B101: Controlled inspections | C101: 1 | D101: 50000 | E101: =C101*D101 -> 50000
A102: 2
B103: Total Testing / Quality Control | E103: =SUM(E101:E102) -> 50000
A104: 213 | B104: DESCRIPTION | C104: QTY | D104: UNIT PRICE | E104: BUDGET TOTAL | F104: NOTES
B105: Project Management
A106: 1 | B106: Project Management | C106: 1 | D106: 500000 | E106: =C106*D106 -> 500000
A107: =A106+1 -> 2 | B107: Estimating Services | C107: 1 | D107: 20000 | E107: =C107*D107 -> 20000
A108: =A107+1 -> 3 | D108: 0 | E108: =C108*D108 -> 0
B109: Total Miscellaneous | E109: =SUM(E106:E108) -> 520000
A110: 214 | B110: DESCRIPTION | C110: QTY | D110: UNIT PRICE | E110: BUDGET TOTAL | F110: NOTES
B111: Reimbursable Expenses
A112: 1 | C112: 0 | D112: 0 | E112: =C112*D112 -> 0
A114: =A113+1 -> 1 | D114: 0 | E114: =C114*D114 -> 0
A115: 4 | D115: 0 | E115: =C115*D115 -> 0
A116: =A115+1 -> 5 | D116: 0 | E116: =C116*D116 -> 0
A117: =A116+1 -> 6 | D117: 0 | E117: =C117*D117 -> 0
B118: Total Reimbursable Expenses | E118: =SUM(E112:E117) -> 0
B120: TOTAL SOFT COSTS | E120: =E109+E103+E98+E90+E82+E71+E66+E58+E51+E43+E38+E21+E16+E118 -> 6784977.5
A124: 300 | B124: FF&E COSTS
A125: SEATING & FURNITURE
A126: 301 | B126: DESCRIPTION | C126: QTY | D126: UNIT PRICE | E126: BUDGET TOTAL | F126: VENDOR | G126: NOTES
B127: Seating and Accessories
A128: =A127+1 -> 1 | B128: Theater Ground Floor GA Cushioned Folding Chairs | C128: 3714 | D128: 125 | E128: =D128*C128 -> 464250
A129: =A128+1 -> 2 | B129: Mezzanine Level Box Chairs | C129: 657 | D129: 300 | E129: =D129*C129 -> 197100
A130: =A129+1 -> 3 | B130: Mezzanine Level Elevated Chairs | C130: 63 | D130: 300 | E130: =D130*C130 -> 18900
...

Sheet Building & Fit-outBudget Detail
A1: Venue
A2: Scope : | B2: ='Soft Cost & FF&E Budget Detail'!B2 -> Warehouse Conversion / Add Second Level & Roof Decks
A3: Capacity: | B3: 7440
A4: SF: | B4: ='Soft Cost & FF&E Budget Detail'!B4 -> 135953
A5: Date: | B5: 46281
A6: Version: | B6: ='Soft Cost & FF&E Budget Detail'!B6 -> 1
A9: 100 | B9: BUILDING & FIT-OUT COSTS
A10: CSI # | B10: TRADE | C10: BUDGET | D10: COST/SF | E10: NOTES
A11: 013000 | B11: PROJECT REQUIREMENTS | C11: ='Building & Fit-out Breakdown'!F27 -> 3034000 | D11: =C11/$B$4 -> 22.316536
A12: 015800 | B12: SCAFFOLDING & STAGING | C12: ='Building & Fit-out Breakdown'!F37 -> 6170000 | D12: =C12/$B$4 -> 45.383331
A13: 024100 | B13: DEMOLITION | C13: ='Building & Fit-out Breakdown'!F63 -> 1287817 | D13: =C13/$B$4 -> 9.4725162
A14: 033000 | B14: CONCRETE | C14: ='Building & Fit-out Breakdown'!F93 -> 177450 | D14: =C14/$B$4 -> 1.3052305
A15: 042000 | B15: MASONRY | C15: ='Building & Fit-out Breakdown'!F119 -> 530010 | D15: =C15/$B$4 -> 3.8984796
A16: 044000 | B16: STONE & CERAMICS | C16: ='Building & Fit-out Breakdown'!F127 -> 764340 | D16: =C16/$B$4 -> 5.62209
A17: 055100 | B17: STRUCTURAL STEEL & MISC METALS | C17: ='Building & Fit-out Breakdown'!F151 -> 0 | D17: =C17/$B$4 -> 0
A18: 061000 | B18: ROUGH CARPENTRY | C18: ='Building & Fit-out Breakdown'!F160 -> 0 | D18: =C18/$B$4 -> 0
A19: 064000 | B19: MILLWORK AND FURNITURE INSTALL | C19: ='Building & Fit-out Breakdown'!F182 -> 0 | D19: =C19/$B$4 -> 0
A20: 075000 | B20: ROOFING | C20: ='Building & Fit-out Breakdown'!F196 -> 2557428 | D20: =C20/$B$4 -> 18.811119
A21: 078100 | B21: FIREPROOFING | C21: ='Building & Fit-out Breakdown'!F204 -> 0 | D21: =C21/$B$4 -> 0
A22: 081000 | B22: DOORS, FRAMES & HARDWARE | C22: ='Building & Fit-out Breakdown'!F213 -> 0 | D22: =C22/$B$4 -> 0
A23: 083000 | B23: SPECIAL DOORS | C23: ='Building & Fit-out Breakdown'!F219 -> 76000 | D23: =C23/$B$4 -> 0.55901672
A24: 084100 | B24: STOREFRONT | C24: ='Building & Fit-out Breakdown'!F229 -> 0 | D24: =C24/$B$4 -> 0
A25: 088000 | B25: GLASS/GLAZING | C25: ='Building & Fit-out Breakdown'!F237 -> 0 | D25: =C25/$B$4 -> 0
A26: 092000 | B26: DRYWALL | C26: ='Building & Fit-out Breakdown'!F270 -> 119664 | D26: =C26/$B$4 -> 0.88018654
A27: 092300 | B27: TILE/BRICK TILE | C27: ='Building & Fit-out Breakdown'!F279 -> 0 | D27: =C27/$B$4 -> 0
A28: 096000 | B28: CARPET/RESILIENT FLOORING | C28: ='Building & Fit-out Breakdown'!F294 -> 765048 | D28: =C28/$B$4 -> 5.6272977
A29: 096050 | B29: FLOOR PREPARATION | C29: ='Building & Fit-out Breakdown'!F302 -> 515298 | D29: =C29/$B$4 -> 3.7902658
A30: 096400 | B30: WOOD FLOORING | C30: ='Building & Fit-out Breakdown'!F308 -> 373050 | D30: =C30/$B$4 -> 2.743963
A31: 099000 | B31: PAINTING/PLASTER | C31: ='Building & Fit-out Breakdown'!F316 -> 1091765 | D31: =C31/$B$4 -> 8.0304591
A32: 100000 | B32: SPECIALITIES | C32: ='Building & Fit-out Breakdown'!F328 -> 1548500 | D32: =C32/$B$4 -> 11.389966
A33: 100500 | B33: ACOUSTICAL PANELS/K13 | C33: ='Building & Fit-out Breakdown'!F334 -> 581802 | D33: =C33/$B$4 -> 4.2794348
A34: 101400 | B34: SIGNAGE | C34: ='Building & Fit-out Breakdown'!F341 -> 50000 | D34: =C34/$B$4 -> 0.36777416
A35: 120000 | B35: FF&E INSTALL | C35: ='Building & Fit-out Breakdown'!F346 -> 50000 | D35: =C35/$B$4 -> 0.36777416
A36: 114000 | B36: FOOD SERVICE AND BAR EQUIPMENT | C36: ='Building & Fit-out Breakdown'!F354 -> 50000 | D36: =C36/$B$4 -> 0.36777416
A37: 142000 | B37: ELEVATOR | C37: ='Building & Fit-out Breakdown'!F361 -> 480000 | D37: =C37/$B$4 -> 3.5306319
A38: 210000 | B38: FIRE PROTECTION | C38: ='Building & Fit-out Breakdown'!F371 -> 1334070 | D38: =C38/$B$4 -> 9.8127294
A39: 220000 | B39: PLUMBING | C39: ='Building & Fit-out Breakdown'!F412 -> 3717250 | D39: =C39/$B$4 -> 27.34217
A40: 230000 | B40: HVAC | C40: ='Building & Fit-out Breakdown'!F417 -> 5964390 | D40: =C40/$B$4 -> 43.87097
A41: 260000 | B41: ELECTRIC | C41: ='Building & Fit-out Breakdown'!F456 -> 5512336.8 | D41: =C41/$B$4 -> 40.5459
A42: 270000 | B42: LOW VOLTAGE CABLING | C42: ='Building & Fit-out Breakdown'!F464 -> 227500 | D42: =C42/$B$4 -> 1.6733724
A43: 265000 | B43: LIGHTING | C43: ='Building & Fit-out Breakdown'!F474 -> 40000 | D43: =C43/$B$4 -> 0.29421933
A44: 283100 | B44: FIRE ALARM | C44: ='Building & Fit-out Breakdown'!F480 -> 521906 | D44: =C44/$B$4 -> 3.8388708
A45: 320000 | B45: SITEWORK | C45: ='Building & Fit-out Breakdown'!F488 -> 346335 | D45: =C45/$B$4 -> 2.5474613
A46: 001000 | B46: PRECONSTRUCTION | C46: 60000 | D46: =C46/$B$4 -> 0.44132899
A47: 010000 | B47: GENERAL CONDITIONS | C47: 0 | D47: =C47/$B$4 -> 0 | E47: Carried in budget summary
A48: 010001 | B48: BONDS | C48: 0 | D48: =C48/$B$4 -> 0 | E48: NIC
B49: SUB TOTAL | C49: =SUM(C11:C47) -> 37945960 | D49: =C49/$B$4 -> 279.11087
A50: 500005 | B50: G.L. INSURANCE | C50: 0 | D50: =C50/$B$4 -> 0
A51: 500006 | B51: BUILDERS RISK INSURANCE | C51: 0 | D51: =C51/$B$4 -> 0
B52: C.M. OVERHEAD & FEE | C52: 0 | D52: =C52/$B$4 -> 0
B53: SUB TOTAL | C53: =SUM(C49:C52) -> 37945960
A54: 500010 | B54: STATE/PROJECT TAX (IF APPLICABLE) | C54: 0 | D54: =C54/$B$4 -> 0
A55: 700002 | B55: DESIGN CONTINGENCY | C55: 0 | D55: =C55/$B$4 -> 0
A56: 700003 | B56: CONSTRUCTION CONTINGENCY | C56: 0 | D56: =C56/$B$4 -> 0
A57: 700004 | B57: EXPEDITING/OVERTIME CONTINGENCY | C57: 0 | D57: =C57/$B$4 -> 0
B58: TOTAL | C58: =SUM(C53:C57) -> 37945960

Sheet Building & Fit-out Breakdown
A1: Venue
A2: Scope: | B2: ='Building & Fit-outBudget Detail'!B2 -> Warehouse Conversion / Add Second Level & Roof Decks
A3: Capacity: | B3: 7440
A4: SF: | B4: =3500+69722+53379+9352 -> 135953
A5: Date: | B5: ='Building & Fit-outBudget Detail'!B5 -> 46281
A6: Architect: | B6: Wake
A7: Version: | B7: ='Building & Fit-outBudget Detail'!B6 -> 1
A10: ITEM | B10: DESCRIPTION | C10: QTY | D10: UNIT | E10: UNIT PRICE | F10: TOTAL | G10: NOTES
A12: 013000 | B12: PROJECT REQUIREMENTS
A13: 1 | B13: BIM Set Up & Coordination | C13: 1 | D13: LS | E13: 30000 | F13: =C13*E13 -> 30000
A14: =A13+1 -> 2 | B14: Plans / Reprographics | C14: 1 | D14: LS | E14: 7500 | F14: =C14*E14 -> 7500
A15: =A14+1 -> 3 | B15: Site Office & Equipment | C15: 1 | D15: LS | E15: 12000 | F15: =C15*E15 -> 12000
A16: =A15+1 -> 4 | B16: Field Techonology | C16: 1 | D16: LS | E16: 200000 | F16: =C16*E16 -> 200000
A17: =A16+1 -> 5 | B17: Construction Signage | C17: 1 | D17: LS | E17: 4500 | F17: =C17*E17 -> 4500
A18: =A17+1 -> 6 | B18: Site Security | C18: 1 | D18: LS | E18: 13000 | F18: =C18*E18 -> 13000
A19: =A18+1 -> 7 | B19: Site Safety Plan / First Aid / TPP / FE's / Safety Inspector | C19: 1 | D19: LS | E19: 400000 | F19: =C19*E19 -> 400000
A20: =A19+1 -> 8 | B20: Portable Toilets | C20: 80 | D20: WK | E20: 400 | F20: =C20*E20 -> 32000
A21: =A20+1 -> 9 | B21: Clean up Materials | C21: 1 | D21: LS | E21: 65000 | F21: =C21*E21 -> 65000
A22: =A21+1 -> 10 | B22: Protection Materials | C22: 1 | D22: LS | E22: 50000 | F22: =C22*E22 -> 50000
A23: =A22+1 -> 11 | B23: Project Labor | C23: 1 | D23: LS | E23: 2000000 | F23: =C23*E23 -> 2000000
A24: =A23+1 -> 12 | B24: Project Rubbish Removals | C24: 1 | D24: LS | E24: 120000 | F24: =C24*E24 -> 120000
A25: =A24+1 -> 13 | B25: Final Clean | C25: 1 | D25: LS | E25: 100000 | F25: =C25*E25 -> 100000
A27: Sub Total | B27: =B12 -> PROJECT REQUIREMENTS | F27: =SUM(F11:F26) -> 3034000
A29: 015800 | B29: SCAFFOLDING & HOARDING
A30: 1 | B30: Install sidewalk bridge and scaffolding around building | C30: 1 | D30: LS | E30: 4000000 | F30: =E30*C30 -> 4000000 | I30: 500/LF bridge
C31: 1126 | D31: LF | E31: 500
C32: =(1126*6)*4 -> 27024 | D32: SF | E32: 75
A33: 2 | B33: Interior scaffolding | C33: 1 | D33: LS | E33: 2000000 | F33: =E33*C33 -> 2000000 | I33: $75/SF for scaffolding
A34: 3 | B34: Barricades | C34: 1 | D34: LS | E34: 150000 | F34: =E34*C34 -> 150000
B35: Site safety During Erection | C35: 1 | D35: LS | E35: 20000 | F35: =E35*C35 -> 20000
A36: 4
A37: Sub Total | B37: =B29 -> SCAFFOLDING & HOARDING | F37: =SUM(F28:F36) -> 6170000
A39: 024100 | B39: DEMOLITION
A40: 1 | B40: Demo existing CMU/masonry walls at new Entry/Lobby area | C40: 2500 | D40: SF | E40: 12 | F40: =C40*E40 -> 30000
A41: =A40+1 -> 2 | B41: Demo 8" CMU interior wall 20' tall | C41: 1975 | D41: SF | E41: 12 | F41: =C41*E41 -> 23700
A42: =A41+1 -> 3 | B42: Demo 8" CMU interior wall 12' tall | C42: =628*12 -> 7536 | D42: SF | E42: 12 | F42: =C42*E42 -> 90432
A43: =A42+1 -> 4 | B43: Demo office area partitions, ceilings, doors, flooring MEP's, (CMU walls line above) | C43: 6825 | D43: SF | E43: 5 | F43: =C43*E43 -> 34125
A44: =A43+1 -> 5 | B44: Demo existing exterior roll up doors | C44: 8 | D44: EA | E44: 5000 | F44: =C44*E44 -> 40000
A45: =A44+1 -> 6 | B45: Demo existing exterior doors | C45: 7 | D45: EA | E45: 250 | F45: =C45*E45 -> 1750
A46: =A45+1 -> 7 | B46: Demo existing windows 1'x10' | C46: 34 | D46: EA | E46: 300 | F46: =C46*E46 -> 10200
A47: =A46+1 -> 8 | B47: Demo ceiling mount steam heaters and associated piping | C47: 28 | D47: EA | E47: 750 | F47: =C47*E47 -> 21000
A48: =A47+1 -> 9 | B48: Demo 5,250MBH boiler and piping (15'x6'x7' 13,000lbs) | C48: 2 | D48: EA | E48: 20000 | F48: =C48*E48 -> 40000
A49: =A48+1 -> 10 | B49: Demo misc. piping, lighting, electrical panels / switchgear / appurtenances throughout space | C49: 1 | D49: SF | E49: 74000 | F49: =C49*E49 -> 74000
A50: =A49+1 -> 11 | B50: Demo dock levelers | C50: 3 | D50: EA | E50: 2500 | F50: =C50*E50 -> 7500
A51: =A50+1 -> 12 | B51: Demo slab at load-in ramp plan west | C51: 1423 | D51: SF | E51: 10 | F51: =C51*E51 -> 14230
A52: =A51+1 -> 13 | B52: Trench slab for new grade beams at new façade | C52: 132 | D52: LF | E52: 100 | F52: =C52*E52 -> 13200 | H52: $2,500/cy
A53: =A52+1 -> 14 | B53: Demo / excavate 6" slab 4' tall at load-in area | C53: =890+1750 -> 2640 | D53: SF | E53: 12 | F53: =C53*E53 -> 31680 | H53: $2,500/cy
A54: =A53+1 -> 15 | B54: Trench slab for below grade sanitary line for bars and bathrooms | C54: 800 | D54: LF | E54: 80 | F54: =C54*E54 -> 64000 | H54: Trenching $150/LF Pour back $50K/LF
A55: =A54+1 -> 16 | B55: Demo / excavate elevator pits | C55: 2 | D55: EA | E55: 25000 | F55: =C55*E55 -> 50000 | H55: New Elvator 4' pit $50K excavate and concrete
A56: =A55+1 -> 17 | B56: Shoring Demo of Steel | C56: 1 | D56: LS | E56: 50000 | F56: =C56*E56 -> 50000
A57: =A56+1 -> 18 | B57: Demo Steel Columns / Roof Steel | C57: 1 | D57: EA | E57: 100000 | F57: =C57*E57 -> 100000
A58: =A57+1 -> 19 | B58: Demo Pre-cast concrete roof | C58: 74000 | D58: SF | E58: 8 | F58: =C58*E58 -> 592000 | G58: Abatement by others
A59: =A58+1 -> 20 | B59: Allow for Floor trenching for MEPS | C59: 0 | D59: LS | E59: 50000 | F59: =C59*E59 -> 0
A60: =A59+1 -> 21 | B60: Demo floor for Recessed floor - Include Excavation | C60: 0 | D60: SF | E60: 0 | F60: =C60*E60 -> 0 | G60: Included Above
A61: =A60+1 -> 22 | B61: Misc Façade Demo Along Johnson Ave (Doors, Roll-ups, Windows, etc.) | C61: 0 | D61: LS | E61: 20000 | F61: =C61*E61 -> 0
A63: Sub Total | B63: =B39 -> DEMOLITION | F63: =SUM(F38:F62) -> 1287817 | G63: $10/SF
A65: 033000 | B65: CONCRETE
A66: 1 | B66: Excavation related to New Columns at Music hall | C66: 0 | D66: SF | E66: 6.5 | F66: =E66*C66 -> 0 | G66: Based on Footprint of New Roof
A67: 2 | B67: CMU wall footing excavation allow 2' deep for new Load bearing wall at Music hall- East wall | C67: 0 | D67: LF | E67: 150 | F67: =E67*C67 -> 0
A68: 3 | B68: Concrete at New footings | C68: 0 | D68: EA | E68: 7500 | F68: =E68*C68 -> 0
B69: Excavate & Install New Footings at Stage | F69: =E69*C69 -> 0
F70: =E70*C70 -> 0 | H70: 4
B71: 1st Floor Raised Slab - Concrete on Styrofoam 24" | C71: 1500 | D71: CY | E71: 70 | F71: =E71*C71 -> 105000 | G71: 20,314 SF (Includes two ramps down to GA)
B72: Concrete ramp stage | F72: =E72*C72 -> 0
B73: Concrete 4'6" H on Styrofoam | C73: 0 | D73: SF | E73: 50 | F73: =E73*C73 -> 0
B74: Concrete at Stage Platform 4'6" H on Styrofoam | C74: 0 | D74: SF | E74: 50 | F74: =E74*C74 -> 0
F75: =E75*C75 -> 0
F76: =E76*C76 -> 0
B77: F/I new foundation wall / perimeter grade beam | C77: 132 | D77: LF | E77: 300 | F77: =E77*C77 -> 39600 | H77: $750/CY
B78: F/I new retaining wall at load-in area excavate slab 4' tall | C78: 219 | D78: LF | E78: 150 | F78: =E78*C78 -> 32850 | G78: 877 SF | H78: $100/CY
A79: 4 | B79: Concrete at CMU footing | C79: 0 | D79: LF | E79: 100 | F79: =E79*C79 -> 0
A80: 5 | B80: Patch slab due to New footing | C80: 0 | D80: SF | E80: 30 | F80: =E80*C80 -> 0
A81: 6 | B81: Patch conc. At Trenching for MEPS | C81: 0 | D81: SF | E81: 30 | F81: =E81*C81 -> 0
A82: =A81+1 -> 7 | B82: New slab Pour-back at Excavated Areas | C82: 0 | D82: SF | E82: 30 | F82: =E82*C82 -> 0
A83: =A82+1 -> 8 | B83: New slab at Recessed floor | C83: 0 | D83: SF | E83: 0 | F83: =E83*C83 -> 0 | G83: Included Above
A84: =A83+1 -> 9 | B84: Concrete on Deck for Mezz of Music Hall with Platforms | C84: 0 | D84: SF | E84: 25 | F84: =E84*C84 -> 0
A85: =A84+1 -> 10 | B85: Concrete In-fill on New Pan Stairs | C85: 0 | D85: EA | E85: 4000 | F85: =E85*C85 -> 0 | G85: (2) Feature Stairs, (2) BOH Stairs
A86: =A85+1 -> 11 | B86: Grouting at Steel Trusses & Column Base Plates | C86: 0 | D86: LS | E86: 15000 | F86: =E86*C86 -> 0
A87: =A86+1 -> 12 | B87: Polished concrete | C87: 0 | D87: SF | E87: 8 | F87: =E87*C87 -> 0
A88: =A87+1 -> 13 | B88: Concrete pads | C88: 0 | D88: LS | E88: 10000 | F88: =E88*C88 -> 0
A89: =A88+1 -> 14 | B89: Patch sidewalk | C89: 0 | D89: LS | E89: 35000 | F89: =E89*C89 -> 0
A90: =A89+1 -> 15 | B90: Misc. Equipment Pads | C90: 0 | D90: LS | E90: 25000 | F90: =E90*C90 -> 0
A91: =A90+1 -> 16 | B91: Concrete at Stage Platform 4'6" H on Styrofoam | C91: 0 | D91: SF | E91: 50 | F91: =E91*C91 -> 0
A93: Sub Total | B93: =B65 -> CONCRETE | F93: =SUM(F64:F92) -> 177450
A95: 042000 | B95: MASONRY
B96: FIRST FLOOR
A97: 1 | B97: Patch & Repair Existing Masonry Wall | C97: 9972 | D97: SF | E97: 10 | F97: =C97*E97 -> 99720
B98: New Masonry Wall at Entry Lobby Area | C98: 2022 | D98: SF
B99: CMU and Brick façade at removed windows | C99: 34 | D99: SF
B100: CMU and Brick façade at removed doors
B101: CMU and Brick façade at removed rolling grilles
B102: Patch masonry at new exterior doors
B103: Patch Masonry at louver openings
B105: F&I CMU wall vestibule stair tower 1 1st FL | C105: 0 | D105: SF | E105: 35
B106: F&I CMU wall vestibule stair tower 2 1st Fl
B107: F&I CMU wall vestibule stair tower 1 2nd FL
B108: F&I CMU wall vestibule stair tower 2 2nd FL
B109: F&I CMU wall vestibule stair tower 1 3rd Fl
B110: F&I CMU wall vestibule stair tower 2 3rd Fl
B111: F&I CMU elevator tower entrance | C111: 3220 | D111: SF | E111: 35 | F111: =C111*E111 -> 112700
...

Sheet General Conditions
B3: Exec | C3: 10 | D3: 9200 | E3: =C3*D3 -> 92000
B4: PM | C4: 90 | D4: 6400 | E4: =C4*D4 -> 576000
B5: APM | C5: 90 | D5: 4600 | E5: =C5*D5 -> 414000
B6: Engineer | C6: 90 | D6: 3900 | E6: =C6*D6 -> 351000
B7: Accoutnant | C7: 10 | D7: 2800 | E7: =C7*D7 -> 28000
E8: =C8*D8 -> 0
B9: Super | C9: 90 | D9: 6000 | E9: =C9*D9 -> 540000
B10: Super | C10: 90 | D10: 6000 | E10: =C10*D10 -> 540000
B11: Super | C11: 90 | D11: 6000 | E11: =C11*D11 -> 540000
B12: General Super | C12: 10 | D12: 6000 | E12: =C12*D12 -> 60000
E13: =SUM(E3:E12) -> 3141000

Sheet Project At-a-Glance
B8: Cost Report Date: | C8: 44957 | F8: Venue Capacity: | G8: TBD
B9: Project Name: | F9: Landlord Work Start Date: | G9: TBD
B10: Location: | F10: LNE Work Start Date: | G10: TBD
B11: Address: | F11: Certificate of Occupancy: | G11: TBD
B12: Project Number: | F12: First Show Date: | G12: TBD
B13: Budget: | C13: =C25 -> #REF! | F13: Project Completion Date: | G13: TBD
B14: Venue EVP: | C14: TBD | F14: Project Manager: | G14: TBD
B17: Description | C17: Budget | D17: Committed Costs Total | E17: Costs to Date Total | F17: Remaining Estimate | G17: Estimated Final Cost | H17: Budget vs EFC Variance
D18: Total | E18: Total
B19: ='Project Detail'!D4 -> Building Costs | C19: ='Project Summary '!C9 -> 63651265 | D19: ='Project Summary '!D9 -> 0 | E19: ='Project Summary '!E9 -> 0 | F19: ='Project Summary '!F9 -> 63651265 | G19: ='Project Summary '!G9 -> 63651265 | H19: ='Project Summary '!H9 -> 0
B20: ='Project Detail'!D33 -> Soft Costs | C20: ='Project Summary '!C15 -> #REF! | D20: ='Project Summary '!D15 -> 0 | E20: ='Project Summary '!E15 -> 0 | F20: ='Project Summary '!F15 -> #REF! | G20: ='Project Summary '!G15 -> #REF! | H20: ='Project Summary '!H15 -> #REF!
B21: FF&E Costs | C21: ='Project Summary '!C27 -> #REF! | D21: ='Project Summary '!D27 -> 0 | E21: ='Project Summary '!E27 -> 0 | F21: ='Project Summary '!F27 -> #REF! | G21: ='Project Summary '!G27 -> #REF! | H21: ='Project Summary '!H27 -> #REF!
B23: ='Project Summary '!B29 -> Sub-Total | C23: =SUM(C19:C21) -> #REF! | D23: =SUM(D19:D21) -> 0 | E23: =SUM(E19:E21) -> 0 | F23: =SUM(F19:F21) -> #REF! | G23: =SUM(G19:G21) -> #REF! | H23: =SUM(H19:H21) -> #REF!
B24: Total Contingency | C24: ='Project Summary '!C30 -> 8098599.2 | F24: =Contingency!G9 -> 8098599.2 | G24: =Contingency!G9 -> 8098599.2 | H24: =C24-G24 -> 0
B25: TOTAL | C25: =SUM(C23:C24) -> #REF! | D25: =SUM(D23:D24) -> 0 | E25: =SUM(E23:E24) -> 0 | F25: =SUM(F23:F24) -> #REF! | G25: =SUM(G23:G24) -> #REF! | H25: =SUM(H23:H24) -> #REF!
B28: Risk Summary
B29: Risk Report Total | D29: ='Risk Report'!G15 -> 0
B30: Remaining Contingency | D30: ='Risk Report'!G19 -> 8098599.2
B31: Exposure | D31: ='Risk Report'!G23 -> 0
B32: Estimated Final Cost (Including Risk Items) | D32: =G25+D31 -> #REF!

Sheet Project Summary 
B2: Description | C2: Budget | D2: Committed Costs | E2: Costs to Date | F2: Remaining Estimate | G2: Estimated Final Cost | H2: Budget vs EFC Variance
D3: Total | E3: Total
B4: ='Project Detail'!D4 -> Building Costs
B5: ='Project Detail'!D5 -> Building & Fit-Out Costs | C5: ='Project Detail'!F10 -> 63651265 | D5: ='Project Detail'!G10 -> 0 | E5: ='Project Detail'!K10 -> 0 | F5: ='Project Detail'!L10 -> 63651265 | G5: ='Project Detail'!M10 -> 63651265 | H5: ='Project Detail'!N10 -> 0
B6: ='Project Detail'!D11 -> Secondary Contractors | C6: ='Project Detail'!F16 -> 0 | D6: ='Project Detail'!G16 -> 0 | E6: ='Project Detail'!K16 -> 0 | F6: ='Project Detail'!L16 -> 0 | G6: ='Project Detail'!M16 -> 0 | H6: ='Project Detail'!N16 -> 0
B7: ='Project Detail'!D17 -> Miscellaneous | C7: ='Project Detail'!F22 -> 0 | D7: ='Project Detail'!G22 -> 0 | E7: ='Project Detail'!K22 -> 0 | F7: ='Project Detail'!L22 -> 0 | G7: ='Project Detail'!M22 -> 0 | H7: ='Project Detail'!N22 -> 0
B8: ='Project Detail'!D23 -> 0 | C8: ='Project Detail'!F28 -> 0 | D8: ='Project Detail'!G28 -> 0 | E8: ='Project Detail'!K28 -> 0 | F8: ='Project Detail'!L28 -> 0 | G8: ='Project Detail'!M28 -> 0 | H8: ='Project Detail'!N28 -> 0
B9: Building Costs Total | C9: =SUM(C5:C8) -> 63651265 | D9: =SUM(D5:D8) -> 0 | E9: =SUM(E5:E8) -> 0 | F9: =SUM(F5:F8) -> 63651265 | G9: =SUM(G5:G8) -> 63651265 | H9: =SUM(H5:H8) -> 0
B11: ='Project Detail'!D33 -> Soft Costs
B12: ='Project Detail'!D34 -> Project Management | C12: ='Project Detail'!F39 -> #REF! | D12: ='Project Detail'!G39 -> 0 | E12: ='Project Detail'!K39 -> 0 | F12: ='Project Detail'!L39 -> #REF! | G12: ='Project Detail'!M39 -> #REF! | H12: ='Project Detail'!N39 -> #REF!
B13: ='Project Detail'!D40 -> Architectural Fees | C13: ='Project Detail'!F45 -> 3526000 | D13: ='Project Detail'!G45 -> 0 | E13: ='Project Detail'!K45 -> 0 | F13: ='Project Detail'!L45 -> 0 | G13: ='Project Detail'!M45 -> 0 | H13: ='Project Detail'!N45 -> 3526000
B14: ='Project Detail'!D46 -> Design, Engineering & Misc. | C14: ='Project Detail'!F57 -> #REF! | D14: ='Project Detail'!G57 -> 0 | E14: ='Project Detail'!K57 -> 0 | F14: ='Project Detail'!L57 -> 0 | G14: ='Project Detail'!M57 -> 0 | H14: ='Project Detail'!N57 -> #REF!
B15: Soft Costs Total | C15: =SUM(C12:C14) -> #REF! | D15: =SUM(D12:D14) -> 0 | E15: =SUM(E12:E14) -> 0 | F15: =SUM(F12:F14) -> #REF! | G15: =SUM(G12:G14) -> #REF! | H15: =SUM(H12:H14) -> #REF!
B17: ='Project Detail'!D62 -> FF&E Costs
B18: ='Project Detail'!D63 -> Seating | C18: ='Project Detail'!F82 -> #REF! | D18: ='Project Detail'!G82 -> 0 | E18: ='Project Detail'!K82 -> 0 | F18: ='Project Detail'!L82 -> #REF! | G18: ='Project Detail'!M82 -> #REF! | H18: ='Project Detail'!N82 -> #REF!
B19: ='Project Detail'!D83 -> Concessions | C19: ='Project Detail'!F88 -> #REF! | D19: ='Project Detail'!G88 -> 0 | E19: ='Project Detail'!K88 -> 0 | F19: ='Project Detail'!L88 -> 0 | G19: ='Project Detail'!M88 -> 0 | H19: ='Project Detail'!N88 -> #REF!
B20: ='Project Detail'!D89 -> Phone & Data Systems | C20: ='Project Detail'!F92 -> 420000 | D20: ='Project Detail'!G92 -> 0 | E20: ='Project Detail'!K92 -> 0 | F20: ='Project Detail'!L92 -> 420000 | G20: ='Project Detail'!M92 -> 420000 | H20: ='Project Detail'!N92 -> 0
B21: ='Project Detail'!D93 -> Office Furniture | C21: ='Project Detail'!F99 -> 65000 | D21: ='Project Detail'!G99 -> 0 | E21: ='Project Detail'!K99 -> 0 | F21: ='Project Detail'!L99 -> 0 | G21: ='Project Detail'!M99 -> 0 | H21: ='Project Detail'!N99 -> 65000
B22: ='Project Detail'!D100 -> Signage/Graphics | C22: ='Project Detail'!F118 -> 0 | D22: ='Project Detail'!G118 -> 0 | E22: ='Project Detail'!K118 -> 0 | F22: ='Project Detail'!L118 -> 0 | G22: ='Project Detail'!M118 -> 0 | H22: ='Project Detail'!N118 -> 0
B23: ='Project Detail'!D119 -> Administration | C23: ='Project Detail'!F130 -> 93000 | D23: ='Project Detail'!G130 -> 0 | E23: ='Project Detail'!K130 -> 0 | F23: ='Project Detail'!L130 -> 0 | G23: ='Project Detail'!M130 -> 0 | H23: ='Project Detail'!N130 -> 93000
B24: ='Project Detail'!D131 -> Facility | C24: ='Project Detail'!F138 -> 0 | D24: ='Project Detail'!G138 -> 0 | E24: ='Project Detail'!K138 -> 0 | F24: ='Project Detail'!L138 -> 0 | G24: ='Project Detail'!M138 -> 0 | H24: ='Project Detail'!N138 -> 0
B25: ='Project Detail'!D139 -> Operations | C25: ='Project Detail'!F150 -> 0 | D25: ='Project Detail'!G150 -> 0 | E25: ='Project Detail'!K150 -> 0 | F25: ='Project Detail'!L150 -> 0 | G25: ='Project Detail'!M150 -> 0 | H25: ='Project Detail'!N150 -> 0
B26: ='Project Detail'!D151 -> Production | C26: ='Project Detail'!F166 -> 4128500 | D26: ='Project Detail'!G166 -> 0 | E26: ='Project Detail'!K166 -> 0 | F26: ='Project Detail'!L166 -> 0 | G26: ='Project Detail'!M166 -> 0 | H26: ='Project Detail'!N166 -> 4128500
B27: FF&E Costs Total | C27: =SUM(C18:C26) -> #REF! | D27: =SUM(D18:D26) -> 0 | E27: =SUM(E18:E26) -> 0 | F27: =SUM(F18:F26) -> #REF! | G27: =SUM(G18:G26) -> #REF! | H27: =SUM(H18:H26) -> #REF!
B29: Sub-Total | C29: =+C9+C15+C27 -> #REF! | D29: =+D9+D15+D27 -> 0 | E29: =+E9+E15+E27 -> 0 | F29: =+F9+F15+F27 -> #REF! | G29: =+G9+G15+G27 -> #REF! | H29: =+H9+H15+H27 -> #REF!
B30: Contingency | C30: ='Project Detail'!F170 -> 8098599.2 | F30: =Contingency!G9 -> 8098599.2 | G30: =Contingency!G9 -> 8098599.2 | H30: =C30-G30 -> 0
B31: GRAND TOTAL | C31: =SUM(C29:C30) -> #REF! | D31: =SUM(D29:D30) -> 0 | E31: =SUM(E29:E30) -> 0 | F31: =SUM(F29:F30) -> #REF! | G31: =SUM(G29:G30) -> #REF! | H31: =SUM(H29:H30) -> #REF!

Sheet Project Detail
B2: Code | C2: Cost Code | D2: Vendor | E2: Description | F2: Budget | G2: Committed Costs | H2: Change Orders | I2: Costs to Date (Gross) | J2: Retention | K2: Costs to Date | L2: Remaining Estimate | M2: Estimated Final Cost | N2: Budget vs EFC Variance | O2: Notes | Q2: Remaining to Invoice | S2: P11-21 (Fcst) | T2: P12-21 (Fcst) | U2: Q4-21 TOTAL (Fcst) | W2: P01-22 (Fcst) | X2: P02-22 (Fcst) | Y2: P03-22 (Fcst) | Z2: Q1-22 TOTAL (Fcst) | AB2: Q4-21/Q1-22 TOTAL | AD2: Remaining to Allocate
B4: 100 | D4: Building Costs
B5: 101 | D5: Building & Fit-Out Costs
B6: 101-1 | D6: General Contractor | F6: ='Budget Summary'!D31 -> 63651265 | G6: =SUMIF('Committed Costs '!C:C,B6,'Committed Costs '!G:G) -> 0 | H6: =SUMIF('Change Orders'!F:F,'Project Detail'!B6,'Change Orders'!E:E) -> 0 | I6: =SUMIF(Invoices!B:B,B6,Invoices!G:G) -> 0 | J6: 0 | K6: =I6-J6 -> 0 | L6: =+M6-G6 -> 63651265 | M6: =IF((F6+H6)>G6,F6+H6,G6) -> 63651265 | N6: =F6-M6 -> 0
B7: 101-2 | F7: 0 | G7: =SUMIF('Committed Costs '!C:C,B7,'Committed Costs '!G:G) -> 0 | H7: =SUMIF('Change Orders'!F:F,'Project Detail'!B7,'Change Orders'!E:E) -> 0 | I7: =SUMIF(Invoices!B:B,B7,Invoices!G:G) -> 0 | J7: 0 | K7: =I7-J7 -> 0 | L7: =+M7-G7 -> 0 | M7: =IF((F7+H7)>G7,F7+H7,G7) -> 0 | N7: =F7-M7 -> 0
B8: 101-3 | F8: 0 | G8: =SUMIF('Committed Costs '!C:C,B8,'Committed Costs '!G:G) -> 0 | H8: =SUMIF('Change Orders'!F:F,'Project Detail'!B8,'Change Orders'!E:E) -> 0 | I8: =SUMIF(Invoices!B:B,B8,Invoices!G:G) -> 0 | J8: 0 | K8: =I8-J8 -> 0 | L8: =+M8-G8 -> 0 | M8: =IF((F8+H8)>G8,F8+H8,G8) -> 0 | N8: =F8-M8 -> 0
B9: 101-4 | F9: 0 | G9: =SUMIF('Committed Costs '!C:C,B9,'Committed Costs '!G:G) -> 0 | H9: =SUMIF('Change Orders'!F:F,'Project Detail'!B9,'Change Orders'!E:E) -> 0 | I9: =SUMIF(Invoices!B:B,B9,Invoices!G:G) -> 0 | J9: 0 | K9: =I9-J9 -> 0 | L9: =+M9-G9 -> 0 | M9: =IF((F9+H9)>G9,F9+H9,G9) -> 0 | N9: =F9-M9 -> 0 | Q9: =M9-K9 -> 0 | U9: =S9+T9 -> 0 | Z9: =W9+X9+Y9 -> 0 | AB9: =U9+Z9 -> 0 | AD9: =Q9-AB9 -> 0
C10: 101 | E10: Total Building & Fit-Out Costs | F10: =SUM(F6:F9) -> 63651265 | G10: =SUM(G6:G9) -> 0 | H10: =SUM(H6:H9) -> 0 | I10: =SUM(I6:I9) -> 0 | J10: =SUM(J6:J9) -> 0 | K10: =SUM(K6:K9) -> 0 | L10: =SUM(L6:L9) -> 63651265 | M10: =SUM(M6:M9) -> 63651265 | N10: =SUM(N6:N9) -> 0 | Q10: =Q9 -> 0 | S10: =S9 -> 0 | T10: =T9 -> 0 | U10: =U9 -> 0 | W10: =W9 -> 0 | X10: =X9 -> 0 | Y10: =Y9 -> 0 | Z10: =Z9 -> 0 | AB10: =AB9 -> 0 | AD10: =AD9 -> 0
B11: 102 | D11: Secondary Contractors
B12: 102-1 | F12: 0 | G12: =SUMIF('Committed Costs '!C:C,B12,'Committed Costs '!G:G) -> 0 | H12: =SUMIF('Change Orders'!F:F,'Project Detail'!B12,'Change Orders'!E:E) -> 0 | I12: =SUMIF(Invoices!B:B,B12,Invoices!G:G) -> 0 | J12: 0 | K12: =I12-J12 -> 0 | L12: =+M12-G12 -> 0 | M12: =IF((F12+H12)>G12,F12+H12,G12) -> 0 | N12: =F12-M12 -> 0
B13: 102-2 | F13: 0 | G13: =SUMIF('Committed Costs '!C:C,B13,'Committed Costs '!G:G) -> 0 | H13: =SUMIF('Change Orders'!F:F,'Project Detail'!B13,'Change Orders'!E:E) -> 0 | I13: =SUMIF(Invoices!B:B,B13,Invoices!G:G) -> 0 | J13: 0 | K13: =I13-J13 -> 0 | L13: =+M13-G13 -> 0 | M13: =IF((F13+H13)>G13,F13+H13,G13) -> 0 | N13: =F13-M13 -> 0
B14: 102-3 | F14: 0 | G14: =SUMIF('Committed Costs '!C:C,B14,'Committed Costs '!G:G) -> 0 | H14: =SUMIF('Change Orders'!F:F,'Project Detail'!B14,'Change Orders'!E:E) -> 0 | I14: =SUMIF(Invoices!B:B,B14,Invoices!G:G) -> 0 | J14: 0 | K14: =I14-J14 -> 0 | L14: =+M14-G14 -> 0 | M14: =IF((F14+H14)>G14,F14+H14,G14) -> 0 | N14: =F14-M14 -> 0
B15: 102-4 | F15: 0 | G15: =SUMIF('Committed Costs '!C:C,B15,'Committed Costs '!G:G) -> 0 | H15: =SUMIF('Change Orders'!F:F,'Project Detail'!B15,'Change Orders'!E:E) -> 0 | I15: =SUMIF(Invoices!B:B,B15,Invoices!G:G) -> 0 | J15: 0 | K15: =I15-J15 -> 0 | L15: =+M15-G15 -> 0 | M15: =IF((F15+H15)>G15,F15+H15,G15) -> 0 | N15: =F15-M15 -> 0 | Q15: =M15-K15 -> 0 | U15: =S15+T15 -> 0 | Z15: =W15+X15+Y15 -> 0 | AB15: =U15+Z15 -> 0 | AD15: =Q15-AB15 -> 0
C16: 102 | E16: Total Secondary Contractors | F16: =SUM(F12:F15) -> 0 | G16: =SUM(G12:G15) -> 0 | H16: =SUM(H12:H15) -> 0 | I16: =SUM(I12:I15) -> 0 | J16: =SUM(J12:J15) -> 0 | K16: =SUM(K12:K15) -> 0 | L16: =SUM(L12:L15) -> 0 | M16: =SUM(M12:M15) -> 0 | N16: =SUM(N12:N15) -> 0 | Q16: =Q15 -> 0 | S16: =S15 -> 0 | T16: =T15 -> 0 | U16: =U15 -> 0 | W16: =W15 -> 0 | X16: =X15 -> 0 | Y16: =Y15 -> 0 | Z16: =Z15 -> 0 | AB16: =AB15 -> 0 | AD16: =AD15 -> 0
B17: 103 | D17: Miscellaneous
B18: 103-1 | F18: 0 | G18: =SUMIF('Committed Costs '!C:C,B18,'Committed Costs '!G:G) -> 0 | H18: =SUMIF('Change Orders'!F:F,'Project Detail'!B18,'Change Orders'!E:E) -> 0 | I18: =SUMIF(Invoices!B:B,B18,Invoices!G:G) -> 0 | J18: 0 | K18: =I18-J18 -> 0 | L18: =+M18-G18 -> 0 | M18: =IF((F18+H18)>G18,F18+H18,G18) -> 0 | N18: =F18-M18 -> 0
B19: 103-2 | F19: 0 | G19: =SUMIF('Committed Costs '!C:C,B19,'Committed Costs '!G:G) -> 0 | H19: =SUMIF('Change Orders'!F:F,'Project Detail'!B19,'Change Orders'!E:E) -> 0 | I19: =SUMIF(Invoices!B:B,B19,Invoices!G:G) -> 0 | J19: 0 | K19: =I19-J19 -> 0 | L19: =+M19-G19 -> 0 | M19: =IF((F19+H19)>G19,F19+H19,G19) -> 0 | N19: =F19-M19 -> 0
B20: 103-3 | F20: 0 | G20: =SUMIF('Committed Costs '!C:C,B20,'Committed Costs '!G:G) -> 0 | H20: =SUMIF('Change Orders'!F:F,'Project Detail'!B20,'Change Orders'!E:E) -> 0 | I20: =SUMIF(Invoices!B:B,B20,Invoices!G:G) -> 0 | J20: 0 | K20: =I20-J20 -> 0 | L20: =+M20-G20 -> 0 | M20: =IF((F20+H20)>G20,F20+H20,G20) -> 0 | N20: =F20-M20 -> 0
B21: 103-4 | F21: 0 | G21: =SUMIF('Committed Costs '!C:C,B21,'Committed Costs '!G:G) -> 0 | H21: =SUMIF('Change Orders'!F:F,'Project Detail'!B21,'Change Orders'!E:E) -> 0 | I21: =SUMIF(Invoices!B:B,B21,Invoices!G:G) -> 0 | J21: 0 | K21: =I21-J21 -> 0 | L21: =+M21-G21 -> 0 | M21: =IF((F21+H21)>G21,F21+H21,G21) -> 0 | N21: =F21-M21 -> 0 | Q21: =M21-K21 -> 0 | U21: =S21+T21 -> 0 | Z21: =W21+X21+Y21 -> 0 | AB21: =U21+Z21 -> 0 | AD21: =Q21-AB21 -> 0
C22: 103 | E22: Total Mics. | F22: =SUM(F18:F21) -> 0 | G22: =SUM(G18:G21) -> 0 | H22: =SUM(H18:H21) -> 0 | I22: =SUM(I18:I21) -> 0 | J22: =SUM(J18:J21) -> 0 | K22: =SUM(K18:K21) -> 0 | L22: =SUM(L18:L21) -> 0 | M22: =SUM(M18:M21) -> 0 | N22: =SUM(N18:N21) -> 0 | Q22: =Q21 -> 0 | S22: =S21 -> 0 | T22: =T21 -> 0 | U22: =U21 -> 0 | W22: =W21 -> 0 | X22: =X21 -> 0 | Y22: =Y21 -> 0 | Z22: =Z21 -> 0 | AB22: =AB21 -> 0 | AD22: =AD21 -> 0
B23: 104
B24: 104-1 | F24: 0 | G24: =SUMIF('Committed Costs '!C:C,B24,'Committed Costs '!G:G) -> 0 | H24: =SUMIF('Change Orders'!F:F,'Project Detail'!B24,'Change Orders'!E:E) -> 0 | I24: =SUMIF(Invoices!B:B,B24,Invoices!G:G) -> 0 | J24: 0 | K24: =I24-J24 -> 0 | L24: =+M24-G24 -> 0 | M24: =K24 -> 0 | N24: =F24-M24 -> 0
B25: 104-2 | F25: 0 | G25: =SUMIF('Committed Costs '!C:C,B25,'Committed Costs '!G:G) -> 0 | H25: =SUMIF('Change Orders'!F:F,'Project Detail'!B25,'Change Orders'!E:E) -> 0 | I25: =SUMIF(Invoices!B:B,B25,Invoices!G:G) -> 0 | J25: 0 | K25: =I25-J25 -> 0 | L25: =+M25-G25 -> 0 | M25: =IF((F25+H25)>G25,F25+H25,G25) -> 0 | N25: =F25-M25 -> 0
B26: 104-3 | F26: 0 | G26: =SUMIF('Committed Costs '!C:C,B26,'Committed Costs '!G:G) -> 0 | H26: =SUMIF('Change Orders'!F:F,'Project Detail'!B26,'Change Orders'!E:E) -> 0 | I26: =SUMIF(Invoices!B:B,B26,Invoices!G:G) -> 0 | J26: 0 | K26: =I26-J26 -> 0 | L26: =+M26-G26 -> 0 | M26: =IF((F26+H26)>G26,F26+H26,G26) -> 0 | N26: =F26-M26 -> 0
B27: 104-4 | F27: 0 | G27: =SUMIF('Committed Costs '!C:C,B27,'Committed Costs '!G:G) -> 0 | H27: =SUMIF('Change Orders'!F:F,'Project Detail'!B27,'Change Orders'!E:E) -> 0 | I27: =SUMIF(Invoices!B:B,B27,Invoices!G:G) -> 0 | J27: 0 | K27: =I27-J27 -> 0 | L27: =+M27-G27 -> 0 | M27: =IF((F27+H27)>G27,F27+H27,G27) -> 0 | N27: =F27-M27 -> 0 | Q27: =M27-K27 -> 0 | U27: =S27+T27 -> 0 | Z27: =W27+X27+Y27 -> 0 | AB27: =U27+Z27 -> 0 | AD27: =Q27-AB27 -> 0
C28: 104 | E28: Total | F28: =SUM(F24:F27) -> 0 | G28: =SUM(G24:G27) -> 0 | H28: =SUM(H24:H27) -> 0 | I28: =SUM(I24:I27) -> 0 | J28: =SUM(J24:J27) -> 0 | K28: =SUM(K24:K27) -> 0 | L28: =SUM(L24:L27) -> 0 | M28: =SUM(M24:M27) -> 0 | N28: =SUM(N24:N27) -> 0 | Q28: =Q27 -> 0 | S28: =S27 -> 0 | T28: =T27 -> 0 | U28: =U27 -> 0 | W28: =W27 -> 0 | X28: =X27 -> 0 | Y28: =Y27 -> 0 | Z28: =Z27 -> 0 | AB28: =AB27 -> 0 | AD28: =AD27 -> 0
E30: TOTAL BUILDING COSTS | F30: =SUM(F10,F16,F22,F28) -> 63651265 | G30: =SUM(G10,G16,G22,G28) -> 0 | H30: =SUM(H10,H16,H22,H28) -> 0 | I30: =SUM(I10,I16,I22,I28) -> 0 | J30: =SUM(J10,J16,J22,J28) -> 0 | K30: =SUM(K10,K16,K22,K28) -> 0 | L30: =SUM(L10,L16,L22,L28) -> 63651265 | M30: =SUM(M10,M16,M22,M28) -> 63651265 | N30: =SUM(N10,N16,N22,N28) -> 0 | Q30: =SUM(Q10,Q16,Q22,Q28) -> 0 | S30: =SUM(S10,S16,S22,S28) -> 0 | T30: =SUM(T10,T16,T22,T28) -> 0 | U30: =SUM(U10,U16,U22,U28) -> 0 | W30: =SUM(W10,W16,W22,W28) -> 0 | X30: =SUM(X10,X16,X22,X28) -> 0 | Y30: =SUM(Y10,Y16,Y22,Y28) -> 0 | Z30: =SUM(Z10,Z16,Z22,Z28) -> 0 | AB30: =SUM(AB10,AB16,AB22,AB28) -> 0 | AD30: =SUM(AD10,AD16,AD22,AD28) -> 0
B33: 200 | D33: Soft Costs
B34: 201 | D34: Project Management
B35: 201-1 | D35: LNE | E35: Project Management | F35: ='Budget Summary'!D45 -> 520000 | G35: =SUMIF('Committed Costs '!C:C,B35,'Committed Costs '!G:G) -> 0 | H35: =SUMIF('Change Orders'!F:F,'Project Detail'!B35,'Change Orders'!E:E) -> 0 | I35: =SUMIF(Invoices!B:B,B35,Invoices!G:G) -> 0 | J35: 0 | K35: =I35-J35 -> 0 | L35: =+M35-G35 -> 0 | M35: =G35 -> 0 | N35: =F35-M35 -> 520000 | Q35: =M35-K35 -> 0 | U35: =S35+T35 -> 0 | Z35: =W35+X35+Y35 -> 0 | AB35: =U35+Z35 -> 0 | AD35: =Q35-AB35 -> 0
B36: 201-2 | D36: TBD | E36: Project Management (3rd Party) | F36: ='Budget Summary'!#REF! -> #REF! | G36: =SUMIF('Committed Costs '!C:C,B36,'Committed Costs '!G:G) -> 0 | H36: =SUMIF('Change Orders'!F:F,'Project Detail'!B36,'Change Orders'!E:E) -> 0 | I36: =SUMIF(Invoices!B:B,B36,Invoices!G:G) -> 0 | J36: 0 | K36: =I36-J36 -> 0 | L36: =+M36-G36 -> #REF! | M36: =IF((F36+H36)>G36,F36+H36,G36) -> #REF! | N36: =F36-M36 -> #REF!
B37: 201-3 | F37: 0 | G37: =SUMIF('Committed Costs '!C:C,B37,'Committed Costs '!G:G) -> 0 | H37: =SUMIF('Change Orders'!F:F,'Project Detail'!B37,'Change Orders'!E:E) -> 0 | I37: =SUMIF(Invoices!B:B,B37,Invoices!G:G) -> 0 | J37: 0 | K37: =I37-J37 -> 0 | L37: =+M37-G37 -> 0 | M37: =IF((F37+H37)>G37,F37+H37,G37) -> 0 | N37: =F37-M37 -> 0
B38: 201-4 | F38: 0 | G38: =SUMIF('Committed Costs '!C:C,B38,'Committed Costs '!G:G) -> 0 | H38: =SUMIF('Change Orders'!F:F,'Project Detail'!B38,'Change Orders'!E:E) -> 0 | I38: =SUMIF(Invoices!B:B,B38,Invoices!G:G) -> 0 | J38: 0 | K38: =I38-J38 -> 0 | L38: =+M38-G38 -> 0 | M38: =IF((F38+H38)>G38,F38+H38,G38) -> 0 | N38: =F38-M38 -> 0
C39: 201 | E39: Total Project Management | F39: =SUM(F35:F38) -> #REF! | G39: =SUM(G35:G38) -> 0 | H39: =SUM(H35:H38) -> 0 | I39: =SUM(I35:I38) -> 0 | J39: =SUM(J35:J38) -> 0 | K39: =SUM(K35:K38) -> 0 | L39: =SUM(L35:L38) -> #REF! | M39: =SUM(M35:M38) -> #REF! | N39: =SUM(N35:N38) -> #REF! | Q39: =Q35 -> 0 | S39: =S35 -> 0 | T39: =T35 -> 0 | U39: =U35 -> 0 | W39: =W35 -> 0 | X39: =X35 -> 0 | Y39: =Y35 -> 0 | Z39: =Z35 -> 0 | AB39: =AB35 -> 0 | AD39: =AD35 -> 0
B40: 202 | D40: Architectural Fees
B41: 202-1 | D41: TBD | E41: Architectural Fees | F41: ='Budget Summary'!D35 -> 3526000 | G41: =SUMIF('Committed Costs '!C:C,B41,'Committed Costs '!G:G) -> 0 | H41: =SUMIF('Change Orders'!F:F,'Project Detail'!B41,'Change Orders'!E:E) -> 0 | I41: =SUMIF(Invoices!B:B,B41,Invoices!G:G) -> 0 | J41: 0 | K41: =I41-J41 -> 0 | L41: =+M41-G41 -> 0 | M41: =G41 -> 0 | N41: =F41-M41 -> 3526000 | Q41: =M41-K41 -> 0 | U41: =S41+T41 -> 0 | Z41: =W41+X41+Y41 -> 0 | AB41: =U41+Z41 -> 0 | AD41: =Q41-AB41 -> 0
B42: 202-2 | F42: 0 | G42: =SUMIF('Committed Costs '!C:C,B42,'Committed Costs '!G:G) -> 0 | H42: =SUMIF('Change Orders'!F:F,'Project Detail'!B42,'Change Orders'!E:E) -> 0 | I42: =SUMIF(Invoices!B:B,B42,Invoices!G:G) -> 0 | J42: 0 | K42: =I42-J42 -> 0 | L42: =+M42-G42 -> 0 | M42: =IF((F42+H42)>G42,F42+H42,G42) -> 0 | N42: =F42-M42 -> 0 | Q42: =M42-K42 -> 0 | U42: =S42+T42 -> 0 | Z42: =W42+X42+Y42 -> 0 | AB42: =U42+Z42 -> 0 | AD42: =Q42-AB42 -> 0
B43: 202-3 | F43: 0 | G43: =SUMIF('Committed Costs '!C:C,B43,'Committed Costs '!G:G) -> 0 | H43: =SUMIF('Change Orders'!F:F,'Project Detail'!B43,'Change Orders'!E:E) -> 0 | I43: =SUMIF(Invoices!B:B,B43,Invoices!G:G) -> 0 | J43: 0 | K43: =I43-J43 -> 0 | L43: =+M43-G43 -> 0 | M43: 0 | N43: =F43-M43 -> 0 | Q43: =M43-K43 -> 0 | U43: =S43+T43 -> 0 | Z43: =W43+X43+Y43 -> 0 | AB43: =U43+Z43 -> 0 | AD43: =Q43-AB43 -> 0
B44: 202-4 | F44: 0 | G44: =SUMIF('Committed Costs '!C:C,B44,'Committed Costs '!G:G) -> 0 | H44: =SUMIF('Change Orders'!F:F,'Project Detail'!B44,'Change Orders'!E:E) -> 0 | I44: =SUMIF(Invoices!B:B,B44,Invoices!G:G) -> 0 | J44: 0 | K44: =I44-J44 -> 0 | L44: =+M44-G44 -> 0 | M44: =IF((F44+H44)>G44,F44+H44,G44) -> 0 | N44: =F44-M44 -> 0
C45: 202 | E45: Total Architectural Fees | F45: =SUM(F41:F44) -> 3526000 | G45: =SUM(G41:G44) -> 0 | H45: =SUM(H41:H44) -> 0 | I45: =SUM(I41:I44) -> 0 | J45: =SUM(J41:J44) -> 0 | K45: =SUM(K41:K44) -> 0 | L45: =SUM(L41:L44) -> 0 | M45: =SUM(M41:M44) -> 0 | N45: =SUM(N41:N44) -> 3526000 | Q45: =SUM(Q41:Q43) -> 0 | S45: =SUM(S41:S43) -> 0 | T45: =SUM(T41:T43) -> 0 | U45: =SUM(U41:U43) -> 0 | W45: =SUM(W41:W43) -> 0 | X45: =SUM(X41:X43) -> 0 | Y45: =SUM(Y41:Y43) -> 0 | Z45: =SUM(Z41:Z43) -> 0 | AB45: =SUM(AB41:AB43) -> 0 | AD45: =SUM(AD41:AD43) -> 0
B46: 203 | D46: Design, Engineering & Misc.
B47: 203-1 | D47: K2 | E47: AV/LV Design | F47: ='Budget Summary'!#REF! -> #REF! | G47: =SUMIF('Committed Costs '!C:C,B47,'Committed Costs '!G:G) -> 0 | H47: =SUMIF('Change Orders'!F:F,'Project Detail'!B47,'Change Orders'!E:E) -> 0 | I47: =SUMIF(Invoices!B:B,B47,Invoices!G:G) -> 0 | J47: 0 | K47: =I47-J47 -> 0 | L47: =+M47-G47 -> 0 | M47: =G47 -> 0 | N47: =F47-M47 -> #REF! | Q47: =M47-K47 -> 0 | U47: =S47+T47 -> 0 | Z47: =W47+X47+Y47 -> 0 | AB47: =U47+Z47 -> 0 | AD47: =Q47-AB47 -> 0
B48: 203-2 | D48: Trimark | E48: Kitchen Design | F48: ='Budget Summary'!#REF! -> #REF! | G48: =SUMIF('Committed Costs '!C:C,B48,'Committed Costs '!G:G) -> 0 | H48: =SUMIF('Change Orders'!F:F,'Project Detail'!B48,'Change Orders'!E:E) -> 0 | I48: =SUMIF(Invoices!B:B,B48,Invoices!G:G) -> 0 | J48: 0 | K48: =I48-J48 -> 0 | L48: =+M48-G48 -> 0 | M48: =G48 -> 0 | N48: =F48-M48 -> #REF! | Q48: =M48-K48 -> 0 | U48: =S48+T48 -> 0 | Z48: =W48+X48+Y48 -> 0 | AB48: =U48+Z48 -> 0 | AD48: =Q48-AB48 -> 0
B49: 203-3 | D49: Bandit Lites | E49: Lighting Design | F49: ='Budget Summary'!#REF! -> #REF! | G49: =SUMIF('Committed Costs '!C:C,B49,'Committed Costs '!G:G) -> 0 | H49: =SUMIF('Change Orders'!F:F,'Project Detail'!B49,'Change Orders'!E:E) -> 0 | I49: =SUMIF(Invoices!B:B,B49,Invoices!G:G) -> 0 | J49: 0 | K49: =I49-J49 -> 0 | L49: =+M49-G49 -> 0 | M49: =G49 -> 0 | N49: =F49-M49 -> #REF! | Q49: =M49-K49 -> 0 | U49: =S49+T49 -> 0 | Z49: =W49+X49+Y49 -> 0 | AB49: =U49+Z49 -> 0 | AD49: =Q49-AB49 -> 0
B50: 203-4 | D50: TBD | E50: Branding | F50: ='Budget Summary'!D33 -> 1483680 | G50: =SUMIF('Committed Costs '!C:C,B50,'Committed Costs '!G:G) -> 0 | H50: =SUMIF('Change Orders'!F:F,'Project Detail'!B50,'Change Orders'!E:E) -> 0 | I50: =SUMIF(Invoices!B:B,B50,Invoices!G:G) -> 0 | J50: 0 | K50: =I50-J50 -> 0 | L50: =+M50-G50 -> 0 | M50: =G50 -> 0 | N50: =F50-M50 -> 1483680
B51: 203-5 | D51: TBD | E51: Civil Engineering | F51: ='Budget Summary'!D36 -> 10000 | G51: =SUMIF('Committed Costs '!C:C,B51,'Committed Costs '!G:G) -> 0 | H51: =SUMIF('Change Orders'!F:F,'Project Detail'!B51,'Change Orders'!E:E) -> 0 | I51: =SUMIF(Invoices!B:B,B51,Invoices!G:G) -> 0 | J51: 0 | K51: =I51-J51 -> 0 | L51: =+M51-G51 -> 0 | M51: =G51 -> 0 | N51: =F51-M51 -> 10000
B52: 203-6 | D52: K2 / Metro Acoustics | E52: Acoustic Design | F52: ='Budget Summary'!#REF! -> #REF! | G52: =SUMIF('Committed Costs '!C:C,B52,'Committed Costs '!G:G) -> 0 | H52: =SUMIF('Change Orders'!F:F,'Project Detail'!B52,'Change Orders'!E:E) -> 0 | I52: =SUMIF(Invoices!B:B,B52,Invoices!G:G) -> 0 | J52: 0 | K52: =I52-J52 -> 0 | L52: =+M52-G52 -> 0 | M52: =G52 -> 0 | N52: =F52-M52 -> #REF!
B53: 203-7 | D53: TBD | E53: Signage / Wayfinding Design | F53: ='Budget Summary'!#REF! -> #REF! | G53: =SUMIF('Committed Costs '!C:C,B53,'Committed Costs '!G:G) -> 0 | H53: =SUMIF('Change Orders'!F:F,'Project Detail'!B53,'Change Orders'!E:E) -> 0 | I53: =SUMIF(Invoices!B:B,B53,Invoices!G:G) -> 0 | J53: 0 | K53: =I53-J53 -> 0 | L53: =+M53-G53 -> 0 | M53: =G53 -> 0 | N53: =F53-M53 -> #REF!
B54: 203-8 | D54: TBD | E54: Zoning & Permit Fees | F54: ='Budget Summary'!D41 -> 628297.48 | G54: =SUMIF('Committed Costs '!C:C,B54,'Committed Costs '!G:G) -> 0 | H54: =SUMIF('Change Orders'!F:F,'Project Detail'!B54,'Change Orders'!E:E) -> 0 | I54: =SUMIF(Invoices!B:B,B54,Invoices!G:G) -> 0 | J54: 0 | K54: =I54-J54 -> 0 | L54: =+M54-G54 -> 0 | M54: =G54 -> 0 | N54: =F54-M54 -> 628297.48
B55: 203-9 | D55: TBD | E55: Testing / Quality Control | F55: ='Budget Summary'!D44 -> 50000 | G55: =SUMIF('Committed Costs '!C:C,B55,'Committed Costs '!G:G) -> 0 | H55: =SUMIF('Change Orders'!F:F,'Project Detail'!B55,'Change Orders'!E:E) -> 0 | I55: =SUMIF(Invoices!B:B,B55,Invoices!G:G) -> 0 | J55: 0 | K55: =I55-J55 -> 0 | L55: =+M55-G55 -> 0 | M55: =G55 -> 0 | N55: =F55-M55 -> 50000
B56: 203-10 | D56: TBD | E56: Reimbursable Expenses | F56: ='Budget Summary'!D46 -> 0 | G56: =SUMIF('Committed Costs '!C:C,B56,'Committed Costs '!G:G) -> 0 | H56: =SUMIF('Change Orders'!F:F,'Project Detail'!B56,'Change Orders'!E:E) -> 0 | I56: =SUMIF(Invoices!B:B,B56,Invoices!G:G) -> 0 | J56: 0 | K56: =I56-J56 -> 0 | L56: =+M56-G56 -> 0 | M56: =G56 -> 0 | N56: =F56-M56 -> 0 | Q56: =M56-K56 -> 0 | U56: =S56+T56 -> 0 | Z56: =W56+X56+Y56 -> 0 | AB56: =U56+Z56 -> 0 | AD56: =Q56-AB56 -> 0
C57: 203 | E57: Total Design, Engineering & Misc. | F57: =SUM(F47:F56) -> #REF! | G57: =SUM(G47:G56) -> 0 | H57: =SUM(H47:H56) -> 0 | I57: =SUM(I47:I56) -> 0 | J57: =SUM(J47:J56) -> 0 | K57: =SUM(K47:K56) -> 0 | L57: =SUM(L47:L56) -> 0 | M57: =SUM(M47:M56) -> 0 | N57: =SUM(N47:N56) -> #REF! | Q57: =SUM(Q47:Q56) -> 0 | S57: =SUM(S47:S56) -> 0 | T57: =SUM(T47:T56) -> 0 | U57: =SUM(U47:U56) -> 0 | W57: =SUM(W47:W56) -> 0 | X57: =SUM(X47:X56) -> 0 | Y57: =SUM(Y47:Y56) -> 0 | Z57: =SUM(Z47:Z56) -> 0 | AB57: =SUM(AB47:AB56) -> 0 | AD57: =SUM(AD47:AD56) -> 0
E59: TOTAL SOFT COSTS | F59: =SUM(F39,F45,F57) -> #REF! | G59: =SUM(G39,G45,G57) -> 0 | H59: =SUM(H39,H45,H57) -> 0 | I59: =SUM(I39,I45,I57) -> 0 | J59: =SUM(J39,J45,J57) -> 0 | K59: =SUM(K39,K45,K57) -> 0 | L59: =SUM(L39,L45,L57) -> #REF! | M59: =SUM(M39,M45,M57) -> #REF! | N59: =SUM(N39,N45,N57) -> #REF! | Q59: =SUM(Q39,Q45,Q57) -> 0 | S59: =SUM(S39,S45,S57) -> 0 | T59: =SUM(T39,T45,T57) -> 0 | U59: =SUM(U39,U45,U57) -> 0 | W59: =SUM(W39,W45,W57) -> 0 | X59: =SUM(X39,X45,X57) -> 0 | Y59: =SUM(Y39,Y45,Y57) -> 0 | Z59: =SUM(Z39,Z45,Z57) -> 0 | AB59: =SUM(AB39,AB45,AB57) -> 0 | AD59: =SUM(AD39,AD45,AD57) -> 0
B62: 300 | D62: FF&E Costs
B63: 301 | D63: Seating
B64: 301-1 | D64: TBD | E64: Fixed Seating | F64: ='Budget Summary'!D49 -> 1043750 | G64: =SUMIF('Committed Costs '!C:C,B64,'Committed Costs '!G:G) -> 0 | H64: =SUMIF('Change Orders'!F:F,'Project Detail'!B64,'Change Orders'!E:E) -> 0 | I64: =SUMIF(Invoices!B:B,B64,Invoices!G:G) -> 0 | J64: 0 | K64: =I64-J64 -> 0 | L64: =+M64-G64 -> 1043750 | M64: =IF((F64+H64)>G64,F64+H64,G64) -> 1043750 | N64: =F64-M64 -> 0 | Q64: =M64-K64 -> 1043750 | U64: =S64+T64 -> 0 | Z64: =W64+X64+Y64 -> 0 | AB64: =U64+Z64 -> 0 | AD64: =Q64-AB64 -> 1043750
B65: 301-2 | D65: N/A | E65: Chairs - Gasser Bar Stools | F65: =46800-46800 -> 0 | G65: =SUMIF('Committed Costs '!C:C,B65,'Committed Costs '!G:G) -> 0 | H65: =SUMIF('Change Orders'!F:F,'Project Detail'!B65,'Change Orders'!E:E) -> 0 | I65: =SUMIF(Invoices!B:B,B65,Invoices!G:G) -> 0 | J65: 0 | K65: =I65-J65 -> 0 | L65: =+M65-G65 -> 0 | M65: =IF((F65+H65)>G65,F65+H65,G65) -> 0 | N65: =F65-M65 -> 0 | Q65: =M65-K65 -> 0 | U65: =S65+T65+#REF! -> #REF! | Z65: =W65+X65+Y65 -> 0 | AB65: =U65+Z65 -> #REF! | AD65: =Q65-AB65 -> #REF!
B66: 301-3 | D66: N/A | E66: Chairs - Gasser | F66: =90000-90000 -> 0 | G66: =SUMIF('Committed Costs '!C:C,B66,'Committed Costs '!G:G) -> 0 | H66: =SUMIF('Change Orders'!F:F,'Project Detail'!B66,'Change Orders'!E:E) -> 0 | I66: =SUMIF(Invoices!B:B,B66,Invoices!G:G) -> 0 | J66: 0 | K66: =I66-J66 -> 0 | L66: =+M66-G66 -> 0 | M66: =IF((F66+H66)>G66,F66+H66,G66) -> 0 | N66: =F66-M66 -> 0 | Q66: =M66-K66 -> 0 | U66: =S66+T66+#REF! -> #REF! | Z66: =W66+X66+Y66 -> 0 | AB66: =U66+Z66 -> #REF! | AD66: =Q66-AB66 -> #REF!
B67: 301-4 | D67: N/A | E67: Ottoman - Boxes | F67: =18720-18720 -> 0 | G67: =SUMIF('Committed Costs '!C:C,B67,'Committed Costs '!G:G) -> 0 | H67: =SUMIF('Change Orders'!F:F,'Project Detail'!B67,'Change Orders'!E:E) -> 0 | I67: =SUMIF(Invoices!B:B,B67,Invoices!G:G) -> 0 | J67: 0 | K67: =I67-J67 -> 0 | L67: =+M67-G67 -> 0 | M67: =IF((F67+H67)>G67,F67+H67,G67) -> 0 | N67: =F67-M67 -> 0 | Q67: =M67-K67 -> 0 | U67: =S67+T67+#REF! -> #REF! | Z67: =W67+X67+Y67 -> 0 | AB67: =U67+Z67 -> #REF! | AD67: =Q67-AB67 -> #REF!
B68: 301-5 | D68: N/A | E68: Side Tables - Boxes | F68: =18000-18000 -> 0 | G68: =SUMIF('Committed Costs '!C:C,B68,'Committed Costs '!G:G) -> 0 | H68: =SUMIF('Change Orders'!F:F,'Project Detail'!B68,'Change Orders'!E:E) -> 0 | I68: =SUMIF(Invoices!B:B,B68,Invoices!G:G) -> 0 | J68: 0 | K68: =I68-J68 -> 0 | L68: =+M68-G68 -> 0 | M68: =IF((F68+H68)>G68,F68+H68,G68) -> 0 | N68: =F68-M68 -> 0 | Q68: =M68-K68 -> 0 | U68: =S68+T68+#REF! -> #REF! | Z68: =W68+X68+Y68 -> 0 | AB68: =U68+Z68 -> #REF! | AD68: =Q68-AB68 -> #REF!
B69: 301-6 | D69: N/A | E69: VIP - Cocktail Table | F69: =5300-5300 -> 0 | G69: =SUMIF('Committed Costs '!C:C,B69,'Committed Costs '!G:G) -> 0 | H69: =SUMIF('Change Orders'!F:F,'Project Detail'!B69,'Change Orders'!E:E) -> 0 | I69: =SUMIF(Invoices!B:B,B69,Invoices!G:G) -> 0 | J69: 0 | K69: =I69-J69 -> 0 | L69: =+M69-G69 -> 0 | M69: =IF((F69+H69)>G69,F69+H69,G69) -> 0 | N69: =F69-M69 -> 0 | Q69: =M69-K69 -> 0 | U69: =S69+T69+#REF! -> #REF! | Z69: =W69+X69+Y69 -> 0 | AB69: =U69+Z69 -> #REF! | AD69: =Q69-AB69 -> #REF!
B70: 301-7 | D70: N/A | E70: VIP - Stools | F70: =12000-12000 -> 0 | G70: =SUMIF('Committed Costs '!C:C,B70,'Committed Costs '!G:G) -> 0 | H70: =SUMIF('Change Orders'!F:F,'Project Detail'!B70,'Change Orders'!E:E) -> 0 | I70: =SUMIF(Invoices!B:B,B70,Invoices!G:G) -> 0 | J70: 0 | K70: =I70-J70 -> 0 | L70: =+M70-G70 -> 0 | M70: =IF((F70+H70)>G70,F70+H70,G70) -> 0 | N70: =F70-M70 -> 0 | Q70: =M70-K70 -> 0 | U70: =S70+T70+#REF! -> #REF! | Z70: =W70+X70+Y70 -> 0 | AB70: =U70+Z70 -> #REF! | AD70: =Q70-AB70 -> #REF!
B71: 301-8 | D71: N/A | E71: VIP - Coffee Tables | F71: =12000-12000 -> 0 | G71: =SUMIF('Committed Costs '!C:C,B71,'Committed Costs '!G:G) -> 0 | H71: =SUMIF('Change Orders'!F:F,'Project Detail'!B71,'Change Orders'!E:E) -> 0 | I71: =SUMIF(Invoices!B:B,B71,Invoices!G:G) -> 0 | J71: 0 | K71: =I71-J71 -> 0 | L71: =+M71-G71 -> 0 | M71: =IF((F71+H71)>G71,F71+H71,G71) -> 0 | N71: =F71-M71 -> 0 | Q71: =M71-K71 -> 0 | U71: =S71+T71+#REF! -> #REF! | Z71: =W71+X71+Y71 -> 0 | AB71: =U71+Z71 -> #REF! | AD71: =Q71-AB71 -> #REF!
B72: 301-9 | D72: N/A | E72: VIP - Hightop | F72: =5000-5000 -> 0 | G72: =SUMIF('Committed Costs '!C:C,B72,'Committed Costs '!G:G) -> 0 | H72: =SUMIF('Change Orders'!F:F,'Project Detail'!B72,'Change Orders'!E:E) -> 0 | I72: =SUMIF(Invoices!B:B,B72,Invoices!G:G) -> 0 | J72: 0 | K72: =I72-J72 -> 0 | L72: =+M72-G72 -> 0 | M72: =IF((F72+H72)>G72,F72+H72,G72) -> 0 | N72: =F72-M72 -> 0 | Q72: =M72-K72 -> 0 | U72: =S72+T72+#REF! -> #REF! | Z72: =W72+X72+Y72 -> 0 | AB72: =U72+Z72 -> #REF! | AD72: =Q72-AB72 -> #REF!
B73: 301-10 | D73: N/A | E73: VIP - Sofa | F73: =12000-12000 -> 0 | G73: =SUMIF('Committed Costs '!C:C,B73,'Committed Costs '!G:G) -> 0 | H73: =SUMIF('Change Orders'!F:F,'Project Detail'!B73,'Change Orders'!E:E) -> 0 | I73: =SUMIF(Invoices!B:B,B73,Invoices!G:G) -> 0 | J73: 0 | K73: =I73-J73 -> 0 | L73: =+M73-G73 -> 0 | M73: =IF((F73+H73)>G73,F73+H73,G73) -> 0 | N73: =F73-M73 -> 0 | Q73: =M73-K73 -> 0 | U73: =S73+T73+#REF! -> #REF! | Z73: =W73+X73+Y73 -> 0 | AB73: =U73+Z73 -> #REF! | AD73: =Q73-AB73 -> #REF!
B74: 301-11 | D74: N/A | E74: VIP - Banquet | F74: =21000-21000 -> 0 | G74: =SUMIF('Committed Costs '!C:C,B74,'Committed Costs '!G:G) -> 0 | H74: =SUMIF('Change Orders'!F:F,'Project Detail'!B74,'Change Orders'!E:E) -> 0 | I74: =SUMIF(Invoices!B:B,B74,Invoices!G:G) -> 0 | J74: 0 | K74: =I74-J74 -> 0 | L74: =+M74-G74 -> 0 | M74: =IF((F74+H74)>G74,F74+H74,G74) -> 0 | N74: =F74-M74 -> 0 | Q74: =M74-K74 -> 0 | U74: =S74+T74+#REF! -> #REF! | Z74: =W74+X74+Y74 -> 0 | AB74: =U74+Z74 -> #REF! | AD74: =Q74-AB74 -> #REF!
B75: 301-12 | D75: N/A | E75: Artist Lounge | F75: =15000-15000 -> 0 | G75: =SUMIF('Committed Costs '!C:C,B75,'Committed Costs '!G:G) -> 0 | H75: =SUMIF('Change Orders'!F:F,'Project Detail'!B75,'Change Orders'!E:E) -> 0 | I75: =SUMIF(Invoices!B:B,B75,Invoices!G:G) -> 0 | J75: 0 | K75: =I75-J75 -> 0 | L75: =+M75-G75 -> 0 | M75: =IF((F75+H75)>G75,F75+H75,G75) -> 0 | N75: =F75-M75 -> 0 | Q75: =M75-K75 -> 0 | U75: =S75+T75+#REF! -> #REF! | Z75: =W75+X75+Y75 -> 0 | AB75: =U75+Z75 -> #REF! | AD75: =Q75-AB75 -> #REF!
B76: 301-13 | D76: N/A | E76: Dressing Room | F76: =15000-15000 -> 0 | G76: =SUMIF('Committed Costs '!C:C,B76,'Committed Costs '!G:G) -> 0 | H76: =SUMIF('Change Orders'!F:F,'Project Detail'!B76,'Change Orders'!E:E) -> 0 | I76: =SUMIF(Invoices!B:B,B76,Invoices!G:G) -> 0 | J76: 0 | K76: =I76-J76 -> 0 | L76: =+M76-G76 -> 0 | M76: =IF((F76+H76)>G76,F76+H76,G76) -> 0 | N76: =F76-M76 -> 0 | Q76: =M76-K76 -> 0 | U76: =S76+T76+#REF! -> #REF! | Z76: =W76+X76+Y76 -> 0 | AB76: =U76+Z76 -> #REF! | AD76: =Q76-AB76 -> #REF!
B77: 301-14 | D77: N/A | E77: Rugs | F77: =5000-5000 -> 0 | G77: =SUMIF('Committed Costs '!C:C,B77,'Committed Costs '!G:G) -> 0 | H77: =SUMIF('Change Orders'!F:F,'Project Detail'!B77,'Change Orders'!E:E) -> 0 | I77: =SUMIF(Invoices!B:B,B77,Invoices!G:G) -> 0 | J77: 0 | K77: =I77-J77 -> 0 | L77: =+M77-G77 -> 0 | M77: =IF((F77+H77)>G77,F77+H77,G77) -> 0 | N77: =F77-M77 -> 0 | Q77: =M77-K77 -> 0 | U77: =S77+T77+#REF! -> #REF! | Z77: =W77+X77+Y77 -> 0 | AB77: =U77+Z77 -> #REF! | AD77: =Q77-AB77 -> #REF!
B78: 301-15 | D78: N/A | E78: Catering Room Chairs | F78: =8000-6820.3-1179.7 -> 0 | G78: =SUMIF('Committed Costs '!C:C,B78,'Committed Costs '!G:G) -> 0 | H78: =SUMIF('Change Orders'!F:F,'Project Detail'!B78,'Change Orders'!E:E) -> 0 | I78: =SUMIF(Invoices!B:B,B78,Invoices!G:G) -> 0 | J78: 0 | K78: =I78-J78 -> 0 | L78: =+M78-G78 -> 0 | M78: 0 | N78: =F78-M78 -> 0 | Q78: =M78-K78 -> 0 | U78: =S78+T78+#REF! -> #REF! | Z78: =W78+X78+Y78 -> 0 | AB78: =U78+Z78 -> #REF! | AD78: =Q78-AB78 -> #REF!
B79: 301-16 | D79: N/A | E79: Catering Room Tables | F79: =4000-4000 -> 0 | G79: =SUMIF('Committed Costs '!C:C,B79,'Committed Costs '!G:G) -> 0 | H79: =SUMIF('Change Orders'!F:F,'Project Detail'!B79,'Change Orders'!E:E) -> 0 | I79: =SUMIF(Invoices!B:B,B79,Invoices!G:G) -> 0 | J79: 0 | K79: =I79-J79 -> 0 | L79: =+M79-G79 -> 0 | M79: 0 | N79: =F79-M79 -> 0 | Q79: =M79-K79 -> 0 | U79: =S79+T79+#REF! -> #REF! | Z79: =W79+X79+Y79 -> 0 | AB79: =U79+Z79 -> #REF! | AD79: =Q79-AB79 -> #REF!
B80: 301-17 | D80: Multiple Vendors | E80: Box & VIP Seats | F80: ='Budget Summary'!#REF! -> #REF! | G80: =SUMIF('Committed Costs '!C:C,B80,'Committed Costs '!G:G) -> 0 | H80: =SUMIF('Change Orders'!F:F,'Project Detail'!B80,'Change Orders'!E:E) -> 0 | I80: =SUMIF(Invoices!B:B,B80,Invoices!G:G) -> 0 | J80: 0 | K80: =I80-J80 -> 0 | L80: =+M80-G80 -> #REF! | M80: =IF((F80+H80)>G80,F80+H80,G80) -> #REF! | N80: =F80-M80 -> #REF! | Q80: =M80-K80 -> #REF! | U80: =S80+T80 -> 0 | Z80: =W80+X80+Y80 -> 0 | AB80: =U80+Z80 -> 0 | AD80: =Q80-AB80 -> #REF!
B81: 301-18 | F81: 0 | G81: =SUMIF('Committed Costs '!C:C,B81,'Committed Costs '!G:G) -> 0 | H81: =SUMIF('Change Orders'!F:F,'Project Detail'!B81,'Change Orders'!E:E) -> 0 | I81: =SUMIF(Invoices!B:B,B81,Invoices!G:G) -> 0 | J81: 0 | K81: =I81-J81 -> 0 | L81: =+M81-G81 -> 0 | M81: =IF((F81+H81)>G81,F81+H81,G81) -> 0 | N81: =F81-M81 -> 0
C82: 301 | E82: Total Seating | F82: =SUM(F64:F81) -> #REF! | G82: =SUM(G64:G81) -> 0 | H82: =SUM(H64:H81) -> 0 | I82: =SUM(I64:I81) -> 0 | J82: =SUM(J64:J81) -> 0 | K82: =SUM(K64:K81) -> 0 | L82: =SUM(L64:L81) -> #REF! | M82: =SUM(M64:M81) -> #REF! | N82: =SUM(N64:N81) -> #REF! | Q82: =SUM(Q64:Q80) -> #REF! | S82: =SUM(S64:S80) -> 0 | T82: =SUM(T64:T80) -> 0 | U82: =U64+U80 -> 0 | W82: =SUM(W64:W80) -> 0 | X82: =SUM(X64:X80) -> 0 | Y82: =SUM(Y64:Y80) -> 0 | Z82: =SUM(Z64:Z80) -> 0 | AB82: =AB64+AB80 -> 0 | AD82: =AD64+AD80 -> #REF!
B83: 302 | D83: Concessions
B84: 302-1 | D84: TriMark | E84: Kitchen and Bars | F84: ='Budget Summary'!D50 -> 1317000 | G84: =SUMIF('Committed Costs '!C:C,B84,'Committed Costs '!G:G) -> 0 | H84: =SUMIF('Change Orders'!F:F,'Project Detail'!B84,'Change Orders'!E:E) -> 0 | I84: =SUMIF(Invoices!B:B,B84,Invoices!G:G) -> 0 | J84: 0 | K84: =I84-J84 -> 0 | L84: =+M84-G84 -> 0 | M84: =G84 -> 0 | N84: =F84-M84 -> 1317000 | Q84: =M84-K84 -> 0 | U84: =S84+T84 -> 0 | Z84: =W84+X84+Y84 -> 0 | AB84: =U84+Z84 -> 0 | AD84: =Q84-AB84 -> 0
B85: 302-2 | D85: TBD | E85: Miscellaneous Equipment (POS) | F85: ='Budget Summary'!D51 -> 0 | G85: =SUMIF('Committed Costs '!C:C,B85,'Committed Costs '!G:G) -> 0 | H85: =SUMIF('Change Orders'!F:F,'Project Detail'!B85,'Change Orders'!E:E) -> 0 | I85: =SUMIF(Invoices!B:B,B85,Invoices!G:G) -> 0 | J85: 0 | K85: =I85-J85 -> 0 | L85: =+M85-G85 -> 0 | M85: =G85 -> 0 | N85: =F85-M85 -> 0 | Q85: =M85-K85 -> 0 | U85: =S85+T85 -> 0 | Z85: =W85+X85+Y85 -> 0 | AB85: =U85+Z85 -> 0 | AD85: =Q85-AB85 -> 0
B86: 302-3 | D86: TBD | E86: Portable Bars | F86: ='Budget Summary'!#REF! -> #REF! | G86: =SUMIF('Committed Costs '!C:C,B86,'Committed Costs '!G:G) -> 0 | H86: =SUMIF('Change Orders'!F:F,'Project Detail'!B86,'Change Orders'!E:E) -> 0 | I86: =SUMIF(Invoices!B:B,B86,Invoices!G:G) -> 0 | J86: 0 | K86: =I86-J86 -> 0 | L86: =+M86-G86 -> 0 | M86: 0 | N86: =F86-M86 -> #REF! | Q86: =M86-K86 -> 0 | U86: =S86+T86 -> 0 | Z86: =W86+X86+Y86 -> 0 | AB86: =U86+Z86 -> 0 | AD86: =Q86-AB86 -> 0
B87: 302-4 | F87: 0 | G87: =SUMIF('Committed Costs '!C:C,B87,'Committed Costs '!G:G) -> 0 | H87: =SUMIF('Change Orders'!F:F,'Project Detail'!B87,'Change Orders'!E:E) -> 0 | I87: =SUMIF(Invoices!B:B,B87,Invoices!G:G) -> 0 | J87: 0 | K87: =I87-J87 -> 0 | L87: =+M87-G87 -> 0 | M87: =IF((F87+H87)>G87,F87+H87,G87) -> 0 | N87: =F87-M87 -> 0 | Q87: =M87-K87 -> 0 | U87: =S87+T87 -> 0 | Z87: =W87+X87+Y87 -> 0 | AB87: =U87+Z87 -> 0 | AD87: =Q87-AB87 -> 0
C88: 302 | E88: Total Concession | F88: =SUM(F84:F87) -> #REF! | G88: =SUM(G84:G87) -> 0 | H88: =SUM(H84:H87) -> 0 | I88: =SUM(I84:I87) -> 0 | J88: =SUM(J84:J87) -> 0 | K88: =SUM(K84:K87) -> 0 | L88: =SUM(L84:L87) -> 0 | M88: =SUM(M84:M87) -> 0 | N88: =SUM(N84:N87) -> #REF! | Q88: =SUM(Q84:Q87) -> 0 | S88: =SUM(S84:S87) -> 0 | T88: =SUM(T84:T87) -> 0 | U88: =SUM(U84:U87) -> 0 | W88: =SUM(W84:W87) -> 0 | X88: =SUM(X84:X87) -> 0 | Y88: =SUM(Y84:Y87) -> 0 | Z88: =SUM(Z84:Z87) -> 0 | AB88: =SUM(AB84:AB87) -> 0 | AD88: =SUM(AD84:AD87) -> 0
B89: 303 | D89: Phone & Data Systems
B90: 303-1 | D90: Multiple Vendors | E90: CCTV | F90: ='Budget Summary'!D52 -> 220000 | G90: =SUMIF('Committed Costs '!C:C,B90,'Committed Costs '!G:G) -> 0 | H90: =SUMIF('Change Orders'!F:F,'Project Detail'!B90,'Change Orders'!E:E) -> 0 | I90: =SUMIF(Invoices!B:B,B90,Invoices!G:G) -> 0 | J90: 0 | K90: =I90-J90 -> 0 | L90: =+M90-G90 -> 220000 | M90: =IF((F90+H90)>G90,F90+H90,G90) -> 220000 | N90: =F90-M90 -> 0 | Q90: =M90-K90 -> 220000 | U90: =S90+T90 -> 0 | Z90: =W90+X90+Y90 -> 0 | AB90: =U90+Z90 -> 0 | AD90: =Q90-AB90 -> 220000
B91: 303-2 | D91: Entisys, Insight, Multi-Link | E91: Data /Wifi Systems | F91: ='Budget Summary'!D53 -> 200000 | G91: =SUMIF('Committed Costs '!C:C,B91,'Committed Costs '!G:G) -> 0 | H91: =SUMIF('Change Orders'!F:F,'Project Detail'!B91,'Change Orders'!E:E) -> 0 | I91: =SUMIF(Invoices!B:B,B91,Invoices!G:G) -> 0 | J91: 0 | K91: =I91-J91 -> 0 | L91: =+M91-G91 -> 200000 | M91: =IF((F91+H91)>G91,F91+H91,G91) -> 200000 | N91: =F91-M91 -> 0 | Q91: =M91-K91 -> 200000 | U91: =S91+T91 -> 0 | Z91: =W91+X91+Y91 -> 0 | AB91: =U91+Z91 -> 0 | AD91: =Q91-AB91 -> 200000
C92: 303 | E92: Total Phone & Data | F92: =SUM(F90:F91) -> 420000 | G92: =SUM(G90:G91) -> 0 | H92: =SUM(H90:H91) -> 0 | I92: =SUM(I90:I91) -> 0 | J92: =SUM(J90:J91) -> 0 | K92: =SUM(K90:K91) -> 0 | L92: =SUM(L90:L91) -> 420000 | M92: =SUM(M90:M91) -> 420000 | N92: =SUM(N90:N91) -> 0 | Q92: =SUM(Q90:Q91) -> 420000 | S92: =SUM(S90:S91) -> 0 | T92: =SUM(T90:T91) -> 0 | U92: =SUM(U90:U91) -> 0 | W92: =SUM(W90:W91) -> 0 | X92: =SUM(X90:X91) -> 0 | Y92: =SUM(Y90:Y91) -> 0 | Z92: =SUM(Z90:Z91) -> 0 | AB92: =SUM(AB90:AB91) -> 0 | AD92: =SUM(AD90:AD91) -> 420000
B93: 304 | D93: Office Furniture
B94: 304-1 | D94: Pivot / YE Co. | E94: Office Furniture (From Furniture Tracker) | F94: ='Budget Summary'!D54 -> 65000 | G94: =SUMIF('Committed Costs '!C:C,B94,'Committed Costs '!G:G) -> 0 | H94: =SUMIF('Change Orders'!F:F,'Project Detail'!B94,'Change Orders'!E:E) -> 0 | I94: =SUMIF(Invoices!B:B,B94,Invoices!G:G) -> 0 | J94: 0 | K94: =I94-J94 -> 0 | L94: =+M94-G94 -> 0 | M94: =G94 -> 0 | N94: =F94-M94 -> 65000 | Q94: =M94-K94 -> 0 | U94: =S94+T94 -> 0 | Z94: =W94+X94+Y94 -> 0 | AB94: =U94+Z94 -> 0 | AD94: =Q94-AB94 -> 0
B95: 304-2 | D95: N/A | E95: Administration Refrigerator | F95: =600-600 -> 0 | G95: =SUMIF('Committed Costs '!C:C,B95,'Committed Costs '!G:G) -> 0 | H95: =SUMIF('Change Orders'!F:F,'Project Detail'!B95,'Change Orders'!E:E) -> 0 | I95: =SUMIF(Invoices!B:B,B95,Invoices!G:G) -> 0 | J95: 0 | K95: =I95-J95 -> 0 | L95: =+M95-G95 -> 0 | M95: =IF((F95+H95)>G95,F95+H95,G95) -> 0 | N95: =F95-M95 -> 0 | Q95: =G95-K95 -> 0 | U95: =S95+T95+#REF! -> #REF! | Z95: =W95+X95+Y95 -> 0 | AB95: =U95+Z95 -> #REF!
B96: 304-3 | D96: N/A | E96: Desks-Production | F96: =1000-1000 -> 0 | G96: =SUMIF('Committed Costs '!C:C,B96,'Committed Costs '!G:G) -> 0 | H96: =SUMIF('Change Orders'!F:F,'Project Detail'!B96,'Change Orders'!E:E) -> 0 | I96: =SUMIF(Invoices!B:B,B96,Invoices!G:G) -> 0 | J96: 0 | K96: =I96-J96 -> 0 | L96: =+M96-G96 -> 0 | M96: =IF((F96+H96)>G96,F96+H96,G96) -> 0 | N96: =F96-M96 -> 0 | Q96: =G96-K96 -> 0 | U96: =S96+T96+#REF! -> #REF! | Z96: =W96+X96+Y96 -> 0 | AB96: =U96+Z96 -> #REF!
B97: 304-4 | D97: N/A | E97: Desk Chairs-Production | F97: =800-800 -> 0 | G97: =SUMIF('Committed Costs '!C:C,B97,'Committed Costs '!G:G) -> 0 | H97: =SUMIF('Change Orders'!F:F,'Project Detail'!B97,'Change Orders'!E:E) -> 0 | I97: =SUMIF(Invoices!B:B,B97,Invoices!G:G) -> 0 | J97: 0 | K97: =I97-J97 -> 0 | L97: =+M97-G97 -> 0 | M97: =IF((F97+H97)>G97,F97+H97,G97) -> 0 | N97: =F97-M97 -> 0 | Q97: =G97-K97 -> 0 | U97: =S97+T97+#REF! -> #REF! | Z97: =W97+X97+Y97 -> 0 | AB97: =U97+Z97 -> #REF!
B98: 304-5 | D98: N/A | E98: File Cabinets-Production | F98: =800-800 -> 0 | G98: =SUMIF('Committed Costs '!C:C,B98,'Committed Costs '!G:G) -> 0 | H98: =SUMIF('Change Orders'!F:F,'Project Detail'!B98,'Change Orders'!E:E) -> 0 | I98: =SUMIF(Invoices!B:B,B98,Invoices!G:G) -> 0 | J98: 0 | K98: =I98-J98 -> 0 | L98: =+M98-G98 -> 0 | M98: =IF((F98+H98)>G98,F98+H98,G98) -> 0 | N98: =F98-M98 -> 0 | Q98: =G98-K98 -> 0 | U98: =S98+T98+#REF! -> #REF! | Z98: =W98+X98+Y98 -> 0 | AB98: =U98+Z98 -> #REF!
C99: 304 | E99: Total Office Furniture | F99: =SUM(F94:F98) -> 65000 | G99: =SUM(G94:G98) -> 0 | H99: =SUM(H94:H98) -> 0 | I99: =SUM(I94:I98) -> 0 | J99: =SUM(J94:J98) -> 0 | K99: =SUM(K94:K98) -> 0 | L99: =SUM(L94:L98) -> 0 | M99: =SUM(M94:M98) -> 0 | N99: =SUM(N94:N98) -> 65000 | Q99: =SUM(Q94:Q98) -> 0 | S99: =SUM(S94:S98) -> 0 | T99: =SUM(T94:T98) -> 0 | U99: =U94 -> 0 | W99: =SUM(W94:W98) -> 0 | X99: =SUM(X94:X98) -> 0 | Y99: =SUM(Y94:Y98) -> 0 | Z99: =SUM(Z94:Z98) -> 0 | AB99: =AB94 -> 0 | AD99: =SUM(AD94:AD98) -> 0
B100: 305 | D100: Signage/Graphics
B101: 305-1 | D101: TBD | E101: Exterior Signage / Wayfinding | F101: 0 | G101: =SUMIF('Committed Costs '!C:C,B101,'Committed Costs '!G:G) -> 0 | H101: =SUMIF('Change Orders'!F:F,'Project Detail'!B101,'Change Orders'!E:E) -> 0 | I101: =SUMIF(Invoices!B:B,B101,Invoices!G:G) -> 0 | J101: 0 | K101: =I101-J101 -> 0 | L101: =+M101-G101 -> 0 | M101: 0 | N101: =F101-M101 -> 0 | Q101: =M101-K101 -> 0 | U101: =S101+T101 -> 0 | Z101: =W101+X101+Y101 -> 0 | AB101: =U101+Z101 -> 0 | AD101: =Q101-AB101 -> 0
B102: 305-2 | D102: TBD | E102: Interior Art & Décor "Warehouse Scope" | F102: 0 | G102: =SUMIF('Committed Costs '!C:C,B102,'Committed Costs '!G:G) -> 0 | H102: =SUMIF('Change Orders'!F:F,'Project Detail'!B102,'Change Orders'!E:E) -> 0 | I102: =SUMIF(Invoices!B:B,B102,Invoices!G:G) -> 0 | J102: 0 | K102: =I102-J102 -> 0 | L102: =+M102-G102 -> 0 | M102: =G102 -> 0 | N102: =F102-M102 -> 0 | Q102: =M102-K102 -> 0 | U102: =S102+T102 -> 0 | Z102: =W102+X102+Y102 -> 0 | AB102: =U102+Z102 -> 0 | AD102: =Q102-AB102 -> 0
B103: 305-3 | F103: =35000-35000 -> 0 | G103: =SUMIF('Committed Costs '!C:C,B103,'Committed Costs '!G:G) -> 0 | H103: =SUMIF('Change Orders'!F:F,'Project Detail'!B103,'Change Orders'!E:E) -> 0 | I103: =SUMIF(Invoices!B:B,B103,Invoices!G:G) -> 0 | J103: 0 | K103: =I103-J103 -> 0 | L103: =+M103-G103 -> 0 | M103: =IF((F103+H103)>G103,F103+H103,G103) -> 0 | N103: =F103-M103 -> 0 | Q103: =M103-K103 -> 0 | U103: =S103+T103 -> 0 | Z103: =W103+X103+Y103 -> 0 | AB103: =U103+Z103 -> 0 | AD103: =Q103-AB103 -> 0
B104: 305-4 | F104: =1000-1000 -> 0 | G104: =SUMIF('Committed Costs '!C:C,B104,'Committed Costs '!G:G) -> 0 | H104: =SUMIF('Change Orders'!F:F,'Project Detail'!B104,'Change Orders'!E:E) -> 0 | I104: =SUMIF(Invoices!B:B,B104,Invoices!G:G) -> 0 | J104: 0 | K104: =I104-J104 -> 0 | L104: =+M104-G104 -> 0 | M104: =IF((F104+H104)>G104,F104+H104,G104) -> 0 | N104: =F104-M104 -> 0 | Q104: =M104-K104 -> 0 | U104: =S104+T104 -> 0 | Z104: =W104+X104+Y104 -> 0 | AB104: =U104+Z104 -> 0 | AD104: =Q104-AB104 -> 0
B105: 305-5 | F105: =20000-20000 -> 0 | G105: =SUMIF('Committed Costs '!C:C,B105,'Committed Costs '!G:G) -> 0 | H105: =SUMIF('Change Orders'!F:F,'Project Detail'!B105,'Change Orders'!E:E) -> 0 | I105: =SUMIF(Invoices!B:B,B105,Invoices!G:G) -> 0 | J105: 0 | K105: =I105-J105 -> 0 | L105: =+M105-G105 -> 0 | M105: =IF((F105+H105)>G105,F105+H105,G105) -> 0 | N105: =F105-M105 -> 0 | Q105: =M105-K105 -> 0 | U105: =S105+T105 -> 0 | Z105: =W105+X105+Y105 -> 0 | AB105: =U105+Z105 -> 0 | AD105: =Q105-AB105 -> 0
B106: 305-6 | F106: =1500-1500 -> 0 | G106: =SUMIF('Committed Costs '!C:C,B106,'Committed Costs '!G:G) -> 0 | H106: =SUMIF('Change Orders'!F:F,'Project Detail'!B106,'Change Orders'!E:E) -> 0 | I106: =SUMIF(Invoices!B:B,B106,Invoices!G:G) -> 0 | J106: 0 | K106: =I106-J106 -> 0 | L106: =+M106-G106 -> 0 | M106: =IF((F106+H106)>G106,F106+H106,G106) -> 0 | N106: =F106-M106 -> 0 | Q106: =M106-K106 -> 0 | U106: =S106+T106 -> 0 | Z106: =W106+X106+Y106 -> 0 | AB106: =U106+Z106 -> 0 | AD106: =Q106-AB106 -> 0
B107: 305-7 | F107: =1500-1500 -> 0 | G107: =SUMIF('Committed Costs '!C:C,B107,'Committed Costs '!G:G) -> 0 | H107: =SUMIF('Change Orders'!F:F,'Project Detail'!B107,'Change Orders'!E:E) -> 0 | I107: =SUMIF(Invoices!B:B,B107,Invoices!G:G) -> 0 | J107: 0 | K107: =I107-J107 -> 0 | L107: =+M107-G107 -> 0 | M107: =IF((F107+H107)>G107,F107+H107,G107) -> 0 | N107: =F107-M107 -> 0 | Q107: =M107-K107 -> 0 | U107: =S107+T107 -> 0 | Z107: =W107+X107+Y107 -> 0 | AB107: =U107+Z107 -> 0 | AD107: =Q107-AB107 -> 0
B108: 305-8 | F108: =10000-10000 -> 0 | G108: =SUMIF('Committed Costs '!C:C,B108,'Committed Costs '!G:G) -> 0 | H108: =SUMIF('Change Orders'!F:F,'Project Detail'!B108,'Change Orders'!E:E) -> 0 | I108: =SUMIF(Invoices!B:B,B108,Invoices!G:G) -> 0 | J108: 0 | K108: =I108-J108 -> 0 | L108: =+M108-G108 -> 0 | M108: =IF((F108+H108)>G108,F108+H108,G108) -> 0 | N108: =F108-M108 -> 0 | Q108: =M108-K108 -> 0 | U108: =S108+T108 -> 0 | Z108: =W108+X108+Y108 -> 0 | AB108: =U108+Z108 -> 0 | AD108: =Q108-AB108 -> 0
...

Sheet Committed Costs 
B2: Committed Costs
B3: Executed Date | C3: Cost Code | D3: Vendor | E3: Description | F3: P.O. Number | G3: Contract Value | H3: Notes
F9: Total Commitments | G9: =SUBTOTAL(9,G4:G6) -> 0
G10: =G9='Project At-a-Glance'!D25 -> TRUE

Sheet Invoices
B2: Invoices
B3: Cost Code | C3: Vendor | D3: Description | E3: Invoice # | F3: Invoice Date | G3: Invoice Amount | H3: GL Period | I3: Notes | J3: Payment Status
B5: 2022 Invoices
F10: March Invoices Total | G10: =SUBTOTAL(9,G6:G9) -> 0
F13: INVOICES GRAND TOTAL | G13: =SUM(G10) -> 0
G14: =G13='Project At-a-Glance'!E25 -> TRUE

Sheet Change Orders
B2: Date Issued | C2: C.O. Number | D2: Vendor | E2: Amount | F2: Cost Code | G2: Description | H2: Notes
D29: Total Change Orders | E29: =SUM(E3:E28) -> 0

Sheet Contingency
B2: Date | C2: Cost Code | D2: Vendor | E2: Description | F2: Amount Applied | G2: Remaining Balance | H2: Notes
B4: March 2020 Contingency | J4: Contingency
B5: 43921 | C5: N/A | D5: N/A | E5: Initial Contingency Amount | F5: 0 | G5: =+J5-F5 -> 8098599.2 | J5: ='Project Detail'!F170 -> 8098599.2
E6: March Contingency Totals | F6: =SUBTOTAL(9,F5) -> 0 | G6: =G5 -> 8098599.2
E9: CONTINGENCY TOTALS | F9: =SUM(F6) -> 0 | G9: =G6 -> 8098599.2

Sheet Risk Report
A1: Risk Report
A3: Requestor | C3: Item | E3: High | G3: Expected Settlement Value | I3: Low | K3: Notes
A4: Project Team
A5: Project Team
A6: Project Team
A7: Project Team
A8: Project Team
A9: Project Team
A10: Project Team
A11: Project Team
A12: Project Team
A13: Project Team
A14: Project Team
E15: =SUM(E4:E14) -> 0 | G15: =SUM(G4:G14) -> 0 | I15: =SUM(I4:I14) -> 0
C19: Current Sources (as of 01/31/2023) | E19: Remaining Contingency | G19: =Contingency!G9 -> 8098599.2
E21: Contingency Balance | G21: =G19-G15 -> 8098599.2
E23: Exposure | G23: =IF(G15>G19,G19-G15,0) -> 0
C26: *Sources reflect over budget items pending resolution.
